Workbook

Sheet PAINEL
A1: BIORENAL - PAINEL FINANCEIRO 2026
A2: Centro de Hemodiálise de Santa Inês - MA | dados da aba EXTRATO e RATEIOS
A4: SALDO EM CONTA | C4: TOTAL DE ENTRADAS | E4: TOTAL DE SAÍDAS
A5: =CADASTROS!$B$4+SUM(EXTRATO!$J$2:$J$3000)+SUM(EXTRATO!$M$2:$M$3000)-SUM(EXTRATO!$K$2:$K$3000)-SUM(EXTRATO!$L$2:$L$3000) -> 480714.13 | C5: =SUM(EXTRATO!$J$2:$J$3000) -> 5790013.3 | E5: =SUM(EXTRATO!$K$2:$K$3000) -> 5861088.3
A7: SALDO DA APLICAÇÃO(SEM RENDIMENTOS) | C7: VALOR RESGATADO NO ANO | E7: TOTAL DE DESPESAS CLASSIFICADAS
A8: =SUM(EXTRATO!$L$2:$L$3000)-SUM(EXTRATO!$M$850:M3000) -> 125496.54 | C8: =SUM(EXTRATO!$M$2:$M$3000) -> 1051789.1 | E8: =ANÁLISES!$N$19 -> 4881177.6
A11: SITUAÇÃO DO TRABALHO
A12: Movimentos bancários registrados | C12: =COUNT(EXTRATO!$C$2:$C$3000) -> 1061
A13: Movimentos com rateio OK | C13: =COUNTIF(EXTRATO!$Q$2:$Q$3000,"RATEIO OK") -> 895
A14: Movimentos NÃO classificados | C14: =COUNTIF(EXTRATO!$Q$2:$Q$3000,"NÃO CLASSIFICADO")+COUNTIF(EXTRATO!$Q$2:$Q$3000,"PENDENTE DE RATEIO") -> 165
A15: Movimentos com DIVERGÊNCIA de rateio | C15: =COUNTIF(EXTRATO!$Q$2:$Q$3000,"DIVERGÊNCIA") -> 1
A16: % classificado | C16: =IFERROR(C13/C12,0) -> 0.84354383
A17: Linhas de rateio marcadas SUGERIDO (conferir) | C17: =COUNTIF(RATEIOS!$J$2:$J$3142,"SUGERIDO") -> 170
A18: Linhas de rateio PENDENTES (preencher) | C18: =COUNTIF(RATEIOS!$J$2:$J$3142,"PENDENTE")+COUNTIF(RATEIOS!$J$2:$J$3142,"REVISAR") -> 303
A19: Conciliados com o extrato | C19: =COUNTIF(EXTRATO!$R$2:$R$3000,"Conciliado") -> 1028
A20: Valor ainda sem classificação | C20: =SUMPRODUCT((RATEIOS!$D$2:$D$3142="")*1,RATEIOS!$F$2:$F$3142) -> 2117734.8
A22: MAIOR CATEGORIA DE DESPESA (ano)
A23: Categoria | C23: =INDEX(ANÁLISES!$A$7:$A$17,MATCH(MAX(ANÁLISES!$N$7:$N$17),ANÁLISES!$N$7:$N$17,0)) -> DESPESAS COM MATERIAIS PARA HEMODIÁLISE E DEMAIS CUSTOS
A24: Valor | C24: =MAX(ANÁLISES!$N$7:$N$17) -> 1175950.7
A27: COMO USAR
A28: 1. EXTRATO: inclua cada movimento na próxima linha livre e preencha a DATA. O ID é automático; mantenha-o para preservar o vínculo.
A29: 2. RATEIOS: data, mês, valor, histórico, natureza e fornecedor aparecem automaticamente. Preencha CATEGORIA e SUBCATEGORIA.
A30: 3. Para dividir: copie a linha em RATEIOS e use Inserir células copiadas. Mantenha o mesmo ID e ajuste o VALOR de cada parte até fechar com o banco.
A31: 4. PRESTAÇÃO DE CONTAS - escolha o mês no topo. Os valores aparecem automaticamente.
A32: 5. ANÁLISES - visão por categoria, subcategoria, fornecedor e mês. Nada para digitar.
A33: 6. INTEGRIDADE - confira antes de fechar o mês. Tudo deve estar OK.
A34: Automação até BAN-02999 (2.999 movimentos). VALOR e DETALHE podem ser editados; não substitua uma linha automática reservada para outro ID.
A37: LEGENDA
C38: Célula que você preenche
C39: OK / conciliado
C40: Precisa da sua atenção (sugerido, pendente ou a verificar)
C41: Divergência — resolver antes de fechar o mês

Sheet EXTRATO
A1: ID_LANC | B1: ORDEM | C1: DATA | D1: MÊS | E1: TIPO DE PAGAMENTO | F1: TIPO DE MOVIMENTAÇÃO | G1: HISTÓRICO DO BANCO | H1: FORNECEDOR/FAVORECIDO | I1: DOCUMENTO | J1: ENTRADA | K1: SAÍDA | L1: APLICAÇÃO | M1: RESGATE | N1: SALDO ACUMULADO | O1: TOTAL RATEADO | P1: DIFERENÇA | Q1: STATUS DO RATEIO | R1: STATUS DA CONCILIAÇÃO | S1: OBSERVAÇÃO
A2: BAN-00001 | B2: 1 | C2: 46024 | D2: =IF(C2="","",MONTH(C2)) -> 1 | E2: OUTROS | F2: RESGATE | G2: RESGATE BB CDB DI | H2: BANCO DO BRASIL - CDB DI | J2: 0 | K2: 0 | L2: 0 | M2: 8500 | N2: =IF(AND(C2="",J2=0,K2=0,L2=0,M2=0),"",CADASTROS!$B$4+SUM($J$2:J2)+SUM($M$2:M2)-SUM($K$2:K2)-SUM($L$2:L2)) -> 8500 | O2: =IF(A2="","",SUMIF(RATEIOS!$A$2:$A$3142,$A2,RATEIOS!$F$2:$F$3142)) -> 8500 | P2: =IF(A2="","",(J2+K2+L2+M2)-O2) -> 0 | Q2: =IF(AND(J2=0,K2=0,L2=0,M2=0),"",IF(O2=0,"PENDENTE DE RATEIO",IF(ABS(P2)>0.005,"DIVERGÊNCIA",IF(COUNTIF(RATEIOS!$A$2:$A$3142,$A2)-COUNTIFS(RATEIOS!$A$2:$A$3142,$A2,RATEIOS!$D$2:$D$3142,"<>")>0,"NÃO CLASSIFICADO","RATEIO OK")))) -> RATEIO OK | R2: Conciliado
A3: BAN-00002 | B3: 2 | C3: 46024 | D3: =IF(C3="","",MONTH(C3)) -> 1 | E3: OUTROS | F3: RESGATE | G3: RESGATE BB CDB DI | H3: BANCO DO BRASIL - CDB DI | J3: 0 | K3: 0 | L3: 0 | M3: 5.27 | N3: =IF(AND(C3="",J3=0,K3=0,L3=0,M3=0),"",CADASTROS!$B$4+SUM($J$2:J3)+SUM($M$2:M3)-SUM($K$2:K3)-SUM($L$2:L3)) -> 8505.27 | O3: =IF(A3="","",SUMIF(RATEIOS!$A$2:$A$3142,$A3,RATEIOS!$F$2:$F$3142)) -> 5.27 | P3: =IF(A3="","",(J3+K3+L3+M3)-O3) -> 0 | Q3: =IF(AND(J3=0,K3=0,L3=0,M3=0),"",IF(O3=0,"PENDENTE DE RATEIO",IF(ABS(P3)>0.005,"DIVERGÊNCIA",IF(COUNTIF(RATEIOS!$A$2:$A$3142,$A3)-COUNTIFS(RATEIOS!$A$2:$A$3142,$A3,RATEIOS!$D$2:$D$3142,"<>")>0,"NÃO CLASSIFICADO","RATEIO OK")))) -> RATEIO OK | R3: Conciliado
A4: BAN-00003 | B4: 3 | C4: 46024 | D4: =IF(C4="","",MONTH(C4)) -> 1 | E4: TRANSFERÊNCIA | F4: SAÍDA | G4: ANA CLAUDIA A. VARÃO (NF - VARÃO E ALMEIDA - ESSENCIAL PHARMA) - REF. IODETO DE POTÁSSIO | H4: ANA CLAUDIA A. VARÃO | I4: 245 | J4: 0 | K4: 270 | L4: 0 | M4: 0 | N4: =IF(AND(C4="",J4=0,K4=0,L4=0,M4=0),"",CADASTROS!$B$4+SUM($J$2:J4)+SUM($M$2:M4)-SUM($K$2:K4)-SUM($L$2:L4)) -> 8235.27 | O4: =IF(A4="","",SUMIF(RATEIOS!$A$2:$A$3142,$A4,RATEIOS!$F$2:$F$3142)) -> 270 | P4: =IF(A4="","",(J4+K4+L4+M4)-O4) -> 0 | Q4: =IF(AND(J4=0,K4=0,L4=0,M4=0),"",IF(O4=0,"PENDENTE DE RATEIO",IF(ABS(P4)>0.005,"DIVERGÊNCIA",IF(COUNTIF(RATEIOS!$A$2:$A$3142,$A4)-COUNTIFS(RATEIOS!$A$2:$A$3142,$A4,RATEIOS!$D$2:$D$3142,"<>")>0,"NÃO CLASSIFICADO","RATEIO OK")))) -> RATEIO OK | R4: Conciliado
A5: BAN-00004 | B5: 4 | C5: 46024 | D5: =IF(C5="","",MONTH(C5)) -> 1 | E5: BOLETO | F5: SAÍDA | G5: ALLMED PRONEFRO (REF. LINHA ARTERIAL E LINHA VENOSA) 1/3 | H5: ALLMED PRONEFRO | I5: 86260 | J5: 0 | K5: 1300.83 | L5: 0 | M5: 0 | N5: =IF(AND(C5="",J5=0,K5=0,L5=0,M5=0),"",CADASTROS!$B$4+SUM($J$2:J5)+SUM($M$2:M5)-SUM($K$2:K5)-SUM($L$2:L5)) -> 6934.44 | O5: =IF(A5="","",SUMIF(RATEIOS!$A$2:$A$3142,$A5,RATEIOS!$F$2:$F$3142)) -> 1300.83 | P5: =IF(A5="","",(J5+K5+L5+M5)-O5) -> 0 | Q5: =IF(AND(J5=0,K5=0,L5=0,M5=0),"",IF(O5=0,"PENDENTE DE RATEIO",IF(ABS(P5)>0.005,"DIVERGÊNCIA",IF(COUNTIF(RATEIOS!$A$2:$A$3142,$A5)-COUNTIFS(RATEIOS!$A$2:$A$3142,$A5,RATEIOS!$D$2:$D$3142,"<>")>0,"NÃO CLASSIFICADO","RATEIO OK")))) -> RATEIO OK | R5: Conciliado
A6: BAN-00005 | B6: 5 | C6: 46024 | D6: =IF(C6="","",MONTH(C6)) -> 1 | E6: BOLETO | F6: SAÍDA | G6: ALLMED PRONEFRO (REF. LINHA ARTERIAL E LINHA VENOSA) 2/2 | H6: ALLMED PRONEFRO | I6: 85727 | J6: 0 | K6: 1952.72 | L6: 0 | M6: 0 | N6: =IF(AND(C6="",J6=0,K6=0,L6=0,M6=0),"",CADASTROS!$B$4+SUM($J$2:J6)+SUM($M$2:M6)-SUM($K$2:K6)-SUM($L$2:L6)) -> 4981.72 | O6: =IF(A6="","",SUMIF(RATEIOS!$A$2:$A$3142,$A6,RATEIOS!$F$2:$F$3142)) -> 1952.72 | P6: =IF(A6="","",(J6+K6+L6+M6)-O6) -> 0 | Q6: =IF(AND(J6=0,K6=0,L6=0,M6=0),"",IF(O6=0,"PENDENTE DE RATEIO",IF(ABS(P6)>0.005,"DIVERGÊNCIA",IF(COUNTIF(RATEIOS!$A$2:$A$3142,$A6)-COUNTIFS(RATEIOS!$A$2:$A$3142,$A6,RATEIOS!$D$2:$D$3142,"<>")>0,"NÃO CLASSIFICADO","RATEIO OK")))) -> RATEIO OK | R6: Conciliado
A7: BAN-00006 | B7: 6 | C7: 46024 | D7: =IF(C7="","",MONTH(C7)) -> 1 | E7: BOLETO | F7: SAÍDA | G7: OMNIELMASTER HEMOMED (REF. CATETER) 2/2 | H7: OMNIELMASTER HEMOMED | I7: 26229 | J7: 0 | K7: 720 | L7: 0 | M7: 0 | N7: =IF(AND(C7="",J7=0,K7=0,L7=0,M7=0),"",CADASTROS!$B$4+SUM($J$2:J7)+SUM($M$2:M7)-SUM($K$2:K7)-SUM($L$2:L7)) -> 4261.72 | O7: =IF(A7="","",SUMIF(RATEIOS!$A$2:$A$3142,$A7,RATEIOS!$F$2:$F$3142)) -> 720 | P7: =IF(A7="","",(J7+K7+L7+M7)-O7) -> 0 | Q7: =IF(AND(J7=0,K7=0,L7=0,M7=0),"",IF(O7=0,"PENDENTE DE RATEIO",IF(ABS(P7)>0.005,"DIVERGÊNCIA",IF(COUNTIF(RATEIOS!$A$2:$A$3142,$A7)-COUNTIFS(RATEIOS!$A$2:$A$3142,$A7,RATEIOS!$D$2:$D$3142,"<>")>0,"NÃO CLASSIFICADO","RATEIO OK")))) -> RATEIO OK | R7: Conciliado
A8: BAN-00007 | B8: 7 | C8: 46024 | D8: =IF(C8="","",MONTH(C8)) -> 1 | E8: BOLETO | F8: SAÍDA | G8: DIALISE COMÉRCIO (REF. ÁCIDO E ISOLADOR) 2/2 | H8: DIALISE COMERCIO | I8: 11363 | J8: 0 | K8: 1840 | L8: 0 | M8: 0 | N8: =IF(AND(C8="",J8=0,K8=0,L8=0,M8=0),"",CADASTROS!$B$4+SUM($J$2:J8)+SUM($M$2:M8)-SUM($K$2:K8)-SUM($L$2:L8)) -> 2421.72 | O8: =IF(A8="","",SUMIF(RATEIOS!$A$2:$A$3142,$A8,RATEIOS!$F$2:$F$3142)) -> 1840 | P8: =IF(A8="","",(J8+K8+L8+M8)-O8) -> 0 | Q8: =IF(AND(J8=0,K8=0,L8=0,M8=0),"",IF(O8=0,"PENDENTE DE RATEIO",IF(ABS(P8)>0.005,"DIVERGÊNCIA",IF(COUNTIF(RATEIOS!$A$2:$A$3142,$A8)-COUNTIFS(RATEIOS!$A$2:$A$3142,$A8,RATEIOS!$D$2:$D$3142,"<>")>0,"NÃO CLASSIFICADO","RATEIO OK")))) -> RATEIO OK | R8: Conciliado
A9: BAN-00008 | B9: 8 | C9: 46024 | D9: =IF(C9="","",MONTH(C9)) -> 1 | E9: BOLETO | F9: SAÍDA | G9: DIÁLISE COMÉRCIO (REF. ÁCIDO PERACETICO E ISOLADOR) 1/2 | H9: DIALISE COMERCIO | I9: 87 | J9: 0 | K9: 2535 | L9: 0 | M9: 0 | N9: =IF(AND(C9="",J9=0,K9=0,L9=0,M9=0),"",CADASTROS!$B$4+SUM($J$2:J9)+SUM($M$2:M9)-SUM($K$2:K9)-SUM($L$2:L9)) -> -113.28 | O9: =IF(A9="","",SUMIF(RATEIOS!$A$2:$A$3142,$A9,RATEIOS!$F$2:$F$3142)) -> 2535 | P9: =IF(A9="","",(J9+K9+L9+M9)-O9) -> 0 | Q9: =IF(AND(J9=0,K9=0,L9=0,M9=0),"",IF(O9=0,"PENDENTE DE RATEIO",IF(ABS(P9)>0.005,"DIVERGÊNCIA",IF(COUNTIF(RATEIOS!$A$2:$A$3142,$A9)-COUNTIFS(RATEIOS!$A$2:$A$3142,$A9,RATEIOS!$D$2:$D$3142,"<>")>0,"NÃO CLASSIFICADO","RATEIO OK")))) -> RATEIO OK | R9: Conciliado
A10: BAN-00009 | B10: 9 | C10: 46024 | D10: =IF(C10="","",MONTH(C10)) -> 1 | E10: OUTROS | F10: RESGATE | G10: BB RENDE FÁCIL | H10: BANCO DO BRASIL - CDB DI | J10: 0 | K10: 0 | L10: 0 | M10: 113.28 | N10: =IF(AND(C10="",J10=0,K10=0,L10=0,M10=0),"",CADASTROS!$B$4+SUM($J$2:J10)+SUM($M$2:M10)-SUM($K$2:K10)-SUM($L$2:L10)) -> 1.8189894e-12 | O10: =IF(A10="","",SUMIF(RATEIOS!$A$2:$A$3142,$A10,RATEIOS!$F$2:$F$3142)) -> 113.28 | P10: =IF(A10="","",(J10+K10+L10+M10)-O10) -> 0 | Q10: =IF(AND(J10=0,K10=0,L10=0,M10=0),"",IF(O10=0,"PENDENTE DE RATEIO",IF(ABS(P10)>0.005,"DIVERGÊNCIA",IF(COUNTIF(RATEIOS!$A$2:$A$3142,$A10)-COUNTIFS(RATEIOS!$A$2:$A$3142,$A10,RATEIOS!$D$2:$D$3142,"<>")>0,"NÃO CLASSIFICADO","RATEIO OK")))) -> RATEIO OK | R10: Conciliado
A11: BAN-00010 | B11: 10 | C11: 46027 | D11: =IF(C11="","",MONTH(C11)) -> 1 | E11: OUTROS | F11: RESGATE | G11: RESGATE BB CDB DI | H11: BANCO DO BRASIL - CDB DI | J11: 0 | K11: 0 | L11: 0 | M11: 2500 | N11: =IF(AND(C11="",J11=0,K11=0,L11=0,M11=0),"",CADASTROS!$B$4+SUM($J$2:J11)+SUM($M$2:M11)-SUM($K$2:K11)-SUM($L$2:L11)) -> 2500 | O11: =IF(A11="","",SUMIF(RATEIOS!$A$2:$A$3142,$A11,RATEIOS!$F$2:$F$3142)) -> 2500 | P11: =IF(A11="","",(J11+K11+L11+M11)-O11) -> 0 | Q11: =IF(AND(J11=0,K11=0,L11=0,M11=0),"",IF(O11=0,"PENDENTE DE RATEIO",IF(ABS(P11)>0.005,"DIVERGÊNCIA",IF(COUNTIF(RATEIOS!$A$2:$A$3142,$A11)-COUNTIFS(RATEIOS!$A$2:$A$3142,$A11,RATEIOS!$D$2:$D$3142,"<>")>0,"NÃO CLASSIFICADO","RATEIO OK")))) -> RATEIO OK | R11: Conciliado
A12: BAN-00011 | B12: 11 | C12: 46027 | D12: =IF(C12="","",MONTH(C12)) -> 1 | E12: OUTROS | F12: RESGATE | G12: RESGATE BB CDB DI | H12: BANCO DO BRASIL - CDB DI | J12: 0 | K12: 0 | L12: 0 | M12: 2.45 | N12: =IF(AND(C12="",J12=0,K12=0,L12=0,M12=0),"",CADASTROS!$B$4+SUM($J$2:J12)+SUM($M$2:M12)-SUM($K$2:K12)-SUM($L$2:L12)) -> 2502.45 | O12: =IF(A12="","",SUMIF(RATEIOS!$A$2:$A$3142,$A12,RATEIOS!$F$2:$F$3142)) -> 2.45 | P12: =IF(A12="","",(J12+K12+L12+M12)-O12) -> 0 | Q12: =IF(AND(J12=0,K12=0,L12=0,M12=0),"",IF(O12=0,"PENDENTE DE RATEIO",IF(ABS(P12)>0.005,"DIVERGÊNCIA",IF(COUNTIF(RATEIOS!$A$2:$A$3142,$A12)-COUNTIFS(RATEIOS!$A$2:$A$3142,$A12,RATEIOS!$D$2:$D$3142,"<>")>0,"NÃO CLASSIFICADO","RATEIO OK")))) -> RATEIO OK | R12: Conciliado
A13: BAN-00012 | B13: 12 | C13: 46027 | D13: =IF(C13="","",MONTH(C13)) -> 1 | E13: BOLETO | F13: SAÍDA | G13: BRANDÃO & BRANDÃO (REF. MATERIAL DE LIMPEZA) 1/1 | H13: BRANDÃO & BRANDÃO | I13: 106199 | J13: 0 | K13: 727 | L13: 0 | M13: 0 | N13: =IF(AND(C13="",J13=0,K13=0,L13=0,M13=0),"",CADASTROS!$B$4+SUM($J$2:J13)+SUM($M$2:M13)-SUM($K$2:K13)-SUM($L$2:L13)) -> 1775.45 | O13: =IF(A13="","",SUMIF(RATEIOS!$A$2:$A$3142,$A13,RATEIOS!$F$2:$F$3142)) -> 727 | P13: =IF(A13="","",(J13+K13+L13+M13)-O13) -> 0 | Q13: =IF(AND(J13=0,K13=0,L13=0,M13=0),"",IF(O13=0,"PENDENTE DE RATEIO",IF(ABS(P13)>0.005,"DIVERGÊNCIA",IF(COUNTIF(RATEIOS!$A$2:$A$3142,$A13)-COUNTIFS(RATEIOS!$A$2:$A$3142,$A13,RATEIOS!$D$2:$D$3142,"<>")>0,"NÃO CLASSIFICADO","RATEIO OK")))) -> RATEIO OK | R13: Conciliado
A14: BAN-00013 | B14: 13 | C14: 46027 | D14: =IF(C14="","",MONTH(C14)) -> 1 | E14: BOLETO | F14: SAÍDA | G14: CASSIANO & CASSINOS CONTABILIDADE | H14: CASSIANO & CASSINOS CONTABILIDADE | I14: 826 | J14: 0 | K14: 1518 | L14: 0 | M14: 0 | N14: =IF(AND(C14="",J14=0,K14=0,L14=0,M14=0),"",CADASTROS!$B$4+SUM($J$2:J14)+SUM($M$2:M14)-SUM($K$2:K14)-SUM($L$2:L14)) -> 257.45 | O14: =IF(A14="","",SUMIF(RATEIOS!$A$2:$A$3142,$A14,RATEIOS!$F$2:$F$3142)) -> 1518 | P14: =IF(A14="","",(J14+K14+L14+M14)-O14) -> 0 | Q14: =IF(AND(J14=0,K14=0,L14=0,M14=0),"",IF(O14=0,"PENDENTE DE RATEIO",IF(ABS(P14)>0.005,"DIVERGÊNCIA",IF(COUNTIF(RATEIOS!$A$2:$A$3142,$A14)-COUNTIFS(RATEIOS!$A$2:$A$3142,$A14,RATEIOS!$D$2:$D$3142,"<>")>0,"NÃO CLASSIFICADO","RATEIO OK")))) -> RATEIO OK | R14: Conciliado
A15: BAN-00014 | B15: 14 | C15: 46028 | D15: =IF(C15="","",MONTH(C15)) -> 1 | E15: PIX | F15: SAÍDA | G15: GAS SÃO JOSE (NF - J V L NOBRE) - GÁS PARA A COPA | H15: GAS SÃO JOSE | I15: 5321 | J15: 0 | K15: 115 | L15: 0 | M15: 0 | N15: =IF(AND(C15="",J15=0,K15=0,L15=0,M15=0),"",CADASTROS!$B$4+SUM($J$2:J15)+SUM($M$2:M15)-SUM($K$2:K15)-SUM($L$2:L15)) -> 142.45 | O15: =IF(A15="","",SUMIF(RATEIOS!$A$2:$A$3142,$A15,RATEIOS!$F$2:$F$3142)) -> 115 | P15: =IF(A15="","",(J15+K15+L15+M15)-O15) -> 0 | Q15: =IF(AND(J15=0,K15=0,L15=0,M15=0),"",IF(O15=0,"PENDENTE DE RATEIO",IF(ABS(P15)>0.005,"DIVERGÊNCIA",IF(COUNTIF(RATEIOS!$A$2:$A$3142,$A15)-COUNTIFS(RATEIOS!$A$2:$A$3142,$A15,RATEIOS!$D$2:$D$3142,"<>")>0,"NÃO CLASSIFICADO","RATEIO OK")))) -> RATEIO OK | R15: Conciliado
A16: BAN-00015 | B16: 15 | C16: 46028 | D16: =IF(C16="","",MONTH(C16)) -> 1 | E16: PIX | F16: SAÍDA | G16: MARKETPLACE (NF - L C BRASIL IMPORT) - REF. SUPORTE PARA JALECOS | H16: MARKETPLACE MERCADO LIVRE | I16: 191282 | J16: 0 | K16: 120.24 | L16: 0 | M16: 0 | N16: =IF(AND(C16="",J16=0,K16=0,L16=0,M16=0),"",CADASTROS!$B$4+SUM($J$2:J16)+SUM($M$2:M16)-SUM($K$2:K16)-SUM($L$2:L16)) -> 22.21 | O16: =IF(A16="","",SUMIF(RATEIOS!$A$2:$A$3142,$A16,RATEIOS!$F$2:$F$3142)) -> 120.24 | P16: =IF(A16="","",(J16+K16+L16+M16)-O16) -> 0 | Q16: =IF(AND(J16=0,K16=0,L16=0,M16=0),"",IF(O16=0,"PENDENTE DE RATEIO",IF(ABS(P16)>0.005,"DIVERGÊNCIA",IF(COUNTIF(RATEIOS!$A$2:$A$3142,$A16)-COUNTIFS(RATEIOS!$A$2:$A$3142,$A16,RATEIOS!$D$2:$D$3142,"<>")>0,"NÃO CLASSIFICADO","RATEIO OK")))) -> RATEIO OK | R16: Conciliado
A17: BAN-00016 | B17: 16 | C17: 46029 | D17: =IF(C17="","",MONTH(C17)) -> 1 | E17: TRANSFERÊNCIA | F17: ENTRADA | G17: MA FES ENFERMAGEM (REF. PISO SALARIAL ENFERMAGEM - COMP. DEZ/2025) | H17: MA FES ENFERMAGEM | J17: 30897.61 | K17: 0 | L17: 0 | M17: 0 | N17: =IF(AND(C17="",J17=0,K17=0,L17=0,M17=0),"",CADASTROS!$B$4+SUM($J$2:J17)+SUM($M$2:M17)-SUM($K$2:K17)-SUM($L$2:L17)) -> 30919.82 | O17: =IF(A17="","",SUMIF(RATEIOS!$A$2:$A$3142,$A17,RATEIOS!$F$2:$F$3142)) -> 30897.61 | P17: =IF(A17="","",(J17+K17+L17+M17)-O17) -> 0 | Q17: =IF(AND(J17=0,K17=0,L17=0,M17=0),"",IF(O17=0,"PENDENTE DE RATEIO",IF(ABS(P17)>0.005,"DIVERGÊNCIA",IF(COUNTIF(RATEIOS!$A$2:$A$3142,$A17)-COUNTIFS(RATEIOS!$A$2:$A$3142,$A17,RATEIOS!$D$2:$D$3142,"<>")>0,"NÃO CLASSIFICADO","RATEIO OK")))) -> RATEIO OK | R17: Conciliado
A18: BAN-00017 | B18: 17 | C18: 46029 | D18: =IF(C18="","",MONTH(C18)) -> 1 | E18: PIX | F18: SAÍDA | G18: CASSIANO & CASSINOS CONTABILIDADE (REF. CERTIFICAÇÃO DIGITAL - PJ) | H18: CASSIANO & CASSINOS CONTABILIDADE | I18: 822 | J18: 0 | K18: 220 | L18: 0 | M18: 0 | N18: =IF(AND(C18="",J18=0,K18=0,L18=0,M18=0),"",CADASTROS!$B$4+SUM($J$2:J18)+SUM($M$2:M18)-SUM($K$2:K18)-SUM($L$2:L18)) -> 30699.82 | O18: =IF(A18="","",SUMIF(RATEIOS!$A$2:$A$3142,$A18,RATEIOS!$F$2:$F$3142)) -> 220 | P18: =IF(A18="","",(J18+K18+L18+M18)-O18) -> 0 | Q18: =IF(AND(J18=0,K18=0,L18=0,M18=0),"",IF(O18=0,"PENDENTE DE RATEIO",IF(ABS(P18)>0.005,"DIVERGÊNCIA",IF(COUNTIF(RATEIOS!$A$2:$A$3142,$A18)-COUNTIFS(RATEIOS!$A$2:$A$3142,$A18,RATEIOS!$D$2:$D$3142,"<>")>0,"NÃO CLASSIFICADO","RATEIO OK")))) -> RATEIO OK | R18: Conciliado
A19: BAN-00018 | B19: 18 | C19: 46029 | D19: =IF(C19="","",MONTH(C19)) -> 1 | E19: BOLETO | F19: SAÍDA | G19: CRISTALIA PRODUTOS (REF. HEPARINAS) 1/3 | H19: CRISTALIA PRODUTOS | I19: 862145 | J19: 0 | K19: 10335.4 | L19: 0 | M19: 0 | N19: =IF(AND(C19="",J19=0,K19=0,L19=0,M19=0),"",CADASTROS!$B$4+SUM($J$2:J19)+SUM($M$2:M19)-SUM($K$2:K19)-SUM($L$2:L19)) -> 20364.42 | O19: =IF(A19="","",SUMIF(RATEIOS!$A$2:$A$3142,$A19,RATEIOS!$F$2:$F$3142)) -> 10335.4 | P19: =IF(A19="","",(J19+K19+L19+M19)-O19) -> 0 | Q19: =IF(AND(J19=0,K19=0,L19=0,M19=0),"",IF(O19=0,"PENDENTE DE RATEIO",IF(ABS(P19)>0.005,"DIVERGÊNCIA",IF(COUNTIF(RATEIOS!$A$2:$A$3142,$A19)-COUNTIFS(RATEIOS!$A$2:$A$3142,$A19,RATEIOS!$D$2:$D$3142,"<>")>0,"NÃO CLASSIFICADO","RATEIO OK")))) -> RATEIO OK | R19: Conciliado
A20: BAN-00019 | B20: 19 | C20: 46029 | D20: =IF(C20="","",MONTH(C20)) -> 1 | E20: PIX | F20: SAÍDA | G20: EQUATORIAL MARANHÃO (ENERGIA - CASA ALUGUEL) | H20: EQUATORIAL MARANHÃO | J20: 0 | K20: 27.78 | L20: 0 | M20: 0 | N20: =IF(AND(C20="",J20=0,K20=0,L20=0,M20=0),"",CADASTROS!$B$4+SUM($J$2:J20)+SUM($M$2:M20)-SUM($K$2:K20)-SUM($L$2:L20)) -> 20336.64 | O20: =IF(A20="","",SUMIF(RATEIOS!$A$2:$A$3142,$A20,RATEIOS!$F$2:$F$3142)) -> 27.78 | P20: =IF(A20="","",(J20+K20+L20+M20)-O20) -> 0 | Q20: =IF(AND(J20=0,K20=0,L20=0,M20=0),"",IF(O20=0,"PENDENTE DE RATEIO",IF(ABS(P20)>0.005,"DIVERGÊNCIA",IF(COUNTIF(RATEIOS!$A$2:$A$3142,$A20)-COUNTIFS(RATEIOS!$A$2:$A$3142,$A20,RATEIOS!$D$2:$D$3142,"<>")>0,"NÃO CLASSIFICADO","RATEIO OK")))) -> RATEIO OK | R20: Conciliado
A21: BAN-00020 | B21: 20 | C21: 46029 | D21: =IF(C21="","",MONTH(C21)) -> 1 | E21: PIX | F21: SAÍDA | G21: ANTONIO SANTOS L. FILHO (REF. ALUGUEL CASA DE APOIO) | H21: ANTONIO SANTOS L. FILHO | I21: SEM NF | J21: 0 | K21: 400 | L21: 0 | M21: 0 | N21: =IF(AND(C21="",J21=0,K21=0,L21=0,M21=0),"",CADASTROS!$B$4+SUM($J$2:J21)+SUM($M$2:M21)-SUM($K$2:K21)-SUM($L$2:L21)) -> 19936.64 | O21: =IF(A21="","",SUMIF(RATEIOS!$A$2:$A$3142,$A21,RATEIOS!$F$2:$F$3142)) -> 400 | P21: =IF(A21="","",(J21+K21+L21+M21)-O21) -> 0 | Q21: =IF(AND(J21=0,K21=0,L21=0,M21=0),"",IF(O21=0,"PENDENTE DE RATEIO",IF(ABS(P21)>0.005,"DIVERGÊNCIA",IF(COUNTIF(RATEIOS!$A$2:$A$3142,$A21)-COUNTIFS(RATEIOS!$A$2:$A$3142,$A21,RATEIOS!$D$2:$D$3142,"<>")>0,"NÃO CLASSIFICADO","RATEIO OK")))) -> RATEIO OK | R21: Conciliado
A22: BAN-00021 | B22: 21 | C22: 46030 | D22: =IF(C22="","",MONTH(C22)) -> 1 | E22: BOLETO | F22: SAÍDA | G22: ALECRIM INDUSTRIA E COMÉRCIO (REF. PAPEL TOALHA) 1/1 | H22: ALECRIM INDUSTRIA E COMÉRCIO | I22: 7657 | J22: 0 | K22: 561.2 | L22: 0 | M22: 0 | N22: =IF(AND(C22="",J22=0,K22=0,L22=0,M22=0),"",CADASTROS!$B$4+SUM($J$2:J22)+SUM($M$2:M22)-SUM($K$2:K22)-SUM($L$2:L22)) -> 19375.44 | O22: =IF(A22="","",SUMIF(RATEIOS!$A$2:$A$3142,$A22,RATEIOS!$F$2:$F$3142)) -> 561.2 | P22: =IF(A22="","",(J22+K22+L22+M22)-O22) -> 0 | Q22: =IF(AND(J22=0,K22=0,L22=0,M22=0),"",IF(O22=0,"PENDENTE DE RATEIO",IF(ABS(P22)>0.005,"DIVERGÊNCIA",IF(COUNTIF(RATEIOS!$A$2:$A$3142,$A22)-COUNTIFS(RATEIOS!$A$2:$A$3142,$A22,RATEIOS!$D$2:$D$3142,"<>")>0,"NÃO CLASSIFICADO","RATEIO OK")))) -> RATEIO OK | R22: Conciliado
A23: BAN-00022 | B23: 22 | C23: 46030 | D23: =IF(C23="","",MONTH(C23)) -> 1 | E23: BOLETO | F23: SAÍDA | G23: BANCO VOLKSWAGEN (NF - CAVEPEL - REF. PRESTAÇÃO CARRO) 5/48 | H23: BANCO VOLKSWAGEN | I23: 38758 | J23: 0 | K23: 1935.4 | L23: 0 | M23: 0 | N23: =IF(AND(C23="",J23=0,K23=0,L23=0,M23=0),"",CADASTROS!$B$4+SUM($J$2:J23)+SUM($M$2:M23)-SUM($K$2:K23)-SUM($L$2:L23)) -> 17440.04 | O23: =IF(A23="","",SUMIF(RATEIOS!$A$2:$A$3142,$A23,RATEIOS!$F$2:$F$3142)) -> 1935.4 | P23: =IF(A23="","",(J23+K23+L23+M23)-O23) -> 0 | Q23: =IF(AND(J23=0,K23=0,L23=0,M23=0),"",IF(O23=0,"PENDENTE DE RATEIO",IF(ABS(P23)>0.005,"DIVERGÊNCIA",IF(COUNTIF(RATEIOS!$A$2:$A$3142,$A23)-COUNTIFS(RATEIOS!$A$2:$A$3142,$A23,RATEIOS!$D$2:$D$3142,"<>")>0,"NÃO CLASSIFICADO","RATEIO OK")))) -> RATEIO OK | R23: Conciliado
A24: BAN-00023 | B24: 23 | C24: 46030 | D24: =IF(C24="","",MONTH(C24)) -> 1 | E24: DÉBITO AUTOMÁTICO | F24: SAÍDA | G24: TARIFA BANCÁRIA (SALÁRIO CRÉD. CONTA) | H24: TARIFA BANCÁRIA | J24: 0 | K24: 26.25 | L24: 0 | M24: 0 | N24: =IF(AND(C24="",J24=0,K24=0,L24=0,M24=0),"",CADASTROS!$B$4+SUM($J$2:J24)+SUM($M$2:M24)-SUM($K$2:K24)-SUM($L$2:L24)) -> 17413.79 | O24: =IF(A24="","",SUMIF(RATEIOS!$A$2:$A$3142,$A24,RATEIOS!$F$2:$F$3142)) -> 26.25 | P24: =IF(A24="","",(J24+K24+L24+M24)-O24) -> 0 | Q24: =IF(AND(J24=0,K24=0,L24=0,M24=0),"",IF(O24=0,"PENDENTE DE RATEIO",IF(ABS(P24)>0.005,"DIVERGÊNCIA",IF(COUNTIF(RATEIOS!$A$2:$A$3142,$A24)-COUNTIFS(RATEIOS!$A$2:$A$3142,$A24,RATEIOS!$D$2:$D$3142,"<>")>0,"NÃO CLASSIFICADO","RATEIO OK")))) -> RATEIO OK | R24: Conciliado
A25: BAN-00024 | B25: 24 | C25: 46030 | D25: =IF(C25="","",MONTH(C25)) -> 1 | E25: OUTROS | F25: RESGATE | G25: BB RENDE FÁCIL | H25: BANCO DO BRASIL - CDB DI | J25: 0 | K25: 0 | L25: 0 | M25: 241.68 | N25: =IF(AND(C25="",J25=0,K25=0,L25=0,M25=0),"",CADASTROS!$B$4+SUM($J$2:J25)+SUM($M$2:M25)-SUM($K$2:K25)-SUM($L$2:L25)) -> 17655.47 | O25: =IF(A25="","",SUMIF(RATEIOS!$A$2:$A$3142,$A25,RATEIOS!$F$2:$F$3142)) -> 241.68 | P25: =IF(A25="","",(J25+K25+L25+M25)-O25) -> 0 | Q25: =IF(AND(J25=0,K25=0,L25=0,M25=0),"",IF(O25=0,"PENDENTE DE RATEIO",IF(ABS(P25)>0.005,"DIVERGÊNCIA",IF(COUNTIF(RATEIOS!$A$2:$A$3142,$A25)-COUNTIFS(RATEIOS!$A$2:$A$3142,$A25,RATEIOS!$D$2:$D$3142,"<>")>0,"NÃO CLASSIFICADO","RATEIO OK")))) -> RATEIO OK | R25: Conciliado
A26: BAN-00025 | B26: 25 | C26: 46030 | D26: =IF(C26="","",MONTH(C26)) -> 1 | E26: OUTROS | F26: RESGATE | G26: RESGATE BB CDB DI | H26: BANCO DO BRASIL - CDB DI | J26: 0 | K26: 0 | L26: 0 | M26: 37500 | N26: =IF(AND(C26="",J26=0,K26=0,L26=0,M26=0),"",CADASTROS!$B$4+SUM($J$2:J26)+SUM($M$2:M26)-SUM($K$2:K26)-SUM($L$2:L26)) -> 55155.47 | O26: =IF(A26="","",SUMIF(RATEIOS!$A$2:$A$3142,$A26,RATEIOS!$F$2:$F$3142)) -> 37500 | P26: =IF(A26="","",(J26+K26+L26+M26)-O26) -> 0 | Q26: =IF(AND(J26=0,K26=0,L26=0,M26=0),"",IF(O26=0,"PENDENTE DE RATEIO",IF(ABS(P26)>0.005,"DIVERGÊNCIA",IF(COUNTIF(RATEIOS!$A$2:$A$3142,$A26)-COUNTIFS(RATEIOS!$A$2:$A$3142,$A26,RATEIOS!$D$2:$D$3142,"<>")>0,"NÃO CLASSIFICADO","RATEIO OK")))) -> RATEIO OK | R26: Conciliado
A27: BAN-00026 | B27: 26 | C27: 46030 | D27: =IF(C27="","",MONTH(C27)) -> 1 | E27: FOLHA DE PAGAMENTO | F27: SAÍDA | G27: FOLHA DE PAGAMENTO (REF. PAGAMENTO DE SALÁRIO - COMP. 12/2026) | H27: FOLHA DE PAGAMENTO | J27: 0 | K27: 55071.75 | L27: 0 | M27: 0 | N27: =IF(AND(C27="",J27=0,K27=0,L27=0,M27=0),"",CADASTROS!$B$4+SUM($J$2:J27)+SUM($M$2:M27)-SUM($K$2:K27)-SUM($L$2:L27)) -> 83.72 | O27: =IF(A27="","",SUMIF(RATEIOS!$A$2:$A$3142,$A27,RATEIOS!$F$2:$F$3142)) -> 55071.75 | P27: =IF(A27="","",(J27+K27+L27+M27)-O27) -> 0 | Q27: =IF(AND(J27=0,K27=0,L27=0,M27=0),"",IF(O27=0,"PENDENTE DE RATEIO",IF(ABS(P27)>0.005,"DIVERGÊNCIA",IF(COUNTIF(RATEIOS!$A$2:$A$3142,$A27)-COUNTIFS(RATEIOS!$A$2:$A$3142,$A27,RATEIOS!$D$2:$D$3142,"<>")>0,"NÃO CLASSIFICADO","RATEIO OK")))) -> RATEIO OK | R27: Conciliado
A28: BAN-00027 | B28: 27 | C28: 46031 | D28: =IF(C28="","",MONTH(C28)) -> 1 | E28: OUTROS | F28: RESGATE | G28: RESGATE BB CDB DI | H28: BANCO DO BRASIL - CDB DI | J28: 0 | K28: 0 | L28: 0 | M28: 69 | N28: =IF(AND(C28="",J28=0,K28=0,L28=0,M28=0),"",CADASTROS!$B$4+SUM($J$2:J28)+SUM($M$2:M28)-SUM($K$2:K28)-SUM($L$2:L28)) -> 152.72 | O28: =IF(A28="","",SUMIF(RATEIOS!$A$2:$A$3142,$A28,RATEIOS!$F$2:$F$3142)) -> 69 | P28: =IF(A28="","",(J28+K28+L28+M28)-O28) -> 0 | Q28: =IF(AND(J28=0,K28=0,L28=0,M28=0),"",IF(O28=0,"PENDENTE DE RATEIO",IF(ABS(P28)>0.005,"DIVERGÊNCIA",IF(COUNTIF(RATEIOS!$A$2:$A$3142,$A28)-COUNTIFS(RATEIOS!$A$2:$A$3142,$A28,RATEIOS!$D$2:$D$3142,"<>")>0,"NÃO CLASSIFICADO","RATEIO OK")))) -> RATEIO OK | R28: Conciliado
A29: BAN-00028 | B29: 28 | C29: 46031 | D29: =IF(C29="","",MONTH(C29)) -> 1 | E29: BOLETO | F29: SAÍDA | G29: EQUATORIAL MARANHÃO (REF. ENERGIA ELÉTRICA DA CLÍNICA) - REF. DEZ/25 | H29: EQUATORIAL MARANHÃO | J29: 0 | K29: 21581.32 | L29: 0 | M29: 0 | N29: =IF(AND(C29="",J29=0,K29=0,L29=0,M29=0),"",CADASTROS!$B$4+SUM($J$2:J29)+SUM($M$2:M29)-SUM($K$2:K29)-SUM($L$2:L29)) -> -21428.6 | O29: =IF(A29="","",SUMIF(RATEIOS!$A$2:$A$3142,$A29,RATEIOS!$F$2:$F$3142)) -> 21581.32 | P29: =IF(A29="","",(J29+K29+L29+M29)-O29) -> 0 | Q29: =IF(AND(J29=0,K29=0,L29=0,M29=0),"",IF(O29=0,"PENDENTE DE RATEIO",IF(ABS(P29)>0.005,"DIVERGÊNCIA",IF(COUNTIF(RATEIOS!$A$2:$A$3142,$A29)-COUNTIFS(RATEIOS!$A$2:$A$3142,$A29,RATEIOS!$D$2:$D$3142,"<>")>0,"NÃO CLASSIFICADO","RATEIO OK")))) -> RATEIO OK | R29: Conciliado
A30: BAN-00029 | B30: 29 | C30: 46031 | D30: =IF(C30="","",MONTH(C30)) -> 1 | E30: TRANSFERÊNCIA | F30: SAÍDA | G30: A C R DA SILVA E CIA (SUPERMERCADO CAMINO - REF. COMPRAS QUINZENAIS - 08/12 E 23/12 ) | H30: CAMINO | I30: NF 10175 / NF 10256 | J30: 0 | K30: 4031.09 | L30: 0 | M30: 0 | N30: =IF(AND(C30="",J30=0,K30=0,L30=0,M30=0),"",CADASTROS!$B$4+SUM($J$2:J30)+SUM($M$2:M30)-SUM($K$2:K30)-SUM($L$2:L30)) -> -25459.69 | O30: =IF(A30="","",SUMIF(RATEIOS!$A$2:$A$3142,$A30,RATEIOS!$F$2:$F$3142)) -> 4031.09 | P30: =IF(A30="","",(J30+K30+L30+M30)-O30) -> 0 | Q30: =IF(AND(J30=0,K30=0,L30=0,M30=0),"",IF(O30=0,"PENDENTE DE RATEIO",IF(ABS(P30)>0.005,"DIVERGÊNCIA",IF(COUNTIF(RATEIOS!$A$2:$A$3142,$A30)-COUNTIFS(RATEIOS!$A$2:$A$3142,$A30,RATEIOS!$D$2:$D$3142,"<>")>0,"NÃO CLASSIFICADO","RATEIO OK")))) -> RATEIO OK | R30: Conciliado | S30: NF 10175 - R$ 2.029,48 / NF 10256 - R$ 2.001,61
A31: BAN-00030 | B31: 30 | C31: 46031 | D31: =IF(C31="","",MONTH(C31)) -> 1 | E31: PIX | F31: SAÍDA | G31: J G MARQUES CONVENIENCIA (REF. ALMOÇO HELENAS BRISTRÔ - AFONSO E EMANUELLE) | H31: J G MARQUES CONVENIENCIA | I31: CUPOM FISCAL | J31: 0 | K31: 94.6 | L31: 0 | M31: 0 | N31: =IF(AND(C31="",J31=0,K31=0,L31=0,M31=0),"",CADASTROS!$B$4+SUM($J$2:J31)+SUM($M$2:M31)-SUM($K$2:K31)-SUM($L$2:L31)) -> -25554.29 | O31: =IF(A31="","",SUMIF(RATEIOS!$A$2:$A$3142,$A31,RATEIOS!$F$2:$F$3142)) -> 94.6 | P31: =IF(A31="","",(J31+K31+L31+M31)-O31) -> 0 | Q31: =IF(AND(J31=0,K31=0,L31=0,M31=0),"",IF(O31=0,"PENDENTE DE RATEIO",IF(ABS(P31)>0.005,"DIVERGÊNCIA",IF(COUNTIF(RATEIOS!$A$2:$A$3142,$A31)-COUNTIFS(RATEIOS!$A$2:$A$3142,$A31,RATEIOS!$D$2:$D$3142,"<>")>0,"NÃO CLASSIFICADO","RATEIO OK")))) -> RATEIO OK | R31: Conciliado
A32: BAN-00031 | B32: 31 | C32: 46031 | D32: =IF(C32="","",MONTH(C32)) -> 1 | E32: PIX | F32: SAÍDA | G32: MARKETPLACE (NF - LOJA KICAPACHO) - REF. COMPRA DE 03 TAPETES SINALIZADORES | H32: MARKETPLACE MERCADO LIVRE | I32: 7410 / 7411 / 7412 | J32: 0 | K32: 387.03 | L32: 0 | M32: 0 | N32: =IF(AND(C32="",J32=0,K32=0,L32=0,M32=0),"",CADASTROS!$B$4+SUM($J$2:J32)+SUM($M$2:M32)-SUM($K$2:K32)-SUM($L$2:L32)) -> -25941.32 | O32: =IF(A32="","",SUMIF(RATEIOS!$A$2:$A$3142,$A32,RATEIOS!$F$2:$F$3142)) -> 387.03 | P32: =IF(A32="","",(J32+K32+L32+M32)-O32) -> 0 | Q32: =IF(AND(J32=0,K32=0,L32=0,M32=0),"",IF(O32=0,"PENDENTE DE RATEIO",IF(ABS(P32)>0.005,"DIVERGÊNCIA",IF(COUNTIF(RATEIOS!$A$2:$A$3142,$A32)-COUNTIFS(RATEIOS!$A$2:$A$3142,$A32,RATEIOS!$D$2:$D$3142,"<>")>0,"NÃO CLASSIFICADO","RATEIO OK")))) -> RATEIO OK | R32: Conciliado
A33: BAN-00032 | B33: 32 | C33: 46031 | D33: =IF(C33="","",MONTH(C33)) -> 1 | E33: OUTROS | F33: RESGATE | G33: RESGATE BB CDB DI | H33: BANCO DO BRASIL - CDB DI | J33: 0 | K33: 0 | L33: 0 | M33: 26000 | N33: =IF(AND(C33="",J33=0,K33=0,L33=0,M33=0),"",CADASTROS!$B$4+SUM($J$2:J33)+SUM($M$2:M33)-SUM($K$2:K33)-SUM($L$2:L33)) -> 58.68 | O33: =IF(A33="","",SUMIF(RATEIOS!$A$2:$A$3142,$A33,RATEIOS!$F$2:$F$3142)) -> 26000 | P33: =IF(A33="","",(J33+K33+L33+M33)-O33) -> 0 | Q33: =IF(AND(J33=0,K33=0,L33=0,M33=0),"",IF(O33=0,"PENDENTE DE RATEIO",IF(ABS(P33)>0.005,"DIVERGÊNCIA",IF(COUNTIF(RATEIOS!$A$2:$A$3142,$A33)-COUNTIFS(RATEIOS!$A$2:$A$3142,$A33,RATEIOS!$D$2:$D$3142,"<>")>0,"NÃO CLASSIFICADO","RATEIO OK")))) -> RATEIO OK | R33: Conciliado
A34: BAN-00033 | B34: 33 | C34: 46034 | D34: =IF(C34="","",MONTH(C34)) -> 1 | E34: OUTROS | F34: RESGATE | G34: CDB/RDB | H34: BANCO DO BRASIL - CDB DI | J34: 0 | K34: 0 | L34: 0 | M34: 57.72 | N34: =IF(AND(C34="",J34=0,K34=0,L34=0,M34=0),"",CADASTROS!$B$4+SUM($J$2:J34)+SUM($M$2:M34)-SUM($K$2:K34)-SUM($L$2:L34)) -> 116.4 | O34: =IF(A34="","",SUMIF(RATEIOS!$A$2:$A$3142,$A34,RATEIOS!$F$2:$F$3142)) -> 57.72 | P34: =IF(A34="","",(J34+K34+L34+M34)-O34) -> 0 | Q34: =IF(AND(J34=0,K34=0,L34=0,M34=0),"",IF(O34=0,"PENDENTE DE RATEIO",IF(ABS(P34)>0.005,"DIVERGÊNCIA",IF(COUNTIF(RATEIOS!$A$2:$A$3142,$A34)-COUNTIFS(RATEIOS!$A$2:$A$3142,$A34,RATEIOS!$D$2:$D$3142,"<>")>0,"NÃO CLASSIFICADO","RATEIO OK")))) -> RATEIO OK | R34: Conciliado
A35: BAN-00034 | B35: 34 | C35: 46034 | D35: =IF(C35="","",MONTH(C35)) -> 1 | E35: PIX | F35: SAÍDA | G35: TIM S/A | H35: TIM S/A | J35: 0 | K35: 290.1 | L35: 0 | M35: 0 | N35: =IF(AND(C35="",J35=0,K35=0,L35=0,M35=0),"",CADASTROS!$B$4+SUM($J$2:J35)+SUM($M$2:M35)-SUM($K$2:K35)-SUM($L$2:L35)) -> -173.7 | O35: =IF(A35="","",SUMIF(RATEIOS!$A$2:$A$3142,$A35,RATEIOS!$F$2:$F$3142)) -> 290.1 | P35: =IF(A35="","",(J35+K35+L35+M35)-O35) -> 0 | Q35: =IF(AND(J35=0,K35=0,L35=0,M35=0),"",IF(O35=0,"PENDENTE DE RATEIO",IF(ABS(P35)>0.005,"DIVERGÊNCIA",IF(COUNTIF(RATEIOS!$A$2:$A$3142,$A35)-COUNTIFS(RATEIOS!$A$2:$A$3142,$A35,RATEIOS!$D$2:$D$3142,"<>")>0,"NÃO CLASSIFICADO","RATEIO OK")))) -> NÃO CLASSIFICADO | R35: Conciliado
A36: BAN-00035 | B36: 35 | C36: 46034 | D36: =IF(C36="","",MONTH(C36)) -> 1 | E36: PIX | F36: ENTRADA | G36: BRITO, TORRES & LOBO (REF. ESTORNO DO PAGAMENTO TIM S/A) | H36: BRITO, TORRES & LOBO | J36: 290.1 | K36: 0 | L36: 0 | M36: 0 | N36: =IF(AND(C36="",J36=0,K36=0,L36=0,M36=0),"",CADASTROS!$B$4+SUM($J$2:J36)+SUM($M$2:M36)-SUM($K$2:K36)-SUM($L$2:L36)) -> 116.4 | O36: =IF(A36="","",SUMIF(RATEIOS!$A$2:$A$3142,$A36,RATEIOS!$F$2:$F$3142)) -> 290.1 | P36: =IF(A36="","",(J36+K36+L36+M36)-O36) -> 0 | Q36: =IF(AND(J36=0,K36=0,L36=0,M36=0),"",IF(O36=0,"PENDENTE DE RATEIO",IF(ABS(P36)>0.005,"DIVERGÊNCIA",IF(COUNTIF(RATEIOS!$A$2:$A$3142,$A36)-COUNTIFS(RATEIOS!$A$2:$A$3142,$A36,RATEIOS!$D$2:$D$3142,"<>")>0,"NÃO CLASSIFICADO","RATEIO OK")))) -> NÃO CLASSIFICADO | R36: Conciliado
A37: BAN-00036 | B37: 36 | C37: 46034 | D37: =IF(C37="","",MONTH(C37)) -> 1 | E37: PIX | F37: SAÍDA | G37: FERCASTRO (REF. BOTAS, SILICONE E PARAFUSO) | H37: FERCASTRO | I37: 7496 | J37: 0 | K37: 188 | L37: 0 | M37: 0 | N37: =IF(AND(C37="",J37=0,K37=0,L37=0,M37=0),"",CADASTROS!$B$4+SUM($J$2:J37)+SUM($M$2:M37)-SUM($K$2:K37)-SUM($L$2:L37)) -> -71.6 | O37: =IF(A37="","",SUMIF(RATEIOS!$A$2:$A$3142,$A37,RATEIOS!$F$2:$F$3142)) -> 188 | P37: =IF(A37="","",(J37+K37+L37+M37)-O37) -> 0 | Q37: =IF(AND(J37=0,K37=0,L37=0,M37=0),"",IF(O37=0,"PENDENTE DE RATEIO",IF(ABS(P37)>0.005,"DIVERGÊNCIA",IF(COUNTIF(RATEIOS!$A$2:$A$3142,$A37)-COUNTIFS(RATEIOS!$A$2:$A$3142,$A37,RATEIOS!$D$2:$D$3142,"<>")>0,"NÃO CLASSIFICADO","RATEIO OK")))) -> RATEIO OK | R37: Conciliado
A38: BAN-00037 | B38: 37 | C38: 46034 | D38: =IF(C38="","",MONTH(C38)) -> 1 | E38: TRANSFERÊNCIA | F38: SAÍDA | G38: M E S XAVIER (REF. CARGA DE 02 OXIGÊNIOS MEDICINAL) | H38: M E S XAVIER | I38: 273 | J38: 0 | K38: 360 | L38: 0 | M38: 0 | N38: =IF(AND(C38="",J38=0,K38=0,L38=0,M38=0),"",CADASTROS!$B$4+SUM($J$2:J38)+SUM($M$2:M38)-SUM($K$2:K38)-SUM($L$2:L38)) -> -431.6 | O38: =IF(A38="","",SUMIF(RATEIOS!$A$2:$A$3142,$A38,RATEIOS!$F$2:$F$3142)) -> 360 | P38: =IF(A38="","",(J38+K38+L38+M38)-O38) -> 0 | Q38: =IF(AND(J38=0,K38=0,L38=0,M38=0),"",IF(O38=0,"PENDENTE DE RATEIO",IF(ABS(P38)>0.005,"DIVERGÊNCIA",IF(COUNTIF(RATEIOS!$A$2:$A$3142,$A38)-COUNTIFS(RATEIOS!$A$2:$A$3142,$A38,RATEIOS!$D$2:$D$3142,"<>")>0,"NÃO CLASSIFICADO","RATEIO OK")))) -> RATEIO OK | R38: Conciliado
A39: BAN-00038 | B39: 38 | C39: 46034 | D39: =IF(C39="","",MONTH(C39)) -> 1 | E39: BOLETO | F39: SAÍDA | G39: INDIFILTROS FILTROS (RE. FILTROS, CARCAÇA, CHAVES) 2/2 | H39: INDIFILTROS FILTROS | I39: 53977 | J39: 0 | K39: 1428.14 | L39: 0 | M39: 0 | N39: =IF(AND(C39="",J39=0,K39=0,L39=0,M39=0),"",CADASTROS!$B$4+SUM($J$2:J39)+SUM($M$2:M39)-SUM($K$2:K39)-SUM($L$2:L39)) -> -1859.74 | O39: =IF(A39="","",SUMIF(RATEIOS!$A$2:$A$3142,$A39,RATEIOS!$F$2:$F$3142)) -> 1428.14 | P39: =IF(A39="","",(J39+K39+L39+M39)-O39) -> 0 | Q39: =IF(AND(J39=0,K39=0,L39=0,M39=0),"",IF(O39=0,"PENDENTE DE RATEIO",IF(ABS(P39)>0.005,"DIVERGÊNCIA",IF(COUNTIF(RATEIOS!$A$2:$A$3142,$A39)-COUNTIFS(RATEIOS!$A$2:$A$3142,$A39,RATEIOS!$D$2:$D$3142,"<>")>0,"NÃO CLASSIFICADO","RATEIO OK")))) -> RATEIO OK | R39: Conciliado
A40: BAN-00039 | B40: 39 | C40: 46034 | D40: =IF(C40="","",MONTH(C40)) -> 1 | E40: DÉBITO AUTOMÁTICO | F40: SAÍDA | G40: TARIFA BANCÁRIA (PACOTE DE SERVIÇOS) | H40: TARIFA PACOTE DE SERVIÇOS | J40: 0 | K40: 263 | L40: 0 | M40: 0 | N40: =IF(AND(C40="",J40=0,K40=0,L40=0,M40=0),"",CADASTROS!$B$4+SUM($J$2:J40)+SUM($M$2:M40)-SUM($K$2:K40)-SUM($L$2:L40)) -> -2122.74 | O40: =IF(A40="","",SUMIF(RATEIOS!$A$2:$A$3142,$A40,RATEIOS!$F$2:$F$3142)) -> 263 | P40: =IF(A40="","",(J40+K40+L40+M40)-O40) -> 0 | Q40: =IF(AND(J40=0,K40=0,L40=0,M40=0),"",IF(O40=0,"PENDENTE DE RATEIO",IF(ABS(P40)>0.005,"DIVERGÊNCIA",IF(COUNTIF(RATEIOS!$A$2:$A$3142,$A40)-COUNTIFS(RATEIOS!$A$2:$A$3142,$A40,RATEIOS!$D$2:$D$3142,"<>")>0,"NÃO CLASSIFICADO","RATEIO OK")))) -> RATEIO OK | R40: Conciliado
A41: BAN-00040 | B41: 40 | C41: 46034 | D41: =IF(C41="","",MONTH(C41)) -> 1 | E41: BOLETO | F41: SAÍDA | G41: MARANET TELECOM (REF. INTERNET) | H41: MARANET TELECOM | I41: 63448 | J41: 0 | K41: 149.9 | L41: 0 | M41: 0 | N41: =IF(AND(C41="",J41=0,K41=0,L41=0,M41=0),"",CADASTROS!$B$4+SUM($J$2:J41)+SUM($M$2:M41)-SUM($K$2:K41)-SUM($L$2:L41)) -> -2272.64 | O41: =IF(A41="","",SUMIF(RATEIOS!$A$2:$A$3142,$A41,RATEIOS!$F$2:$F$3142)) -> 149.9 | P41: =IF(A41="","",(J41+K41+L41+M41)-O41) -> 0 | Q41: =IF(AND(J41=0,K41=0,L41=0,M41=0),"",IF(O41=0,"PENDENTE DE RATEIO",IF(ABS(P41)>0.005,"DIVERGÊNCIA",IF(COUNTIF(RATEIOS!$A$2:$A$3142,$A41)-COUNTIFS(RATEIOS!$A$2:$A$3142,$A41,RATEIOS!$D$2:$D$3142,"<>")>0,"NÃO CLASSIFICADO","RATEIO OK")))) -> RATEIO OK | R41: Conciliado
A42: BAN-00041 | B42: 41 | C42: 46034 | D42: =IF(C42="","",MONTH(C42)) -> 1 | E42: OUTROS | F42: RESGATE | G42: RESGATE BB CDB DI | H42: BANCO DO BRASIL - CDB DI | J42: 0 | K42: 0 | L42: 0 | M42: 2500 | N42: =IF(AND(C42="",J42=0,K42=0,L42=0,M42=0),"",CADASTROS!$B$4+SUM($J$2:J42)+SUM($M$2:M42)-SUM($K$2:K42)-SUM($L$2:L42)) -> 227.36 | O42: =IF(A42="","",SUMIF(RATEIOS!$A$2:$A$3142,$A42,RATEIOS!$F$2:$F$3142)) -> 2500 | P42: =IF(A42="","",(J42+K42+L42+M42)-O42) -> 0 | Q42: =IF(AND(J42=0,K42=0,L42=0,M42=0),"",IF(O42=0,"PENDENTE DE RATEIO",IF(ABS(P42)>0.005,"DIVERGÊNCIA",IF(COUNTIF(RATEIOS!$A$2:$A$3142,$A42)-COUNTIFS(RATEIOS!$A$2:$A$3142,$A42,RATEIOS!$D$2:$D$3142,"<>")>0,"NÃO CLASSIFICADO","RATEIO OK")))) -> RATEIO OK | R42: Conciliado
A43: BAN-00042 | B43: 42 | C43: 46035 | D43: =IF(C43="","",MONTH(C43)) -> 1 | E43: OUTROS | F43: RESGATE | G43: RESGATE BB CDB DI | H43: BANCO DO BRASIL - CDB DI | J43: 0 | K43: 0 | L43: 0 | M43: 7.2 | N43: =IF(AND(C43="",J43=0,K43=0,L43=0,M43=0),"",CADASTROS!$B$4+SUM($J$2:J43)+SUM($M$2:M43)-SUM($K$2:K43)-SUM($L$2:L43)) -> 234.56 | O43: =IF(A43="","",SUMIF(RATEIOS!$A$2:$A$3142,$A43,RATEIOS!$F$2:$F$3142)) -> 7.2 | P43: =IF(A43="","",(J43+K43+L43+M43)-O43) -> 0 | Q43: =IF(AND(J43=0,K43=0,L43=0,M43=0),"",IF(O43=0,"PENDENTE DE RATEIO",IF(ABS(P43)>0.005,"DIVERGÊNCIA",IF(COUNTIF(RATEIOS!$A$2:$A$3142,$A43)-COUNTIFS(RATEIOS!$A$2:$A$3142,$A43,RATEIOS!$D$2:$D$3142,"<>")>0,"NÃO CLASSIFICADO","RATEIO OK")))) -> RATEIO OK | R43: Conciliado
A44: BAN-00043 | B44: 43 | C44: 46035 | D44: =IF(C44="","",MONTH(C44)) -> 1 | E44: FOLHA DE PAGAMENTO | F44: SAÍDA | G44: FOLHA DE PAGAMENTO (REF. PISO SALARIAL DA ENFERMAGEM - COMP. DEZ/2025) | H44: FOLHA DE PAGAMENTO - PISO | J44: 0 | K44: 30897.61 | L44: 0 | M44: 0 | N44: =IF(AND(C44="",J44=0,K44=0,L44=0,M44=0),"",CADASTROS!$B$4+SUM($J$2:J44)+SUM($M$2:M44)-SUM($K$2:K44)-SUM($L$2:L44)) -> -30663.05 | O44: =IF(A44="","",SUMIF(RATEIOS!$A$2:$A$3142,$A44,RATEIOS!$F$2:$F$3142)) -> 30897.61 | P44: =IF(A44="","",(J44+K44+L44+M44)-O44) -> 0 | Q44: =IF(AND(J44=0,K44=0,L44=0,M44=0),"",IF(O44=0,"PENDENTE DE RATEIO",IF(ABS(P44)>0.005,"DIVERGÊNCIA",IF(COUNTIF(RATEIOS!$A$2:$A$3142,$A44)-COUNTIFS(RATEIOS!$A$2:$A$3142,$A44,RATEIOS!$D$2:$D$3142,"<>")>0,"NÃO CLASSIFICADO","RATEIO OK")))) -> RATEIO OK | R44: Conciliado
A45: BAN-00044 | B45: 44 | C45: 46035 | D45: =IF(C45="","",MONTH(C45)) -> 1 | E45: DÉBITO AUTOMÁTICO | F45: SAÍDA | G45: TARIFA BANCÁRIA (SALÁRIO CRÉD. CONTA) | H45: TARIFA BANCÁRIA | J45: 0 | K45: 31.5 | L45: 0 | M45: 0 | N45: =IF(AND(C45="",J45=0,K45=0,L45=0,M45=0),"",CADASTROS!$B$4+SUM($J$2:J45)+SUM($M$2:M45)-SUM($K$2:K45)-SUM($L$2:L45)) -> -30694.55 | O45: =IF(A45="","",SUMIF(RATEIOS!$A$2:$A$3142,$A45,RATEIOS!$F$2:$F$3142)) -> 31.5 | P45: =IF(A45="","",(J45+K45+L45+M45)-O45) -> 0 | Q45: =IF(AND(J45=0,K45=0,L45=0,M45=0),"",IF(O45=0,"PENDENTE DE RATEIO",IF(ABS(P45)>0.005,"DIVERGÊNCIA",IF(COUNTIF(RATEIOS!$A$2:$A$3142,$A45)-COUNTIFS(RATEIOS!$A$2:$A$3142,$A45,RATEIOS!$D$2:$D$3142,"<>")>0,"NÃO CLASSIFICADO","RATEIO OK")))) -> RATEIO OK | R45: Conciliado
A46: BAN-00045 | B46: 45 | C46: 46035 | D46: =IF(C46="","",MONTH(C46)) -> 1 | E46: OUTROS | F46: RESGATE | G46: RESGATE BB CDB DI | H46: BANCO DO BRASIL - CDB DI | J46: 0 | K46: 0 | L46: 0 | M46: 31000 | N46: =IF(AND(C46="",J46=0,K46=0,L46=0,M46=0),"",CADASTROS!$B$4+SUM($J$2:J46)+SUM($M$2:M46)-SUM($K$2:K46)-SUM($L$2:L46)) -> 305.45 | O46: =IF(A46="","",SUMIF(RATEIOS!$A$2:$A$3142,$A46,RATEIOS!$F$2:$F$3142)) -> 31000 | P46: =IF(A46="","",(J46+K46+L46+M46)-O46) -> 0 | Q46: =IF(AND(J46=0,K46=0,L46=0,M46=0),"",IF(O46=0,"PENDENTE DE RATEIO",IF(ABS(P46)>0.005,"DIVERGÊNCIA",IF(COUNTIF(RATEIOS!$A$2:$A$3142,$A46)-COUNTIFS(RATEIOS!$A$2:$A$3142,$A46,RATEIOS!$D$2:$D$3142,"<>")>0,"NÃO CLASSIFICADO","RATEIO OK")))) -> RATEIO OK | R46: Conciliado
A47: BAN-00046 | B47: 46 | C47: 46036 | D47: =IF(C47="","",MONTH(C47)) -> 1 | E47: OUTROS | F47: RESGATE | G47: RESGATE BB CDB DI | H47: BANCO DO BRASIL - CDB DI | J47: 0 | K47: 0 | L47: 0 | M47: 102.3 | N47: =IF(AND(C47="",J47=0,K47=0,L47=0,M47=0),"",CADASTROS!$B$4+SUM($J$2:J47)+SUM($M$2:M47)-SUM($K$2:K47)-SUM($L$2:L47)) -> 407.75 | O47: =IF(A47="","",SUMIF(RATEIOS!$A$2:$A$3142,$A47,RATEIOS!$F$2:$F$3142)) -> 102.3 | P47: =IF(A47="","",(J47+K47+L47+M47)-O47) -> 0 | Q47: =IF(AND(J47=0,K47=0,L47=0,M47=0),"",IF(O47=0,"PENDENTE DE RATEIO",IF(ABS(P47)>0.005,"DIVERGÊNCIA",IF(COUNTIF(RATEIOS!$A$2:$A$3142,$A47)-COUNTIFS(RATEIOS!$A$2:$A$3142,$A47,RATEIOS!$D$2:$D$3142,"<>")>0,"NÃO CLASSIFICADO","RATEIO OK")))) -> RATEIO OK | R47: Conciliado
A48: BAN-00047 | B48: 47 | C48: 46036 | D48: =IF(C48="","",MONTH(C48)) -> 1 | E48: BOLETO | F48: SAÍDA | G48: ISS (MUNICIPIO DE SANTA INÊS) - NF 04 (REF. COMP. 10/2025) - NF EMITIDA EM 04/12/2025 | H48: ISS | J48: 0 | K48: 25067.52 | L48: 0 | M48: 0 | N48: =IF(AND(C48="",J48=0,K48=0,L48=0,M48=0),"",CADASTROS!$B$4+SUM($J$2:J48)+SUM($M$2:M48)-SUM($K$2:K48)-SUM($L$2:L48)) -> -24659.77 | O48: =IF(A48="","",SUMIF(RATEIOS!$A$2:$A$3142,$A48,RATEIOS!$F$2:$F$3142)) -> 25067.52 | P48: =IF(A48="","",(J48+K48+L48+M48)-O48) -> 0 | Q48: =IF(AND(J48=0,K48=0,L48=0,M48=0),"",IF(O48=0,"PENDENTE DE RATEIO",IF(ABS(P48)>0.005,"DIVERGÊNCIA",IF(COUNTIF(RATEIOS!$A$2:$A$3142,$A48)-COUNTIFS(RATEIOS!$A$2:$A$3142,$A48,RATEIOS!$D$2:$D$3142,"<>")>0,"NÃO CLASSIFICADO","RATEIO OK")))) -> RATEIO OK | R48: Conciliado
A49: BAN-00048 | B49: 48 | C49: 46036 | D49: =IF(C49="","",MONTH(C49)) -> 1 | E49: BOLETO | F49: SAÍDA | G49: PAGAMENTO DE IPTU (2026) | H49: PAGAMENTO DE IPTU | J49: 0 | K49: 852.23 | L49: 0 | M49: 0 | N49: =IF(AND(C49="",J49=0,K49=0,L49=0,M49=0),"",CADASTROS!$B$4+SUM($J$2:J49)+SUM($M$2:M49)-SUM($K$2:K49)-SUM($L$2:L49)) -> -25512 | O49: =IF(A49="","",SUMIF(RATEIOS!$A$2:$A$3142,$A49,RATEIOS!$F$2:$F$3142)) -> 852.23 | P49: =IF(A49="","",(J49+K49+L49+M49)-O49) -> 0 | Q49: =IF(AND(J49=0,K49=0,L49=0,M49=0),"",IF(O49=0,"PENDENTE DE RATEIO",IF(ABS(P49)>0.005,"DIVERGÊNCIA",IF(COUNTIF(RATEIOS!$A$2:$A$3142,$A49)-COUNTIFS(RATEIOS!$A$2:$A$3142,$A49,RATEIOS!$D$2:$D$3142,"<>")>0,"NÃO CLASSIFICADO","RATEIO OK")))) -> RATEIO OK | R49: Conciliado
A50: BAN-00049 | B50: 49 | C50: 46036 | D50: =IF(C50="","",MONTH(C50)) -> 1 | E50: OUTROS | F50: RESGATE | G50: RESGATE BB CDB DI | H50: BANCO DO BRASIL - CDB DI | J50: 0 | K50: 0 | L50: 0 | M50: 26000 | N50: =IF(AND(C50="",J50=0,K50=0,L50=0,M50=0),"",CADASTROS!$B$4+SUM($J$2:J50)+SUM($M$2:M50)-SUM($K$2:K50)-SUM($L$2:L50)) -> 488 | O50: =IF(A50="","",SUMIF(RATEIOS!$A$2:$A$3142,$A50,RATEIOS!$F$2:$F$3142)) -> 26000 | P50: =IF(A50="","",(J50+K50+L50+M50)-O50) -> 0 | Q50: =IF(AND(J50=0,K50=0,L50=0,M50=0),"",IF(O50=0,"PENDENTE DE RATEIO",IF(ABS(P50)>0.005,"DIVERGÊNCIA",IF(COUNTIF(RATEIOS!$A$2:$A$3142,$A50)-COUNTIFS(RATEIOS!$A$2:$A$3142,$A50,RATEIOS!$D$2:$D$3142,"<>")>0,"NÃO CLASSIFICADO","RATEIO OK")))) -> RATEIO OK | R50: Conciliado
A51: BAN-00050 | B51: 50 | C51: 46037 | D51: =IF(C51="","",MONTH(C51)) -> 1 | E51: OUTROS | F51: RESGATE | G51: RESGATE BB CDB DI | H51: BANCO DO BRASIL - CDB DI | J51: 0 | K51: 0 | L51: 0 | M51: 96.72 | N51: =IF(AND(C51="",J51=0,K51=0,L51=0,M51=0),"",CADASTROS!$B$4+SUM($J$2:J51)+SUM($M$2:M51)-SUM($K$2:K51)-SUM($L$2:L51)) -> 584.72 | O51: =IF(A51="","",SUMIF(RATEIOS!$A$2:$A$3142,$A51,RATEIOS!$F$2:$F$3142)) -> 96.72 | P51: =IF(A51="","",(J51+K51+L51+M51)-O51) -> 0 | Q51: =IF(AND(J51=0,K51=0,L51=0,M51=0),"",IF(O51=0,"PENDENTE DE RATEIO",IF(ABS(P51)>0.005,"DIVERGÊNCIA",IF(COUNTIF(RATEIOS!$A$2:$A$3142,$A51)-COUNTIFS(RATEIOS!$A$2:$A$3142,$A51,RATEIOS!$D$2:$D$3142,"<>")>0,"NÃO CLASSIFICADO","RATEIO OK")))) -> RATEIO OK | R51: Conciliado
A52: BAN-00051 | B52: 51 | C52: 46037 | D52: =IF(C52="","",MONTH(C52)) -> 1 | E52: BOLETO | F52: SAÍDA | G52: ISS (MUNICIPIO DE SANTA INÊS) - NF 05 (REF. COMP. 11/2025) - NF EMITIDA EM 16/12/2025 | H52: ISS | J52: 0 | K52: 23758.98 | L52: 0 | M52: 0 | N52: =IF(AND(C52="",J52=0,K52=0,L52=0,M52=0),"",CADASTROS!$B$4+SUM($J$2:J52)+SUM($M$2:M52)-SUM($K$2:K52)-SUM($L$2:L52)) -> -23174.26 | O52: =IF(A52="","",SUMIF(RATEIOS!$A$2:$A$3142,$A52,RATEIOS!$F$2:$F$3142)) -> 23758.98 | P52: =IF(A52="","",(J52+K52+L52+M52)-O52) -> 0 | Q52: =IF(AND(J52=0,K52=0,L52=0,M52=0),"",IF(O52=0,"PENDENTE DE RATEIO",IF(ABS(P52)>0.005,"DIVERGÊNCIA",IF(COUNTIF(RATEIOS!$A$2:$A$3142,$A52)-COUNTIFS(RATEIOS!$A$2:$A$3142,$A52,RATEIOS!$D$2:$D$3142,"<>")>0,"NÃO CLASSIFICADO","RATEIO OK")))) -> RATEIO OK | R52: Conciliado
A53: BAN-00052 | B53: 52 | C53: 46037 | D53: =IF(C53="","",MONTH(C53)) -> 1 | E53: OUTROS | F53: RESGATE | G53: RESGATE BB CDB DI | H53: BANCO DO BRASIL - CDB DI | J53: 0 | K53: 0 | L53: 0 | M53: 23500 | N53: =IF(AND(C53="",J53=0,K53=0,L53=0,M53=0),"",CADASTROS!$B$4+SUM($J$2:J53)+SUM($M$2:M53)-SUM($K$2:K53)-SUM($L$2:L53)) -> 325.74 | O53: =IF(A53="","",SUMIF(RATEIOS!$A$2:$A$3142,$A53,RATEIOS!$F$2:$F$3142)) -> 23500 | P53: =IF(A53="","",(J53+K53+L53+M53)-O53) -> 0 | Q53: =IF(AND(J53=0,K53=0,L53=0,M53=0),"",IF(O53=0,"PENDENTE DE RATEIO",IF(ABS(P53)>0.005,"DIVERGÊNCIA",IF(COUNTIF(RATEIOS!$A$2:$A$3142,$A53)-COUNTIFS(RATEIOS!$A$2:$A$3142,$A53,RATEIOS!$D$2:$D$3142,"<>")>0,"NÃO CLASSIFICADO","RATEIO OK")))) -> RATEIO OK | R53: Conciliado
A54: BAN-00053 | B54: 53 | C54: 46038 | D54: =IF(C54="","",MONTH(C54)) -> 1 | E54: OUTROS | F54: RESGATE | G54: CDB/RDB | H54: BANCO DO BRASIL - CDB DI | J54: 0 | K54: 0 | L54: 0 | M54: 99.17 | N54: =IF(AND(C54="",J54=0,K54=0,L54=0,M54=0),"",CADASTROS!$B$4+SUM($J$2:J54)+SUM($M$2:M54)-SUM($K$2:K54)-SUM($L$2:L54)) -> 424.91 | O54: =IF(A54="","",SUMIF(RATEIOS!$A$2:$A$3142,$A54,RATEIOS!$F$2:$F$3142)) -> 99.17 | P54: =IF(A54="","",(J54+K54+L54+M54)-O54) -> 0 | Q54: =IF(AND(J54=0,K54=0,L54=0,M54=0),"",IF(O54=0,"PENDENTE DE RATEIO",IF(ABS(P54)>0.005,"DIVERGÊNCIA",IF(COUNTIF(RATEIOS!$A$2:$A$3142,$A54)-COUNTIFS(RATEIOS!$A$2:$A$3142,$A54,RATEIOS!$D$2:$D$3142,"<>")>0,"NÃO CLASSIFICADO","RATEIO OK")))) -> RATEIO OK | R54: Conciliado
A55: BAN-00054 | B55: 54 | C55: 46038 | D55: =IF(C55="","",MONTH(C55)) -> 1 | E55: BOLETO | F55: SAÍDA | G55: BB PAY (FORTES) - RELÓGIO DE PONTO | H55: FORTES CONECTA - RELÓGIO DE PONTO | I55: 408235 / 408236 / 359628 | J55: 0 | K55: 97.02 | L55: 0 | M55: 0 | N55: =IF(AND(C55="",J55=0,K55=0,L55=0,M55=0),"",CADASTROS!$B$4+SUM($J$2:J55)+SUM($M$2:M55)-SUM($K$2:K55)-SUM($L$2:L55)) -> 327.89 | O55: =IF(A55="","",SUMIF(RATEIOS!$A$2:$A$3142,$A55,RATEIOS!$F$2:$F$3142)) -> 97.02 | P55: =IF(A55="","",(J55+K55+L55+M55)-O55) -> 0 | Q55: =IF(AND(J55=0,K55=0,L55=0,M55=0),"",IF(O55=0,"PENDENTE DE RATEIO",IF(ABS(P55)>0.005,"DIVERGÊNCIA",IF(COUNTIF(RATEIOS!$A$2:$A$3142,$A55)-COUNTIFS(RATEIOS!$A$2:$A$3142,$A55,RATEIOS!$D$2:$D$3142,"<>")>0,"NÃO CLASSIFICADO","RATEIO OK")))) -> RATEIO OK | R55: Conciliado | S55: VENC. ERA DIA 15/01/2026 - R$ 95,00
A56: BAN-00055 | B56: 55 | C56: 46038 | D56: =IF(C56="","",MONTH(C56)) -> 1 | E56: BOLETO | F56: SAÍDA | G56: BB PAY (FORTES) - RELÓGIO DE PONTO | H56: FORTES CONECTA - RELÓGIO DE PONTO | I56: 103856 / 366901 | J56: 0 | K56: 211.41 | L56: 0 | M56: 0 | N56: =IF(AND(C56="",J56=0,K56=0,L56=0,M56=0),"",CADASTROS!$B$4+SUM($J$2:J56)+SUM($M$2:M56)-SUM($K$2:K56)-SUM($L$2:L56)) -> 116.48 | O56: =IF(A56="","",SUMIF(RATEIOS!$A$2:$A$3142,$A56,RATEIOS!$F$2:$F$3142)) -> 211.41 | P56: =IF(A56="","",(J56+K56+L56+M56)-O56) -> 0 | Q56: =IF(AND(J56=0,K56=0,L56=0,M56=0),"",IF(O56=0,"PENDENTE DE RATEIO",IF(ABS(P56)>0.005,"DIVERGÊNCIA",IF(COUNTIF(RATEIOS!$A$2:$A$3142,$A56)-COUNTIFS(RATEIOS!$A$2:$A$3142,$A56,RATEIOS!$D$2:$D$3142,"<>")>0,"NÃO CLASSIFICADO","RATEIO OK")))) -> RATEIO OK | R56: Conciliado | S56: VENC. ERA DIA 15/01/2026 - R$ 207,00
A57: BAN-00056 | B57: 56 | C57: 46038 | D57: =IF(C57="","",MONTH(C57)) -> 1 | E57: BOLETO | F57: SAÍDA | G57: BIOGREEN INCINERAÇÃO DE RESIDUOS (REF. COLETO LIXO INFECTANTE) - REF. 12/2025 | H57: BIOGREEN | I57: 112 | J57: 0 | K57: 1632.53 | L57: 0 | M57: 0 | N57: =IF(AND(C57="",J57=0,K57=0,L57=0,M57=0),"",CADASTROS!$B$4+SUM($J$2:J57)+SUM($M$2:M57)-SUM($K$2:K57)-SUM($L$2:L57)) -> -1516.05 | O57: =IF(A57="","",SUMIF(RATEIOS!$A$2:$A$3142,$A57,RATEIOS!$F$2:$F$3142)) -> 1632.53 | P57: =IF(A57="","",(J57+K57+L57+M57)-O57) -> 0 | Q57: =IF(AND(J57=0,K57=0,L57=0,M57=0),"",IF(O57=0,"PENDENTE DE RATEIO",IF(ABS(P57)>0.005,"DIVERGÊNCIA",IF(COUNTIF(RATEIOS!$A$2:$A$3142,$A57)-COUNTIFS(RATEIOS!$A$2:$A$3142,$A57,RATEIOS!$D$2:$D$3142,"<>")>0,"NÃO CLASSIFICADO","RATEIO OK")))) -> RATEIO OK | R57: Conciliado | S57: VENC. ERA DIA 15/01/2026 - R$ 1.600,00
A58: BAN-00057 | B58: 57 | C58: 46038 | D58: =IF(C58="","",MONTH(C58)) -> 1 | E58: BOLETO | F58: SAÍDA | G58: LEMOS BRANCO & CIA - POSTO PREMIUM (COMBUSTÍVEL CARRO) | H58: LEMOS BRANCO & CIA | I58: 2440 | J58: 0 | K58: 791.15 | L58: 0 | M58: 0 | N58: =IF(AND(C58="",J58=0,K58=0,L58=0,M58=0),"",CADASTROS!$B$4+SUM($J$2:J58)+SUM($M$2:M58)-SUM($K$2:K58)-SUM($L$2:L58)) -> -2307.2 | O58: =IF(A58="","",SUMIF(RATEIOS!$A$2:$A$3142,$A58,RATEIOS!$F$2:$F$3142)) -> 791.15 | P58: =IF(A58="","",(J58+K58+L58+M58)-O58) -> 0 | Q58: =IF(AND(J58=0,K58=0,L58=0,M58=0),"",IF(O58=0,"PENDENTE DE RATEIO",IF(ABS(P58)>0.005,"DIVERGÊNCIA",IF(COUNTIF(RATEIOS!$A$2:$A$3142,$A58)-COUNTIFS(RATEIOS!$A$2:$A$3142,$A58,RATEIOS!$D$2:$D$3142,"<>")>0,"NÃO CLASSIFICADO","RATEIO OK")))) -> RATEIO OK | R58: Conciliado
A59: BAN-00058 | B59: 58 | C59: 46038 | D59: =IF(C59="","",MONTH(C59)) -> 1 | E59: BOLETO | F59: SAÍDA | G59: FARMARIN INDUST. (REF. SORO DE 100 ML E 500 ML) 2/2 | H59: FARMARIN INDUST | I59: 445944 | J59: 0 | K59: 6578.4 | L59: 0 | M59: 0 | N59: =IF(AND(C59="",J59=0,K59=0,L59=0,M59=0),"",CADASTROS!$B$4+SUM($J$2:J59)+SUM($M$2:M59)-SUM($K$2:K59)-SUM($L$2:L59)) -> -8885.6 | O59: =IF(A59="","",SUMIF(RATEIOS!$A$2:$A$3142,$A59,RATEIOS!$F$2:$F$3142)) -> 6578.4 | P59: =IF(A59="","",(J59+K59+L59+M59)-O59) -> 0 | Q59: =IF(AND(J59=0,K59=0,L59=0,M59=0),"",IF(O59=0,"PENDENTE DE RATEIO",IF(ABS(P59)>0.005,"DIVERGÊNCIA",IF(COUNTIF(RATEIOS!$A$2:$A$3142,$A59)-COUNTIFS(RATEIOS!$A$2:$A$3142,$A59,RATEIOS!$D$2:$D$3142,"<>")>0,"NÃO CLASSIFICADO","RATEIO OK")))) -> RATEIO OK | R59: Conciliado
A60: BAN-00059 | B60: 59 | C60: 46038 | D60: =IF(C60="","",MONTH(C60)) -> 1 | E60: OUTROS | F60: RESGATE | G60: RESGATE BB CDB DI | H60: BANCO DO BRASIL - CDB DI | J60: 0 | K60: 0 | L60: 0 | M60: 9000 | N60: =IF(AND(C60="",J60=0,K60=0,L60=0,M60=0),"",CADASTROS!$B$4+SUM($J$2:J60)+SUM($M$2:M60)-SUM($K$2:K60)-SUM($L$2:L60)) -> 114.4 | O60: =IF(A60="","",SUMIF(RATEIOS!$A$2:$A$3142,$A60,RATEIOS!$F$2:$F$3142)) -> 9000 | P60: =IF(A60="","",(J60+K60+L60+M60)-O60) -> 0 | Q60: =IF(AND(J60=0,K60=0,L60=0,M60=0),"",IF(O60=0,"PENDENTE DE RATEIO",IF(ABS(P60)>0.005,"DIVERGÊNCIA",IF(COUNTIF(RATEIOS!$A$2:$A$3142,$A60)-COUNTIFS(RATEIOS!$A$2:$A$3142,$A60,RATEIOS!$D$2:$D$3142,"<>")>0,"NÃO CLASSIFICADO","RATEIO OK")))) -> RATEIO OK | R60: Conciliado
A61: BAN-00060 | B61: 60 | C61: 46041 | D61: =IF(C61="","",MONTH(C61)) -> 1 | E61: OUTROS | F61: RESGATE | G61: RESGATE BB CDB DI | H61: BANCO DO BRASIL - CDB DI | J61: 0 | K61: 0 | L61: 0 | M61: 42.48 | N61: =IF(AND(C61="",J61=0,K61=0,L61=0,M61=0),"",CADASTROS!$B$4+SUM($J$2:J61)+SUM($M$2:M61)-SUM($K$2:K61)-SUM($L$2:L61)) -> 156.88 | O61: =IF(A61="","",SUMIF(RATEIOS!$A$2:$A$3142,$A61,RATEIOS!$F$2:$F$3142)) -> 42.48 | P61: =IF(A61="","",(J61+K61+L61+M61)-O61) -> 0 | Q61: =IF(AND(J61=0,K61=0,L61=0,M61=0),"",IF(O61=0,"PENDENTE DE RATEIO",IF(ABS(P61)>0.005,"DIVERGÊNCIA",IF(COUNTIF(RATEIOS!$A$2:$A$3142,$A61)-COUNTIFS(RATEIOS!$A$2:$A$3142,$A61,RATEIOS!$D$2:$D$3142,"<>")>0,"NÃO CLASSIFICADO","RATEIO OK")))) -> RATEIO OK | R61: Conciliado
A62: BAN-00061 | B62: 61 | C62: 46041 | D62: =IF(C62="","",MONTH(C62)) -> 1 | E62: BOLETO | F62: SAÍDA | G62: NIPRO MEDICAL (REF. FILTROS MÁQUINAS) 2/2 | H62: NIPRO | I62: 22585 | J62: 0 | K62: 6437.5 | L62: 0 | M62: 0 | N62: =IF(AND(C62="",J62=0,K62=0,L62=0,M62=0),"",CADASTROS!$B$4+SUM($J$2:J62)+SUM($M$2:M62)-SUM($K$2:K62)-SUM($L$2:L62)) -> -6280.62 | O62: =IF(A62="","",SUMIF(RATEIOS!$A$2:$A$3142,$A62,RATEIOS!$F$2:$F$3142)) -> 6437.5 | P62: =IF(A62="","",(J62+K62+L62+M62)-O62) -> 0 | Q62: =IF(AND(J62=0,K62=0,L62=0,M62=0),"",IF(O62=0,"PENDENTE DE RATEIO",IF(ABS(P62)>0.005,"DIVERGÊNCIA",IF(COUNTIF(RATEIOS!$A$2:$A$3142,$A62)-COUNTIFS(RATEIOS!$A$2:$A$3142,$A62,RATEIOS!$D$2:$D$3142,"<>")>0,"NÃO CLASSIFICADO","RATEIO OK")))) -> RATEIO OK | R62: Conciliado | S62: VENC. ERA DIA 17/01/2026
A63: BAN-00062 | B63: 62 | C63: 46041 | D63: =IF(C63="","",MONTH(C63)) -> 1 | E63: BOLETO | F63: SAÍDA | G63: FARMARIN INDUST. (REF. SOROS) 1/2 | H63: FARMARIN INDUST | I63: 449787 | J63: 0 | K63: 1965.6 | L63: 0 | M63: 0 | N63: =IF(AND(C63="",J63=0,K63=0,L63=0,M63=0),"",CADASTROS!$B$4+SUM($J$2:J63)+SUM($M$2:M63)-SUM($K$2:K63)-SUM($L$2:L63)) -> -8246.22 | O63: =IF(A63="","",SUMIF(RATEIOS!$A$2:$A$3142,$A63,RATEIOS!$F$2:$F$3142)) -> 1965.6 | P63: =IF(A63="","",(J63+K63+L63+M63)-O63) -> 0 | Q63: =IF(AND(J63=0,K63=0,L63=0,M63=0),"",IF(O63=0,"PENDENTE DE RATEIO",IF(ABS(P63)>0.005,"DIVERGÊNCIA",IF(COUNTIF(RATEIOS!$A$2:$A$3142,$A63)-COUNTIFS(RATEIOS!$A$2:$A$3142,$A63,RATEIOS!$D$2:$D$3142,"<>")>0,"NÃO CLASSIFICADO","RATEIO OK")))) -> RATEIO OK | R63: Conciliado | S63: VENC. ERA DIA 17/01/2026
A64: BAN-00063 | B64: 63 | C64: 46041 | D64: =IF(C64="","",MONTH(C64)) -> 1 | E64: BOLETO | F64: SAÍDA | G64: FARMARIN INDUST. (REF. SOLUÇÕES) 1/2 | H64: FARMARIN INDUST | I64: 449808 | J64: 0 | K64: 17567 | L64: 0 | M64: 0 | N64: =IF(AND(C64="",J64=0,K64=0,L64=0,M64=0),"",CADASTROS!$B$4+SUM($J$2:J64)+SUM($M$2:M64)-SUM($K$2:K64)-SUM($L$2:L64)) -> -25813.22 | O64: =IF(A64="","",SUMIF(RATEIOS!$A$2:$A$3142,$A64,RATEIOS!$F$2:$F$3142)) -> 17567 | P64: =IF(A64="","",(J64+K64+L64+M64)-O64) -> 0 | Q64: =IF(AND(J64=0,K64=0,L64=0,M64=0),"",IF(O64=0,"PENDENTE DE RATEIO",IF(ABS(P64)>0.005,"DIVERGÊNCIA",IF(COUNTIF(RATEIOS!$A$2:$A$3142,$A64)-COUNTIFS(RATEIOS!$A$2:$A$3142,$A64,RATEIOS!$D$2:$D$3142,"<>")>0,"NÃO CLASSIFICADO","RATEIO OK")))) -> RATEIO OK | R64: Conciliado | S64: VENC. ERA DIA 17/01/2026
A65: BAN-00064 | B65: 64 | C65: 46041 | D65: =IF(C65="","",MONTH(C65)) -> 1 | E65: PIX | F65: SAÍDA | G65: E G BISPO TRANSPORTES (REF. FRETE DE MERCADORIA) | H65: E G BISPO TRANSPORTES | I65: 1189 | J65: 0 | K65: 200 | L65: 0 | M65: 0 | N65: =IF(AND(C65="",J65=0,K65=0,L65=0,M65=0),"",CADASTROS!$B$4+SUM($J$2:J65)+SUM($M$2:M65)-SUM($K$2:K65)-SUM($L$2:L65)) -> -26013.22 | O65: =IF(A65="","",SUMIF(RATEIOS!$A$2:$A$3142,$A65,RATEIOS!$F$2:$F$3142)) -> 200 | P65: =IF(A65="","",(J65+K65+L65+M65)-O65) -> 0 | Q65: =IF(AND(J65=0,K65=0,L65=0,M65=0),"",IF(O65=0,"PENDENTE DE RATEIO",IF(ABS(P65)>0.005,"DIVERGÊNCIA",IF(COUNTIF(RATEIOS!$A$2:$A$3142,$A65)-COUNTIFS(RATEIOS!$A$2:$A$3142,$A65,RATEIOS!$D$2:$D$3142,"<>")>0,"NÃO CLASSIFICADO","RATEIO OK")))) -> RATEIO OK | R65: Conciliado
A66: BAN-00065 | B66: 65 | C66: 46041 | D66: =IF(C66="","",MONTH(C66)) -> 1 | E66: PIX | F66: SAÍDA | G66: E M GONÇALVES PADARIA (REF. FORNEC. DE PÃES E BOLOS - DEZ/25) - FAVORECIDO: EDILBERTO M. GONÇALVES | H66: E M GONÇALVES PADARIA | I66: 164 | J66: 0 | K66: 1554 | L66: 0 | M66: 0 | N66: =IF(AND(C66="",J66=0,K66=0,L66=0,M66=0),"",CADASTROS!$B$4+SUM($J$2:J66)+SUM($M$2:M66)-SUM($K$2:K66)-SUM($L$2:L66)) -> -27567.22 | O66: =IF(A66="","",SUMIF(RATEIOS!$A$2:$A$3142,$A66,RATEIOS!$F$2:$F$3142)) -> 1554 | P66: =IF(A66="","",(J66+K66+L66+M66)-O66) -> 0 | Q66: =IF(AND(J66=0,K66=0,L66=0,M66=0),"",IF(O66=0,"PENDENTE DE RATEIO",IF(ABS(P66)>0.005,"DIVERGÊNCIA",IF(COUNTIF(RATEIOS!$A$2:$A$3142,$A66)-COUNTIFS(RATEIOS!$A$2:$A$3142,$A66,RATEIOS!$D$2:$D$3142,"<>")>0,"NÃO CLASSIFICADO","RATEIO OK")))) -> RATEIO OK | R66: Conciliado
A67: BAN-00066 | B67: 66 | C67: 46041 | D67: =IF(C67="","",MONTH(C67)) -> 1 | E67: PIX | F67: SAÍDA | G67: I F DA SILVA & CIA LTDA (REF. DEZ/2025) | H67: I F DA SILVA & CIA LTDA | I67: 3 | J67: 0 | K67: 8306.33 | L67: 0 | M67: 0 | N67: =IF(AND(C67="",J67=0,K67=0,L67=0,M67=0),"",CADASTROS!$B$4+SUM($J$2:J67)+SUM($M$2:M67)-SUM($K$2:K67)-SUM($L$2:L67)) -> -35873.55 | O67: =IF(A67="","",SUMIF(RATEIOS!$A$2:$A$3142,$A67,RATEIOS!$F$2:$F$3142)) -> 8306.33 | P67: =IF(A67="","",(J67+K67+L67+M67)-O67) -> 0 | Q67: =IF(AND(J67=0,K67=0,L67=0,M67=0),"",IF(O67=0,"PENDENTE DE RATEIO",IF(ABS(P67)>0.005,"DIVERGÊNCIA",IF(COUNTIF(RATEIOS!$A$2:$A$3142,$A67)-COUNTIFS(RATEIOS!$A$2:$A$3142,$A67,RATEIOS!$D$2:$D$3142,"<>")>0,"NÃO CLASSIFICADO","RATEIO OK")))) -> RATEIO OK | R67: Conciliado
A68: BAN-00067 | B68: 67 | C68: 46041 | D68: =IF(C68="","",MONTH(C68)) -> 1 | E68: TRANSFERÊNCIA | F68: SAÍDA | G68: CASAMATER (REF. NOV/2025) | H68: CASAMATER | I68: 70375 | J68: 0 | K68: 4600 | L68: 0 | M68: 0 | N68: =IF(AND(C68="",J68=0,K68=0,L68=0,M68=0),"",CADASTROS!$B$4+SUM($J$2:J68)+SUM($M$2:M68)-SUM($K$2:K68)-SUM($L$2:L68)) -> -40473.55 | O68: =IF(A68="","",SUMIF(RATEIOS!$A$2:$A$3142,$A68,RATEIOS!$F$2:$F$3142)) -> 4600 | P68: =IF(A68="","",(J68+K68+L68+M68)-O68) -> 0 | Q68: =IF(AND(J68=0,K68=0,L68=0,M68=0),"",IF(O68=0,"PENDENTE DE RATEIO",IF(ABS(P68)>0.005,"DIVERGÊNCIA",IF(COUNTIF(RATEIOS!$A$2:$A$3142,$A68)-COUNTIFS(RATEIOS!$A$2:$A$3142,$A68,RATEIOS!$D$2:$D$3142,"<>")>0,"NÃO CLASSIFICADO","RATEIO OK")))) -> RATEIO OK | R68: Conciliado
A69: BAN-00068 | B69: 68 | C69: 46041 | D69: =IF(C69="","",MONTH(C69)) -> 1 | E69: OUTROS | F69: RESGATE | G69: RESGATE BB CDB DI | H69: BANCO DO BRASIL - CDB DI | J69: 0 | K69: 0 | L69: 0 | M69: 40500 | N69: =IF(AND(C69="",J69=0,K69=0,L69=0,M69=0),"",CADASTROS!$B$4+SUM($J$2:J69)+SUM($M$2:M69)-SUM($K$2:K69)-SUM($L$2:L69)) -> 26.45 | O69: =IF(A69="","",SUMIF(RATEIOS!$A$2:$A$3142,$A69,RATEIOS!$F$2:$F$3142)) -> 40500 | P69: =IF(A69="","",(J69+K69+L69+M69)-O69) -> 0 | Q69: =IF(AND(J69=0,K69=0,L69=0,M69=0),"",IF(O69=0,"PENDENTE DE RATEIO",IF(ABS(P69)>0.005,"DIVERGÊNCIA",IF(COUNTIF(RATEIOS!$A$2:$A$3142,$A69)-COUNTIFS(RATEIOS!$A$2:$A$3142,$A69,RATEIOS!$D$2:$D$3142,"<>")>0,"NÃO CLASSIFICADO","RATEIO OK")))) -> RATEIO OK | R69: Conciliado
A70: BAN-00069 | B70: 69 | C70: 46042 | D70: =IF(C70="","",MONTH(C70)) -> 1 | E70: OUTROS | F70: RESGATE | G70: RESGATE BB CDB DI | H70: BANCO DO BRASIL - CDB DI | J70: 0 | K70: 0 | L70: 0 | M70: 230.04 | N70: =IF(AND(C70="",J70=0,K70=0,L70=0,M70=0),"",CADASTROS!$B$4+SUM($J$2:J70)+SUM($M$2:M70)-SUM($K$2:K70)-SUM($L$2:L70)) -> 256.49 | O70: =IF(A70="","",SUMIF(RATEIOS!$A$2:$A$3142,$A70,RATEIOS!$F$2:$F$3142)) -> 230.04 | P70: =IF(A70="","",(J70+K70+L70+M70)-O70) -> 0 | Q70: =IF(AND(J70=0,K70=0,L70=0,M70=0),"",IF(O70=0,"PENDENTE DE RATEIO",IF(ABS(P70)>0.005,"DIVERGÊNCIA",IF(COUNTIF(RATEIOS!$A$2:$A$3142,$A70)-COUNTIFS(RATEIOS!$A$2:$A$3142,$A70,RATEIOS!$D$2:$D$3142,"<>")>0,"NÃO CLASSIFICADO","RATEIO OK")))) -> RATEIO OK | R70: Conciliado
A71: BAN-00070 | B71: 70 | C71: 46042 | D71: =IF(C71="","",MONTH(C71)) -> 1 | E71: BOLETO | F71: SAÍDA | G71: CRISTALIA PRODUTOS (REF. HEPARINAS) 3/3 | H71: CRISTALIA PRODUTOS | I71: 818699 | J71: 0 | K71: 10332.3 | L71: 0 | M71: 0 | N71: =IF(AND(C71="",J71=0,K71=0,L71=0,M71=0),"",CADASTROS!$B$4+SUM($J$2:J71)+SUM($M$2:M71)-SUM($K$2:K71)-SUM($L$2:L71)) -> -10075.81 | O71: =IF(A71="","",SUMIF(RATEIOS!$A$2:$A$3142,$A71,RATEIOS!$F$2:$F$3142)) -> 10332.3 | P71: =IF(A71="","",(J71+K71+L71+M71)-O71) -> 0 | Q71: =IF(AND(J71=0,K71=0,L71=0,M71=0),"",IF(O71=0,"PENDENTE DE RATEIO",IF(ABS(P71)>0.005,"DIVERGÊNCIA",IF(COUNTIF(RATEIOS!$A$2:$A$3142,$A71)-COUNTIFS(RATEIOS!$A$2:$A$3142,$A71,RATEIOS!$D$2:$D$3142,"<>")>0,"NÃO CLASSIFICADO","RATEIO OK")))) -> RATEIO OK | R71: Conciliado
A72: BAN-00071 | B72: 71 | C72: 46042 | D72: =IF(C72="","",MONTH(C72)) -> 1 | E72: PIX | F72: SAÍDA | G72: FGTS (13º SALÁRIO) | H72: FGTS | J72: 0 | K72: 984.93 | L72: 0 | M72: 0 | N72: =IF(AND(C72="",J72=0,K72=0,L72=0,M72=0),"",CADASTROS!$B$4+SUM($J$2:J72)+SUM($M$2:M72)-SUM($K$2:K72)-SUM($L$2:L72)) -> -11060.74 | O72: =IF(A72="","",SUMIF(RATEIOS!$A$2:$A$3142,$A72,RATEIOS!$F$2:$F$3142)) -> 984.93 | P72: =IF(A72="","",(J72+K72+L72+M72)-O72) -> 0 | Q72: =IF(AND(J72=0,K72=0,L72=0,M72=0),"",IF(O72=0,"PENDENTE DE RATEIO",IF(ABS(P72)>0.005,"DIVERGÊNCIA",IF(COUNTIF(RATEIOS!$A$2:$A$3142,$A72)-COUNTIFS(RATEIOS!$A$2:$A$3142,$A72,RATEIOS!$D$2:$D$3142,"<>")>0,"NÃO CLASSIFICADO","RATEIO OK")))) -> RATEIO OK | R72: Conciliado
A73: BAN-00072 | B73: 72 | C73: 46042 | D73: =IF(C73="","",MONTH(C73)) -> 1 | E73: PIX | F73: SAÍDA | G73: FGTS (12/2025) | H73: FGTS | J73: 0 | K73: 5097.67 | L73: 0 | M73: 0 | N73: =IF(AND(C73="",J73=0,K73=0,L73=0,M73=0),"",CADASTROS!$B$4+SUM($J$2:J73)+SUM($M$2:M73)-SUM($K$2:K73)-SUM($L$2:L73)) -> -16158.41 | O73: =IF(A73="","",SUMIF(RATEIOS!$A$2:$A$3142,$A73,RATEIOS!$F$2:$F$3142)) -> 5097.67 | P73: =IF(A73="","",(J73+K73+L73+M73)-O73) -> 0 | Q73: =IF(AND(J73=0,K73=0,L73=0,M73=0),"",IF(O73=0,"PENDENTE DE RATEIO",IF(ABS(P73)>0.005,"DIVERGÊNCIA",IF(COUNTIF(RATEIOS!$A$2:$A$3142,$A73)-COUNTIFS(RATEIOS!$A$2:$A$3142,$A73,RATEIOS!$D$2:$D$3142,"<>")>0,"NÃO CLASSIFICADO","RATEIO OK")))) -> RATEIO OK | R73: Conciliado
A74: BAN-00073 | B74: 73 | C74: 46042 | D74: =IF(C74="","",MONTH(C74)) -> 1 | E74: DARF | F74: SAÍDA | G74: INSS (12/2025) | H74: INSS | J74: 0 | K74: 20075.85 | L74: 0 | M74: 0 | N74: =IF(AND(C74="",J74=0,K74=0,L74=0,M74=0),"",CADASTROS!$B$4+SUM($J$2:J74)+SUM($M$2:M74)-SUM($K$2:K74)-SUM($L$2:L74)) -> -36234.26 | O74: =IF(A74="","",SUMIF(RATEIOS!$A$2:$A$3142,$A74,RATEIOS!$F$2:$F$3142)) -> 20075.85 | P74: =IF(A74="","",(J74+K74+L74+M74)-O74) -> 0 | Q74: =IF(AND(J74=0,K74=0,L74=0,M74=0),"",IF(O74=0,"PENDENTE DE RATEIO",IF(ABS(P74)>0.005,"DIVERGÊNCIA",IF(COUNTIF(RATEIOS!$A$2:$A$3142,$A74)-COUNTIFS(RATEIOS!$A$2:$A$3142,$A74,RATEIOS!$D$2:$D$3142,"<>")>0,"NÃO CLASSIFICADO","RATEIO OK")))) -> RATEIO OK | R74: Conciliado
A75: BAN-00074 | B75: 74 | C75: 46042 | D75: =IF(C75="","",MONTH(C75)) -> 1 | E75: DARF | F75: SAÍDA | G75: DARF - RETENÇÕES (PIS/COFINS/CSLL) | H75: TRIBUTOS FEDEREIAS MENSAIS | J75: 0 | K75: 57.77 | L75: 0 | M75: 0 | N75: =IF(AND(C75="",J75=0,K75=0,L75=0,M75=0),"",CADASTROS!$B$4+SUM($J$2:J75)+SUM($M$2:M75)-SUM($K$2:K75)-SUM($L$2:L75)) -> -36292.03 | O75: =IF(A75="","",SUMIF(RATEIOS!$A$2:$A$3142,$A75,RATEIOS!$F$2:$F$3142)) -> 57.77 | P75: =IF(A75="","",(J75+K75+L75+M75)-O75) -> 0 | Q75: =IF(AND(J75=0,K75=0,L75=0,M75=0),"",IF(O75=0,"PENDENTE DE RATEIO",IF(ABS(P75)>0.005,"DIVERGÊNCIA",IF(COUNTIF(RATEIOS!$A$2:$A$3142,$A75)-COUNTIFS(RATEIOS!$A$2:$A$3142,$A75,RATEIOS!$D$2:$D$3142,"<>")>0,"NÃO CLASSIFICADO","RATEIO OK")))) -> RATEIO OK | R75: Conciliado
A76: BAN-00075 | B76: 75 | C76: 46042 | D76: =IF(C76="","",MONTH(C76)) -> 1 | E76: DARF | F76: SAÍDA | G76: DARF - RETENÇÕES (IRRF) | H76: TRIBUTOS FEDEREIAS MENSAIS | J76: 0 | K76: 18.64 | L76: 0 | M76: 0 | N76: =IF(AND(C76="",J76=0,K76=0,L76=0,M76=0),"",CADASTROS!$B$4+SUM($J$2:J76)+SUM($M$2:M76)-SUM($K$2:K76)-SUM($L$2:L76)) -> -36310.67 | O76: =IF(A76="","",SUMIF(RATEIOS!$A$2:$A$3142,$A76,RATEIOS!$F$2:$F$3142)) -> 18.64 | P76: =IF(A76="","",(J76+K76+L76+M76)-O76) -> 0 | Q76: =IF(AND(J76=0,K76=0,L76=0,M76=0),"",IF(O76=0,"PENDENTE DE RATEIO",IF(ABS(P76)>0.005,"DIVERGÊNCIA",IF(COUNTIF(RATEIOS!$A$2:$A$3142,$A76)-COUNTIFS(RATEIOS!$A$2:$A$3142,$A76,RATEIOS!$D$2:$D$3142,"<>")>0,"NÃO CLASSIFICADO","RATEIO OK")))) -> RATEIO OK | R76: Conciliado
A77: BAN-00076 | B77: 76 | C77: 46042 | D77: =IF(C77="","",MONTH(C77)) -> 1 | E77: OUTROS | F77: RESGATE | G77: RESGATE BB CDB DI | H77: BANCO DO BRASIL - CDB DI | J77: 0 | K77: 0 | L77: 0 | M77: 36500 | N77: =IF(AND(C77="",J77=0,K77=0,L77=0,M77=0),"",CADASTROS!$B$4+SUM($J$2:J77)+SUM($M$2:M77)-SUM($K$2:K77)-SUM($L$2:L77)) -> 189.33 | O77: =IF(A77="","",SUMIF(RATEIOS!$A$2:$A$3142,$A77,RATEIOS!$F$2:$F$3142)) -> 36500 | P77: =IF(A77="","",(J77+K77+L77+M77)-O77) -> 0 | Q77: =IF(AND(J77=0,K77=0,L77=0,M77=0),"",IF(O77=0,"PENDENTE DE RATEIO",IF(ABS(P77)>0.005,"DIVERGÊNCIA",IF(COUNTIF(RATEIOS!$A$2:$A$3142,$A77)-COUNTIFS(RATEIOS!$A$2:$A$3142,$A77,RATEIOS!$D$2:$D$3142,"<>")>0,"NÃO CLASSIFICADO","RATEIO OK")))) -> RATEIO OK | R77: Conciliado
A78: BAN-00077 | B78: 77 | C78: 46043 | D78: =IF(C78="","",MONTH(C78)) -> 1 | E78: OUTROS | F78: RESGATE | G78: RESGATE BB CDB DI | H78: BANCO DO BRASIL - CDB DI | J78: 0 | K78: 0 | L78: 0 | M78: 228.49 | N78: =IF(AND(C78="",J78=0,K78=0,L78=0,M78=0),"",CADASTROS!$B$4+SUM($J$2:J78)+SUM($M$2:M78)-SUM($K$2:K78)-SUM($L$2:L78)) -> 417.82 | O78: =IF(A78="","",SUMIF(RATEIOS!$A$2:$A$3142,$A78,RATEIOS!$F$2:$F$3142)) -> 228.49 | P78: =IF(A78="","",(J78+K78+L78+M78)-O78) -> 0 | Q78: =IF(AND(J78=0,K78=0,L78=0,M78=0),"",IF(O78=0,"PENDENTE DE RATEIO",IF(ABS(P78)>0.005,"DIVERGÊNCIA",IF(COUNTIF(RATEIOS!$A$2:$A$3142,$A78)-COUNTIFS(RATEIOS!$A$2:$A$3142,$A78,RATEIOS!$D$2:$D$3142,"<>")>0,"NÃO CLASSIFICADO","RATEIO OK")))) -> RATEIO OK | R78: Conciliado
A79: BAN-00078 | B79: 78 | C79: 46043 | D79: =IF(C79="","",MONTH(C79)) -> 1 | E79: BOLETO | F79: SAÍDA | G79: J SUL DISTRIBUIDORA (REF. INSUMOS) 2/3 | H79: J SUL DISTRIBUIDORA | I79: 47395 | J79: 0 | K79: 640.65 | L79: 0 | M79: 0 | N79: =IF(AND(C79="",J79=0,K79=0,L79=0,M79=0),"",CADASTROS!$B$4+SUM($J$2:J79)+SUM($M$2:M79)-SUM($K$2:K79)-SUM($L$2:L79)) -> -222.83 | O79: =IF(A79="","",SUMIF(RATEIOS!$A$2:$A$3142,$A79,RATEIOS!$F$2:$F$3142)) -> 640.65 | P79: =IF(A79="","",(J79+K79+L79+M79)-O79) -> 0 | Q79: =IF(AND(J79=0,K79=0,L79=0,M79=0),"",IF(O79=0,"PENDENTE DE RATEIO",IF(ABS(P79)>0.005,"DIVERGÊNCIA",IF(COUNTIF(RATEIOS!$A$2:$A$3142,$A79)-COUNTIFS(RATEIOS!$A$2:$A$3142,$A79,RATEIOS!$D$2:$D$3142,"<>")>0,"NÃO CLASSIFICADO","RATEIO OK")))) -> RATEIO OK | R79: Conciliado
A80: BAN-00079 | B80: 79 | C80: 46043 | D80: =IF(C80="","",MONTH(C80)) -> 1 | E80: BOLETO | F80: SAÍDA | G80: NIPRO MEDICAL (REF. CAPILAR 190) 2/2 | H80: NIPRO | I80: 179173 | J80: 0 | K80: 2904 | L80: 0 | M80: 0 | N80: =IF(AND(C80="",J80=0,K80=0,L80=0,M80=0),"",CADASTROS!$B$4+SUM($J$2:J80)+SUM($M$2:M80)-SUM($K$2:K80)-SUM($L$2:L80)) -> -3126.83 | O80: =IF(A80="","",SUMIF(RATEIOS!$A$2:$A$3142,$A80,RATEIOS!$F$2:$F$3142)) -> 2904 | P80: =IF(A80="","",(J80+K80+L80+M80)-O80) -> 0 | Q80: =IF(AND(J80=0,K80=0,L80=0,M80=0),"",IF(O80=0,"PENDENTE DE RATEIO",IF(ABS(P80)>0.005,"DIVERGÊNCIA",IF(COUNTIF(RATEIOS!$A$2:$A$3142,$A80)-COUNTIFS(RATEIOS!$A$2:$A$3142,$A80,RATEIOS!$D$2:$D$3142,"<>")>0,"NÃO CLASSIFICADO","RATEIO OK")))) -> RATEIO OK | R80: Conciliado
A81: BAN-00080 | B81: 80 | C81: 46043 | D81: =IF(C81="","",MONTH(C81)) -> 1 | E81: OUTROS | F81: RESGATE | G81: RESGATE BB CDB DI | H81: BANCO DO BRASIL - CDB DI | J81: 0 | K81: 0 | L81: 0 | M81: 3500 | N81: =IF(AND(C81="",J81=0,K81=0,L81=0,M81=0),"",CADASTROS!$B$4+SUM($J$2:J81)+SUM($M$2:M81)-SUM($K$2:K81)-SUM($L$2:L81)) -> 373.17 | O81: =IF(A81="","",SUMIF(RATEIOS!$A$2:$A$3142,$A81,RATEIOS!$F$2:$F$3142)) -> 3500 | P81: =IF(A81="","",(J81+K81+L81+M81)-O81) -> 0 | Q81: =IF(AND(J81=0,K81=0,L81=0,M81=0),"",IF(O81=0,"PENDENTE DE RATEIO",IF(ABS(P81)>0.005,"DIVERGÊNCIA",IF(COUNTIF(RATEIOS!$A$2:$A$3142,$A81)-COUNTIFS(RATEIOS!$A$2:$A$3142,$A81,RATEIOS!$D$2:$D$3142,"<>")>0,"NÃO CLASSIFICADO","RATEIO OK")))) -> RATEIO OK | R81: Conciliado
A82: BAN-00081 | B82: 81 | C82: 46044 | D82: =IF(C82="","",MONTH(C82)) -> 1 | E82: OUTROS | F82: RESGATE | G82: RESGATE BB CDB DI | H82: BANCO DO BRASIL - CDB DI | J82: 0 | K82: 0 | L82: 0 | M82: 24.15 | N82: =IF(AND(C82="",J82=0,K82=0,L82=0,M82=0),"",CADASTROS!$B$4+SUM($J$2:J82)+SUM($M$2:M82)-SUM($K$2:K82)-SUM($L$2:L82)) -> 397.32 | O82: =IF(A82="","",SUMIF(RATEIOS!$A$2:$A$3142,$A82,RATEIOS!$F$2:$F$3142)) -> 24.15 | P82: =IF(A82="","",(J82+K82+L82+M82)-O82) -> 0 | Q82: =IF(AND(J82=0,K82=0,L82=0,M82=0),"",IF(O82=0,"PENDENTE DE RATEIO",IF(ABS(P82)>0.005,"DIVERGÊNCIA",IF(COUNTIF(RATEIOS!$A$2:$A$3142,$A82)-COUNTIFS(RATEIOS!$A$2:$A$3142,$A82,RATEIOS!$D$2:$D$3142,"<>")>0,"NÃO CLASSIFICADO","RATEIO OK")))) -> RATEIO OK | R82: Conciliado
A83: BAN-00082 | B83: 82 | C83: 46045 | D83: =IF(C83="","",MONTH(C83)) -> 1 | E83: TRANSFERÊNCIA | F83: SAÍDA | G83: CLAUDIANE C. SILVA (REF. HAVER VIAGEM PARA HTI - 24/01) | H83: CLAUDIANE CARDOSO DA SILVA (CARRO HTI) | I83: NF AVULSA - 2477 | J83: 0 | K83: 700 | L83: 0 | M83: 0 | N83: =IF(AND(C83="",J83=0,K83=0,L83=0,M83=0),"",CADASTROS!$B$4+SUM($J$2:J83)+SUM($M$2:M83)-SUM($K$2:K83)-SUM($L$2:L83)) -> -302.68 | O83: =IF(A83="","",SUMIF(RATEIOS!$A$2:$A$3142,$A83,RATEIOS!$F$2:$F$3142)) -> 700 | P83: =IF(A83="","",(J83+K83+L83+M83)-O83) -> 0 | Q83: =IF(AND(J83=0,K83=0,L83=0,M83=0),"",IF(O83=0,"PENDENTE DE RATEIO",IF(ABS(P83)>0.005,"DIVERGÊNCIA",IF(COUNTIF(RATEIOS!$A$2:$A$3142,$A83)-COUNTIFS(RATEIOS!$A$2:$A$3142,$A83,RATEIOS!$D$2:$D$3142,"<>")>0,"NÃO CLASSIFICADO","RATEIO OK")))) -> RATEIO OK | R83: Conciliado | S83: NF EMITIDA EM 27/01 - NO VALOR DE R$ 1.176,00 (ENTRADA - R$ 700,00 + VALOR RESTANTE - R$ 476,00 - 10/02) - DESCONTO DE R$ 154,00 INSS
A84: BAN-00083 | B84: 83 | C84: 46045 | D84: =IF(C84="","",MONTH(C84)) -> 1 | E84: DARF | F84: SAÍDA | G84: PIS (REF. NF 004 – COMP. OUT/2025 E NF 005 – COMP. NOV/2025 – RECEB. DEZEMBRO/2025) | H84: PIS | J84: 0 | K84: 6347.44 | L84: 0 | M84: 0 | N84: =IF(AND(C84="",J84=0,K84=0,L84=0,M84=0),"",CADASTROS!$B$4+SUM($J$2:J84)+SUM($M$2:M84)-SUM($K$2:K84)-SUM($L$2:L84)) -> -6650.12 | O84: =IF(A84="","",SUMIF(RATEIOS!$A$2:$A$3142,$A84,RATEIOS!$F$2:$F$3142)) -> 6347.44 | P84: =IF(A84="","",(J84+K84+L84+M84)-O84) -> 0 | Q84: =IF(AND(J84=0,K84=0,L84=0,M84=0),"",IF(O84=0,"PENDENTE DE RATEIO",IF(ABS(P84)>0.005,"DIVERGÊNCIA",IF(COUNTIF(RATEIOS!$A$2:$A$3142,$A84)-COUNTIFS(RATEIOS!$A$2:$A$3142,$A84,RATEIOS!$D$2:$D$3142,"<>")>0,"NÃO CLASSIFICADO","RATEIO OK")))) -> RATEIO OK | R84: Conciliado
A85: BAN-00084 | B85: 84 | C85: 46045 | D85: =IF(C85="","",MONTH(C85)) -> 1 | E85: DARF | F85: SAÍDA | G85: COFINS (REF. NF 004 – COMP. OUT/2025 E NF 005 – COMP. NOV/2025 – RECEB. DEZEMBRO/2025) | H85: COFINS | J85: 0 | K85: 29295.9 | L85: 0 | M85: 0 | N85: =IF(AND(C85="",J85=0,K85=0,L85=0,M85=0),"",CADASTROS!$B$4+SUM($J$2:J85)+SUM($M$2:M85)-SUM($K$2:K85)-SUM($L$2:L85)) -> -35946.02 | O85: =IF(A85="","",SUMIF(RATEIOS!$A$2:$A$3142,$A85,RATEIOS!$F$2:$F$3142)) -> 29295.9 | P85: =IF(A85="","",(J85+K85+L85+M85)-O85) -> 0 | Q85: =IF(AND(J85=0,K85=0,L85=0,M85=0),"",IF(O85=0,"PENDENTE DE RATEIO",IF(ABS(P85)>0.005,"DIVERGÊNCIA",IF(COUNTIF(RATEIOS!$A$2:$A$3142,$A85)-COUNTIFS(RATEIOS!$A$2:$A$3142,$A85,RATEIOS!$D$2:$D$3142,"<>")>0,"NÃO CLASSIFICADO","RATEIO OK")))) -> RATEIO OK | R85: Conciliado
A86: BAN-00085 | B86: 85 | C86: 46045 | D86: =IF(C86="","",MONTH(C86)) -> 1 | E86: OUTROS | F86: RESGATE | G86: RESGATE BB CDB DI | H86: BANCO DO BRASIL - CDB DI | J86: 0 | K86: 0 | L86: 0 | M86: 36000 | N86: =IF(AND(C86="",J86=0,K86=0,L86=0,M86=0),"",CADASTROS!$B$4+SUM($J$2:J86)+SUM($M$2:M86)-SUM($K$2:K86)-SUM($L$2:L86)) -> 53.98 | O86: =IF(A86="","",SUMIF(RATEIOS!$A$2:$A$3142,$A86,RATEIOS!$F$2:$F$3142)) -> 36000 | P86: =IF(A86="","",(J86+K86+L86+M86)-O86) -> 0 | Q86: =IF(AND(J86=0,K86=0,L86=0,M86=0),"",IF(O86=0,"PENDENTE DE RATEIO",IF(ABS(P86)>0.005,"DIVERGÊNCIA",IF(COUNTIF(RATEIOS!$A$2:$A$3142,$A86)-COUNTIFS(RATEIOS!$A$2:$A$3142,$A86,RATEIOS!$D$2:$D$3142,"<>")>0,"NÃO CLASSIFICADO","RATEIO OK")))) -> RATEIO OK | R86: Conciliado
A87: BAN-00086 | B87: 86 | C87: 46048 | D87: =IF(C87="","",MONTH(C87)) -> 1 | E87: OUTROS | F87: RESGATE | G87: CDB/RDB | H87: BANCO DO BRASIL - CDB DI | J87: 0 | K87: 0 | L87: 0 | M87: 293.76 | N87: =IF(AND(C87="",J87=0,K87=0,L87=0,M87=0),"",CADASTROS!$B$4+SUM($J$2:J87)+SUM($M$2:M87)-SUM($K$2:K87)-SUM($L$2:L87)) -> 347.74 | O87: =IF(A87="","",SUMIF(RATEIOS!$A$2:$A$3142,$A87,RATEIOS!$F$2:$F$3142)) -> 293.76 | P87: =IF(A87="","",(J87+K87+L87+M87)-O87) -> 0 | Q87: =IF(AND(J87=0,K87=0,L87=0,M87=0),"",IF(O87=0,"PENDENTE DE RATEIO",IF(ABS(P87)>0.005,"DIVERGÊNCIA",IF(COUNTIF(RATEIOS!$A$2:$A$3142,$A87)-COUNTIFS(RATEIOS!$A$2:$A$3142,$A87,RATEIOS!$D$2:$D$3142,"<>")>0,"NÃO CLASSIFICADO","RATEIO OK")))) -> RATEIO OK | R87: Conciliado
A88: BAN-00087 | B88: 87 | C88: 46048 | D88: =IF(C88="","",MONTH(C88)) -> 1 | E88: TRANSFERÊNCIA | F88: SAÍDA | G88: A A DA SILVA LTDA (REF. FARDAMENTOS FUNCIONÁRIOS) - HAVER | H88: A A DA SILVA LTDA | I88: 1449 | J88: 0 | K88: 455 | L88: 0 | M88: 0 | N88: =IF(AND(C88="",J88=0,K88=0,L88=0,M88=0),"",CADASTROS!$B$4+SUM($J$2:J88)+SUM($M$2:M88)-SUM($K$2:K88)-SUM($L$2:L88)) -> -107.26 | O88: =IF(A88="","",SUMIF(RATEIOS!$A$2:$A$3142,$A88,RATEIOS!$F$2:$F$3142)) -> 455 | P88: =IF(A88="","",(J88+K88+L88+M88)-O88) -> 0 | Q88: =IF(AND(J88=0,K88=0,L88=0,M88=0),"",IF(O88=0,"PENDENTE DE RATEIO",IF(ABS(P88)>0.005,"DIVERGÊNCIA",IF(COUNTIF(RATEIOS!$A$2:$A$3142,$A88)-COUNTIFS(RATEIOS!$A$2:$A$3142,$A88,RATEIOS!$D$2:$D$3142,"<>")>0,"NÃO CLASSIFICADO","RATEIO OK")))) -> RATEIO OK | R88: Conciliado | S88: NF N°1449 EMITIDA EM: 04/03/2026 - ADIANTAMENTO DE R$455,00 FEITO EM 26/01 - QUITAÇÃO EM 04/03 NO VALOR DE R$525,00
A89: BAN-00088 | B89: 88 | C89: 46048 | D89: =IF(C89="","",MONTH(C89)) -> 1 | E89: BOLETO | F89: SAÍDA | G89: COOP. UNIMED (REF. COMPRESA DE GAZE) 1/3 | H89: COOP. UNIMED | I89: 628262 | J89: 0 | K89: 1042.92 | L89: 0 | M89: 0 | N89: =IF(AND(C89="",J89=0,K89=0,L89=0,M89=0),"",CADASTROS!$B$4+SUM($J$2:J89)+SUM($M$2:M89)-SUM($K$2:K89)-SUM($L$2:L89)) -> -1150.18 | O89: =IF(A89="","",SUMIF(RATEIOS!$A$2:$A$3142,$A89,RATEIOS!$F$2:$F$3142)) -> 1042.92 | P89: =IF(A89="","",(J89+K89+L89+M89)-O89) -> 0 | Q89: =IF(AND(J89=0,K89=0,L89=0,M89=0),"",IF(O89=0,"PENDENTE DE RATEIO",IF(ABS(P89)>0.005,"DIVERGÊNCIA",IF(COUNTIF(RATEIOS!$A$2:$A$3142,$A89)-COUNTIFS(RATEIOS!$A$2:$A$3142,$A89,RATEIOS!$D$2:$D$3142,"<>")>0,"NÃO CLASSIFICADO","RATEIO OK")))) -> RATEIO OK | R89: Conciliado | S89: VENC. ERA DIA 22/01 - VALOR: R$ 1.037,40
A90: BAN-00089 | B90: 89 | C90: 46048 | D90: =IF(C90="","",MONTH(C90)) -> 1 | E90: BOLETO | F90: SAÍDA | G90: BIOCOMPANY (REF. CURATIVOS, CATETER E PERMICATH) 2/2 | H90: BIOCOMPANY | I90: 76843 | J90: 0 | K90: 1867.5 | L90: 0 | M90: 0 | N90: =IF(AND(C90="",J90=0,K90=0,L90=0,M90=0),"",CADASTROS!$B$4+SUM($J$2:J90)+SUM($M$2:M90)-SUM($K$2:K90)-SUM($L$2:L90)) -> -3017.68 | O90: =IF(A90="","",SUMIF(RATEIOS!$A$2:$A$3142,$A90,RATEIOS!$F$2:$F$3142)) -> 1867.5 | P90: =IF(A90="","",(J90+K90+L90+M90)-O90) -> 0 | Q90: =IF(AND(J90=0,K90=0,L90=0,M90=0),"",IF(O90=0,"PENDENTE DE RATEIO",IF(ABS(P90)>0.005,"DIVERGÊNCIA",IF(COUNTIF(RATEIOS!$A$2:$A$3142,$A90)-COUNTIFS(RATEIOS!$A$2:$A$3142,$A90,RATEIOS!$D$2:$D$3142,"<>")>0,"NÃO CLASSIFICADO","RATEIO OK")))) -> RATEIO OK | R90: Conciliado
A91: BAN-00090 | B91: 90 | C91: 46048 | D91: =IF(C91="","",MONTH(C91)) -> 1 | E91: BOLETO | F91: SAÍDA | G91: ULTRAMEGA DISTRIBUIDORA (REF. INSUMOS: AGULHAS, FITAS, SERINGAS...ETC) 2/2 | H91: ULTRAMEGA DISTRIBUIDORA | I91: 273457 | J91: 0 | K91: 1242.43 | L91: 0 | M91: 0 | N91: =IF(AND(C91="",J91=0,K91=0,L91=0,M91=0),"",CADASTROS!$B$4+SUM($J$2:J91)+SUM($M$2:M91)-SUM($K$2:K91)-SUM($L$2:L91)) -> -4260.11 | O91: =IF(A91="","",SUMIF(RATEIOS!$A$2:$A$3142,$A91,RATEIOS!$F$2:$F$3142)) -> 1242.43 | P91: =IF(A91="","",(J91+K91+L91+M91)-O91) -> 0 | Q91: =IF(AND(J91=0,K91=0,L91=0,M91=0),"",IF(O91=0,"PENDENTE DE RATEIO",IF(ABS(P91)>0.005,"DIVERGÊNCIA",IF(COUNTIF(RATEIOS!$A$2:$A$3142,$A91)-COUNTIFS(RATEIOS!$A$2:$A$3142,$A91,RATEIOS!$D$2:$D$3142,"<>")>0,"NÃO CLASSIFICADO","RATEIO OK")))) -> RATEIO OK | R91: Conciliado
A92: BAN-00091 | B92: 91 | C92: 46048 | D92: =IF(C92="","",MONTH(C92)) -> 1 | E92: BOLETO | F92: SAÍDA | G92: FARMARIN INDUSTRIA (RE. SOLUÇÃO ÁCIDA E SOLUÇÃO BÁSICA) 2/2 | H92: FARMARIN INDUSTRIA | I92: 446875 | J92: 0 | K92: 35134 | L92: 0 | M92: 0 | N92: =IF(AND(C92="",J92=0,K92=0,L92=0,M92=0),"",CADASTROS!$B$4+SUM($J$2:J92)+SUM($M$2:M92)-SUM($K$2:K92)-SUM($L$2:L92)) -> -39394.11 | O92: =IF(A92="","",SUMIF(RATEIOS!$A$2:$A$3142,$A92,RATEIOS!$F$2:$F$3142)) -> 35134 | P92: =IF(A92="","",(J92+K92+L92+M92)-O92) -> 0 | Q92: =IF(AND(J92=0,K92=0,L92=0,M92=0),"",IF(O92=0,"PENDENTE DE RATEIO",IF(ABS(P92)>0.005,"DIVERGÊNCIA",IF(COUNTIF(RATEIOS!$A$2:$A$3142,$A92)-COUNTIFS(RATEIOS!$A$2:$A$3142,$A92,RATEIOS!$D$2:$D$3142,"<>")>0,"NÃO CLASSIFICADO","RATEIO OK")))) -> RATEIO OK | R92: Conciliado
A93: BAN-00092 | B93: 92 | C93: 46048 | D93: =IF(C93="","",MONTH(C93)) -> 1 | E93: BOLETO | F93: SAÍDA | G93: MED VITTA (REF. INSUMOS E MEDICAMENTOS) 2/2 | H93: MED VITTA | I93: 67359 | J93: 0 | K93: 1116.33 | L93: 0 | M93: 0 | N93: =IF(AND(C93="",J93=0,K93=0,L93=0,M93=0),"",CADASTROS!$B$4+SUM($J$2:J93)+SUM($M$2:M93)-SUM($K$2:K93)-SUM($L$2:L93)) -> -40510.44 | O93: =IF(A93="","",SUMIF(RATEIOS!$A$2:$A$3142,$A93,RATEIOS!$F$2:$F$3142)) -> 1116.33 | P93: =IF(A93="","",(J93+K93+L93+M93)-O93) -> 0 | Q93: =IF(AND(J93=0,K93=0,L93=0,M93=0),"",IF(O93=0,"PENDENTE DE RATEIO",IF(ABS(P93)>0.005,"DIVERGÊNCIA",IF(COUNTIF(RATEIOS!$A$2:$A$3142,$A93)-COUNTIFS(RATEIOS!$A$2:$A$3142,$A93,RATEIOS!$D$2:$D$3142,"<>")>0,"NÃO CLASSIFICADO","RATEIO OK")))) -> RATEIO OK | R93: Conciliado
A94: BAN-00093 | B94: 93 | C94: 46048 | D94: =IF(C94="","",MONTH(C94)) -> 1 | E94: BOLETO | F94: SAÍDA | G94: J SUL DISTRIBUIDORA (REF. INSUMOS) 1/3 | H94: J SUL DISTRIBUIDORA | I94: 47808 | J94: 0 | K94: 590.55 | L94: 0 | M94: 0 | N94: =IF(AND(C94="",J94=0,K94=0,L94=0,M94=0),"",CADASTROS!$B$4+SUM($J$2:J94)+SUM($M$2:M94)-SUM($K$2:K94)-SUM($L$2:L94)) -> -41100.99 | O94: =IF(A94="","",SUMIF(RATEIOS!$A$2:$A$3142,$A94,RATEIOS!$F$2:$F$3142)) -> 590.55 | P94: =IF(A94="","",(J94+K94+L94+M94)-O94) -> 0 | Q94: =IF(AND(J94=0,K94=0,L94=0,M94=0),"",IF(O94=0,"PENDENTE DE RATEIO",IF(ABS(P94)>0.005,"DIVERGÊNCIA",IF(COUNTIF(RATEIOS!$A$2:$A$3142,$A94)-COUNTIFS(RATEIOS!$A$2:$A$3142,$A94,RATEIOS!$D$2:$D$3142,"<>")>0,"NÃO CLASSIFICADO","RATEIO OK")))) -> RATEIO OK | R94: Conciliado
A95: BAN-00094 | B95: 94 | C95: 46048 | D95: =IF(C95="","",MONTH(C95)) -> 1 | E95: PIX | F95: SAÍDA | G95: MARKETPLACE (NF - U Z INDUSTRIA - CASA E SEGURANÇA) - REF. FECHADURA DIGITAL | H95: MARKETPLACE MERCADO LIVRE | I95: 392488 | J95: 0 | K95: 299 | L95: 0 | M95: 0 | N95: =IF(AND(C95="",J95=0,K95=0,L95=0,M95=0),"",CADASTROS!$B$4+SUM($J$2:J95)+SUM($M$2:M95)-SUM($K$2:K95)-SUM($L$2:L95)) -> -41399.99 | O95: =IF(A95="","",SUMIF(RATEIOS!$A$2:$A$3142,$A95,RATEIOS!$F$2:$F$3142)) -> 299 | P95: =IF(A95="","",(J95+K95+L95+M95)-O95) -> 0 | Q95: =IF(AND(J95=0,K95=0,L95=0,M95=0),"",IF(O95=0,"PENDENTE DE RATEIO",IF(ABS(P95)>0.005,"DIVERGÊNCIA",IF(COUNTIF(RATEIOS!$A$2:$A$3142,$A95)-COUNTIFS(RATEIOS!$A$2:$A$3142,$A95,RATEIOS!$D$2:$D$3142,"<>")>0,"NÃO CLASSIFICADO","RATEIO OK")))) -> RATEIO OK | R95: Conciliado
A96: BAN-00095 | B96: 95 | C96: 46048 | D96: =IF(C96="","",MONTH(C96)) -> 1 | E96: OUTROS | F96: RESGATE | G96: RESGATE BB CDB DI | H96: BANCO DO BRASIL - CDB DI | J96: 0 | K96: 0 | L96: 0 | M96: 41500 | N96: =IF(AND(C96="",J96=0,K96=0,L96=0,M96=0),"",CADASTROS!$B$4+SUM($J$2:J96)+SUM($M$2:M96)-SUM($K$2:K96)-SUM($L$2:L96)) -> 100.01 | O96: =IF(A96="","",SUMIF(RATEIOS!$A$2:$A$3142,$A96,RATEIOS!$F$2:$F$3142)) -> 41500 | P96: =IF(A96="","",(J96+K96+L96+M96)-O96) -> 0 | Q96: =IF(AND(J96=0,K96=0,L96=0,M96=0),"",IF(O96=0,"PENDENTE DE RATEIO",IF(ABS(P96)>0.005,"DIVERGÊNCIA",IF(COUNTIF(RATEIOS!$A$2:$A$3142,$A96)-COUNTIFS(RATEIOS!$A$2:$A$3142,$A96,RATEIOS!$D$2:$D$3142,"<>")>0,"NÃO CLASSIFICADO","RATEIO OK")))) -> RATEIO OK | R96: Conciliado
A97: BAN-00096 | B97: 96 | C97: 46049 | D97: =IF(C97="","",MONTH(C97)) -> 1 | E97: OUTROS | F97: RESGATE | G97: RESGATE BB CDB DI | H97: BANCO DO BRASIL - CDB DI | J97: 0 | K97: 0 | L97: 0 | M97: 2000 | N97: =IF(AND(C97="",J97=0,K97=0,L97=0,M97=0),"",CADASTROS!$B$4+SUM($J$2:J97)+SUM($M$2:M97)-SUM($K$2:K97)-SUM($L$2:L97)) -> 2100.01 | O97: =IF(A97="","",SUMIF(RATEIOS!$A$2:$A$3142,$A97,RATEIOS!$F$2:$F$3142)) -> 2000 | P97: =IF(A97="","",(J97+K97+L97+M97)-O97) -> 0 | Q97: =IF(AND(J97=0,K97=0,L97=0,M97=0),"",IF(O97=0,"PENDENTE DE RATEIO",IF(ABS(P97)>0.005,"DIVERGÊNCIA",IF(COUNTIF(RATEIOS!$A$2:$A$3142,$A97)-COUNTIFS(RATEIOS!$A$2:$A$3142,$A97,RATEIOS!$D$2:$D$3142,"<>")>0,"NÃO CLASSIFICADO","RATEIO OK")))) -> RATEIO OK | R97: Conciliado
A98: BAN-00097 | B98: 97 | C98: 46049 | D98: =IF(C98="","",MONTH(C98)) -> 1 | E98: OUTROS | F98: RESGATE | G98: RESGATE BB CDB DI | H98: BANCO DO BRASIL - CDB DI | J98: 0 | K98: 0 | L98: 0 | M98: 355.24 | N98: =IF(AND(C98="",J98=0,K98=0,L98=0,M98=0),"",CADASTROS!$B$4+SUM($J$2:J98)+SUM($M$2:M98)-SUM($K$2:K98)-SUM($L$2:L98)) -> 2455.25 | O98: =IF(A98="","",SUMIF(RATEIOS!$A$2:$A$3142,$A98,RATEIOS!$F$2:$F$3142)) -> 355.24 | P98: =IF(A98="","",(J98+K98+L98+M98)-O98) -> 0 | Q98: =IF(AND(J98=0,K98=0,L98=0,M98=0),"",IF(O98=0,"PENDENTE DE RATEIO",IF(ABS(P98)>0.005,"DIVERGÊNCIA",IF(COUNTIF(RATEIOS!$A$2:$A$3142,$A98)-COUNTIFS(RATEIOS!$A$2:$A$3142,$A98,RATEIOS!$D$2:$D$3142,"<>")>0,"NÃO CLASSIFICADO","RATEIO OK")))) -> RATEIO OK | R98: Conciliado
A99: BAN-00098 | B99: 98 | C99: 46049 | D99: =IF(C99="","",MONTH(C99)) -> 1 | E99: BOLETO | F99: SAÍDA | G99: SUPERMÉDICA (REF. INSUMOS E MEDICAMENTOS) 2/2 | H99: SUPERMÉDICA | I99: 371993 | J99: 0 | K99: 2450.97 | L99: 0 | M99: 0 | N99: =IF(AND(C99="",J99=0,K99=0,L99=0,M99=0),"",CADASTROS!$B$4+SUM($J$2:J99)+SUM($M$2:M99)-SUM($K$2:K99)-SUM($L$2:L99)) -> 4.28 | O99: =IF(A99="","",SUMIF(RATEIOS!$A$2:$A$3142,$A99,RATEIOS!$F$2:$F$3142)) -> 2450.97 | P99: =IF(A99="","",(J99+K99+L99+M99)-O99) -> 0 | Q99: =IF(AND(J99=0,K99=0,L99=0,M99=0),"",IF(O99=0,"PENDENTE DE RATEIO",IF(ABS(P99)>0.005,"DIVERGÊNCIA",IF(COUNTIF(RATEIOS!$A$2:$A$3142,$A99)-COUNTIFS(RATEIOS!$A$2:$A$3142,$A99,RATEIOS!$D$2:$D$3142,"<>")>0,"NÃO CLASSIFICADO","RATEIO OK")))) -> RATEIO OK | R99: Conciliado
A100: BAN-00099 | B100: 99 | C100: 46050 | D100: =IF(C100="","",MONTH(C100)) -> 1 | E100: OUTROS | F100: RESGATE | G100: CDB/RDB | H100: BANCO DO BRASIL - CDB DI | J100: 0 | K100: 0 | L100: 0 | M100: 17.96 | N100: =IF(AND(C100="",J100=0,K100=0,L100=0,M100=0),"",CADASTROS!$B$4+SUM($J$2:J100)+SUM($M$2:M100)-SUM($K$2:K100)-SUM($L$2:L100)) -> 22.24 | O100: =IF(A100="","",SUMIF(RATEIOS!$A$2:$A$3142,$A100,RATEIOS!$F$2:$F$3142)) -> 17.96 | P100: =IF(A100="","",(J100+K100+L100+M100)-O100) -> 0 | Q100: =IF(AND(J100=0,K100=0,L100=0,M100=0),"",IF(O100=0,"PENDENTE DE RATEIO",IF(ABS(P100)>0.005,"DIVERGÊNCIA",IF(COUNTIF(RATEIOS!$A$2:$A$3142,$A100)-COUNTIFS(RATEIOS!$A$2:$A$3142,$A100,RATEIOS!$D$2:$D$3142,"<>")>0,"NÃO CLASSIFICADO","RATEIO OK")))) -> RATEIO OK | R100: Conciliado
...

Sheet RATEIOS
A1: ID_LANC | B1: DATA | C1: MÊS | D1: CATEGORIA | E1: SUBCATEGORIA | F1: VALOR | G1: DETALHE DO COMPONENTE | H1: NATUREZA | I1: FORNECEDOR | J1: ORIGEM DA CLASSIFICAÇÃO | K1: CONFERÊNCIA
A2: BAN-00001 | B2: =IF(A2="","",IF(INDEX(EXTRATO!$C$2:$C$3000,MATCH($A2,EXTRATO!$A$2:$A$3000,0))="","",INDEX(EXTRATO!$C$2:$C$3000,MATCH($A2,EXTRATO!$A$2:$A$3000,0)))) -> 46024 | C2: =IF(B2="","",MONTH(B2)) -> 1 | D2: ENTRADAS | E2: Resgate de Aplicações Financeiras (CDI BB) | F2: 8500 | G2: RESGATE BB CDB DI | H2: =IF(A2="","",IF(INDEX(EXTRATO!$F$2:$F$3000,MATCH($A2,EXTRATO!$A$2:$A$3000,0))="","",INDEX(EXTRATO!$F$2:$F$3000,MATCH($A2,EXTRATO!$A$2:$A$3000,0)))) -> RESGATE | I2: =IF(A2="","",IF(INDEX(EXTRATO!$H$2:$H$3000,MATCH($A2,EXTRATO!$A$2:$A$3000,0))="","",INDEX(EXTRATO!$H$2:$H$3000,MATCH($A2,EXTRATO!$A$2:$A$3000,0)))) -> BANCO DO BRASIL - CDB DI | J2: AUTOMÁTICO | K2: =IF(AND(A2="",D2="",E2="",F2=""),"",IF(D2="","SEM CATEGORIA",IF(E2="","SEM SUBCATEGORIA",IF(COUNTIFS(CADASTROS!$L$7:$L$93,D2,CADASTROS!$D$7:$D$93,E2)=0,"INCOMPATÍVEL","OK")))) -> OK
A3: BAN-00002 | B3: =IF(A3="","",IF(INDEX(EXTRATO!$C$2:$C$3000,MATCH($A3,EXTRATO!$A$2:$A$3000,0))="","",INDEX(EXTRATO!$C$2:$C$3000,MATCH($A3,EXTRATO!$A$2:$A$3000,0)))) -> 46024 | C3: =IF(B3="","",MONTH(B3)) -> 1 | D3: ENTRADAS | E3: Resgate de Aplicações Financeiras (CDI BB) | F3: 5.27 | G3: RESGATE BB CDB DI | H3: =IF(A3="","",IF(INDEX(EXTRATO!$F$2:$F$3000,MATCH($A3,EXTRATO!$A$2:$A$3000,0))="","",INDEX(EXTRATO!$F$2:$F$3000,MATCH($A3,EXTRATO!$A$2:$A$3000,0)))) -> RESGATE | I3: =IF(A3="","",IF(INDEX(EXTRATO!$H$2:$H$3000,MATCH($A3,EXTRATO!$A$2:$A$3000,0))="","",INDEX(EXTRATO!$H$2:$H$3000,MATCH($A3,EXTRATO!$A$2:$A$3000,0)))) -> BANCO DO BRASIL - CDB DI | J3: AUTOMÁTICO | K3: =IF(AND(A3="",D3="",E3="",F3=""),"",IF(D3="","SEM CATEGORIA",IF(E3="","SEM SUBCATEGORIA",IF(COUNTIFS(CADASTROS!$L$7:$L$93,D3,CADASTROS!$D$7:$D$93,E3)=0,"INCOMPATÍVEL","OK")))) -> OK
A4: BAN-00003 | B4: =IF(A4="","",IF(INDEX(EXTRATO!$C$2:$C$3000,MATCH($A4,EXTRATO!$A$2:$A$3000,0))="","",INDEX(EXTRATO!$C$2:$C$3000,MATCH($A4,EXTRATO!$A$2:$A$3000,0)))) -> 46024 | C4: =IF(B4="","",MONTH(B4)) -> 1 | D4: DESPESAS COM MATERIAIS PARA HEMODIÁLISE E DEMAIS CUSTOS | E4: Agulhas, Seringas, Máscaras, Luvas, Equipo e Med. Div. | F4: 270 | G4: ANA CLAUDIA A. VARÃO (NF - VARÃO E ALMEIDA - ESSENCIAL PHARMA) - REF. IODETO DE POTÁSSIO | H4: =IF(A4="","",IF(INDEX(EXTRATO!$F$2:$F$3000,MATCH($A4,EXTRATO!$A$2:$A$3000,0))="","",INDEX(EXTRATO!$F$2:$F$3000,MATCH($A4,EXTRATO!$A$2:$A$3000,0)))) -> SAÍDA | I4: =IF(A4="","",IF(INDEX(EXTRATO!$H$2:$H$3000,MATCH($A4,EXTRATO!$A$2:$A$3000,0))="","",INDEX(EXTRATO!$H$2:$H$3000,MATCH($A4,EXTRATO!$A$2:$A$3000,0)))) -> ANA CLAUDIA A. VARÃO | J4: MAPEADO | K4: =IF(AND(A4="",D4="",E4="",F4=""),"",IF(D4="","SEM CATEGORIA",IF(E4="","SEM SUBCATEGORIA",IF(COUNTIFS(CADASTROS!$L$7:$L$93,D4,CADASTROS!$D$7:$D$93,E4)=0,"INCOMPATÍVEL","OK")))) -> OK
A5: BAN-00004 | B5: =IF(A5="","",IF(INDEX(EXTRATO!$C$2:$C$3000,MATCH($A5,EXTRATO!$A$2:$A$3000,0))="","",INDEX(EXTRATO!$C$2:$C$3000,MATCH($A5,EXTRATO!$A$2:$A$3000,0)))) -> 46024 | C5: =IF(B5="","",MONTH(B5)) -> 1 | D5: DESPESAS COM MATERIAIS PARA HEMODIÁLISE E DEMAIS CUSTOS | E5: Linha Arterial e Venosa | F5: 1300.83 | G5: ALLMED PRONEFRO (REF. LINHA ARTERIAL E LINHA VENOSA) 1/3 | H5: =IF(A5="","",IF(INDEX(EXTRATO!$F$2:$F$3000,MATCH($A5,EXTRATO!$A$2:$A$3000,0))="","",INDEX(EXTRATO!$F$2:$F$3000,MATCH($A5,EXTRATO!$A$2:$A$3000,0)))) -> SAÍDA | I5: =IF(A5="","",IF(INDEX(EXTRATO!$H$2:$H$3000,MATCH($A5,EXTRATO!$A$2:$A$3000,0))="","",INDEX(EXTRATO!$H$2:$H$3000,MATCH($A5,EXTRATO!$A$2:$A$3000,0)))) -> ALLMED PRONEFRO | J5: MAPEADO | K5: =IF(AND(A5="",D5="",E5="",F5=""),"",IF(D5="","SEM CATEGORIA",IF(E5="","SEM SUBCATEGORIA",IF(COUNTIFS(CADASTROS!$L$7:$L$93,D5,CADASTROS!$D$7:$D$93,E5)=0,"INCOMPATÍVEL","OK")))) -> OK
A6: BAN-00005 | B6: =IF(A6="","",IF(INDEX(EXTRATO!$C$2:$C$3000,MATCH($A6,EXTRATO!$A$2:$A$3000,0))="","",INDEX(EXTRATO!$C$2:$C$3000,MATCH($A6,EXTRATO!$A$2:$A$3000,0)))) -> 46024 | C6: =IF(B6="","",MONTH(B6)) -> 1 | D6: DESPESAS COM MATERIAIS PARA HEMODIÁLISE E DEMAIS CUSTOS | E6: Linha Arterial e Venosa | F6: 1952.72 | G6: ALLMED PRONEFRO (REF. LINHA ARTERIAL E LINHA VENOSA) 2/2 | H6: =IF(A6="","",IF(INDEX(EXTRATO!$F$2:$F$3000,MATCH($A6,EXTRATO!$A$2:$A$3000,0))="","",INDEX(EXTRATO!$F$2:$F$3000,MATCH($A6,EXTRATO!$A$2:$A$3000,0)))) -> SAÍDA | I6: =IF(A6="","",IF(INDEX(EXTRATO!$H$2:$H$3000,MATCH($A6,EXTRATO!$A$2:$A$3000,0))="","",INDEX(EXTRATO!$H$2:$H$3000,MATCH($A6,EXTRATO!$A$2:$A$3000,0)))) -> ALLMED PRONEFRO | J6: MAPEADO | K6: =IF(AND(A6="",D6="",E6="",F6=""),"",IF(D6="","SEM CATEGORIA",IF(E6="","SEM SUBCATEGORIA",IF(COUNTIFS(CADASTROS!$L$7:$L$93,D6,CADASTROS!$D$7:$D$93,E6)=0,"INCOMPATÍVEL","OK")))) -> OK
A7: BAN-00006 | B7: =IF(A7="","",IF(INDEX(EXTRATO!$C$2:$C$3000,MATCH($A7,EXTRATO!$A$2:$A$3000,0))="","",INDEX(EXTRATO!$C$2:$C$3000,MATCH($A7,EXTRATO!$A$2:$A$3000,0)))) -> 46024 | C7: =IF(B7="","",MONTH(B7)) -> 1 | D7: DESPESAS COM MATERIAIS PARA HEMODIÁLISE E DEMAIS CUSTOS | E7: CDL e Perm-cath | F7: 720 | G7: OMNIELMASTER HEMOMED (REF. CATETER) 2/2 | H7: =IF(A7="","",IF(INDEX(EXTRATO!$F$2:$F$3000,MATCH($A7,EXTRATO!$A$2:$A$3000,0))="","",INDEX(EXTRATO!$F$2:$F$3000,MATCH($A7,EXTRATO!$A$2:$A$3000,0)))) -> SAÍDA | I7: =IF(A7="","",IF(INDEX(EXTRATO!$H$2:$H$3000,MATCH($A7,EXTRATO!$A$2:$A$3000,0))="","",INDEX(EXTRATO!$H$2:$H$3000,MATCH($A7,EXTRATO!$A$2:$A$3000,0)))) -> OMNIELMASTER HEMOMED | J7: MAPEADO | K7: =IF(AND(A7="",D7="",E7="",F7=""),"",IF(D7="","SEM CATEGORIA",IF(E7="","SEM SUBCATEGORIA",IF(COUNTIFS(CADASTROS!$L$7:$L$93,D7,CADASTROS!$D$7:$D$93,E7)=0,"INCOMPATÍVEL","OK")))) -> OK
A8: BAN-00007 | B8: =IF(A8="","",IF(INDEX(EXTRATO!$C$2:$C$3000,MATCH($A8,EXTRATO!$A$2:$A$3000,0))="","",INDEX(EXTRATO!$C$2:$C$3000,MATCH($A8,EXTRATO!$A$2:$A$3000,0)))) -> 46024 | C8: =IF(B8="","",MONTH(B8)) -> 1 | D8: DESPESAS COM MATERIAIS PARA HEMODIÁLISE E DEMAIS CUSTOS | E8: Peroxide | F8: 1350 | G8: DIALISE COMÉRCIO (REF. ÁCIDO PERACETICO 5%) 2/2 | H8: =IF(A8="","",IF(INDEX(EXTRATO!$F$2:$F$3000,MATCH($A8,EXTRATO!$A$2:$A$3000,0))="","",INDEX(EXTRATO!$F$2:$F$3000,MATCH($A8,EXTRATO!$A$2:$A$3000,0)))) -> SAÍDA | I8: =IF(A8="","",IF(INDEX(EXTRATO!$H$2:$H$3000,MATCH($A8,EXTRATO!$A$2:$A$3000,0))="","",INDEX(EXTRATO!$H$2:$H$3000,MATCH($A8,EXTRATO!$A$2:$A$3000,0)))) -> DIALISE COMERCIO | J8: MAPEADO | K8: =IF(AND(A8="",D8="",E8="",F8=""),"",IF(D8="","SEM CATEGORIA",IF(E8="","SEM SUBCATEGORIA",IF(COUNTIFS(CADASTROS!$L$7:$L$93,D8,CADASTROS!$D$7:$D$93,E8)=0,"INCOMPATÍVEL","OK")))) -> OK
A9: BAN-00007 | B9: =IF(A9="","",IF(INDEX(EXTRATO!$C$2:$C$3000,MATCH($A9,EXTRATO!$A$2:$A$3000,0))="","",INDEX(EXTRATO!$C$2:$C$3000,MATCH($A9,EXTRATO!$A$2:$A$3000,0)))) -> 46024 | C9: =IF(B9="","",MONTH(B9)) -> 1 | D9: DESPESAS COM MATERIAIS PARA HEMODIÁLISE E DEMAIS CUSTOS | E9: Agulhas, Seringas, Máscaras, Luvas, Equipo e Med. Div. | F9: 490 | G9: DIALISE COMÉRCIO (REF. ISOLADOR DE PRESSÃO) 2/2 | H9: =IF(A9="","",IF(INDEX(EXTRATO!$F$2:$F$3000,MATCH($A9,EXTRATO!$A$2:$A$3000,0))="","",INDEX(EXTRATO!$F$2:$F$3000,MATCH($A9,EXTRATO!$A$2:$A$3000,0)))) -> SAÍDA | I9: =IF(A9="","",IF(INDEX(EXTRATO!$H$2:$H$3000,MATCH($A9,EXTRATO!$A$2:$A$3000,0))="","",INDEX(EXTRATO!$H$2:$H$3000,MATCH($A9,EXTRATO!$A$2:$A$3000,0)))) -> DIALISE COMERCIO | J9: MAPEADO | K9: =IF(AND(A9="",D9="",E9="",F9=""),"",IF(D9="","SEM CATEGORIA",IF(E9="","SEM SUBCATEGORIA",IF(COUNTIFS(CADASTROS!$L$7:$L$93,D9,CADASTROS!$D$7:$D$93,E9)=0,"INCOMPATÍVEL","OK")))) -> OK
A10: BAN-00008 | B10: =IF(A10="","",IF(INDEX(EXTRATO!$C$2:$C$3000,MATCH($A10,EXTRATO!$A$2:$A$3000,0))="","",INDEX(EXTRATO!$C$2:$C$3000,MATCH($A10,EXTRATO!$A$2:$A$3000,0)))) -> 46024 | C10: =IF(B10="","",MONTH(B10)) -> 1 | D10: DESPESAS COM MATERIAIS PARA HEMODIÁLISE E DEMAIS CUSTOS | E10: Peroxide | F10: 1800 | G10: DIÁLISE COMÉRCIO (REF. ÁCIDO PERACETICO) 1/2 | H10: =IF(A10="","",IF(INDEX(EXTRATO!$F$2:$F$3000,MATCH($A10,EXTRATO!$A$2:$A$3000,0))="","",INDEX(EXTRATO!$F$2:$F$3000,MATCH($A10,EXTRATO!$A$2:$A$3000,0)))) -> SAÍDA | I10: =IF(A10="","",IF(INDEX(EXTRATO!$H$2:$H$3000,MATCH($A10,EXTRATO!$A$2:$A$3000,0))="","",INDEX(EXTRATO!$H$2:$H$3000,MATCH($A10,EXTRATO!$A$2:$A$3000,0)))) -> DIALISE COMERCIO | J10: MAPEADO | K10: =IF(AND(A10="",D10="",E10="",F10=""),"",IF(D10="","SEM CATEGORIA",IF(E10="","SEM SUBCATEGORIA",IF(COUNTIFS(CADASTROS!$L$7:$L$93,D10,CADASTROS!$D$7:$D$93,E10)=0,"INCOMPATÍVEL","OK")))) -> OK
A11: BAN-00008 | B11: =IF(A11="","",IF(INDEX(EXTRATO!$C$2:$C$3000,MATCH($A11,EXTRATO!$A$2:$A$3000,0))="","",INDEX(EXTRATO!$C$2:$C$3000,MATCH($A11,EXTRATO!$A$2:$A$3000,0)))) -> 46024 | C11: =IF(B11="","",MONTH(B11)) -> 1 | D11: DESPESAS COM MATERIAIS PARA HEMODIÁLISE E DEMAIS CUSTOS | E11: Agulhas, Seringas, Máscaras, Luvas, Equipo e Med. Div. | F11: 735 | G11: DIÁLISE COMÉRCIO (REF. ISOLADOR DE PRESSÃO) 1/2 | H11: =IF(A11="","",IF(INDEX(EXTRATO!$F$2:$F$3000,MATCH($A11,EXTRATO!$A$2:$A$3000,0))="","",INDEX(EXTRATO!$F$2:$F$3000,MATCH($A11,EXTRATO!$A$2:$A$3000,0)))) -> SAÍDA | I11: =IF(A11="","",IF(INDEX(EXTRATO!$H$2:$H$3000,MATCH($A11,EXTRATO!$A$2:$A$3000,0))="","",INDEX(EXTRATO!$H$2:$H$3000,MATCH($A11,EXTRATO!$A$2:$A$3000,0)))) -> DIALISE COMERCIO | J11: MAPEADO | K11: =IF(AND(A11="",D11="",E11="",F11=""),"",IF(D11="","SEM CATEGORIA",IF(E11="","SEM SUBCATEGORIA",IF(COUNTIFS(CADASTROS!$L$7:$L$93,D11,CADASTROS!$D$7:$D$93,E11)=0,"INCOMPATÍVEL","OK")))) -> OK
A12: BAN-00009 | B12: =IF(A12="","",IF(INDEX(EXTRATO!$C$2:$C$3000,MATCH($A12,EXTRATO!$A$2:$A$3000,0))="","",INDEX(EXTRATO!$C$2:$C$3000,MATCH($A12,EXTRATO!$A$2:$A$3000,0)))) -> 46024 | C12: =IF(B12="","",MONTH(B12)) -> 1 | D12: ENTRADAS | E12: Resgate de Aplicações Financeiras (CDI BB) | F12: 113.28 | G12: BB RENDE FÁCIL | H12: =IF(A12="","",IF(INDEX(EXTRATO!$F$2:$F$3000,MATCH($A12,EXTRATO!$A$2:$A$3000,0))="","",INDEX(EXTRATO!$F$2:$F$3000,MATCH($A12,EXTRATO!$A$2:$A$3000,0)))) -> RESGATE | I12: =IF(A12="","",IF(INDEX(EXTRATO!$H$2:$H$3000,MATCH($A12,EXTRATO!$A$2:$A$3000,0))="","",INDEX(EXTRATO!$H$2:$H$3000,MATCH($A12,EXTRATO!$A$2:$A$3000,0)))) -> BANCO DO BRASIL - CDB DI | J12: AUTOMÁTICO | K12: =IF(AND(A12="",D12="",E12="",F12=""),"",IF(D12="","SEM CATEGORIA",IF(E12="","SEM SUBCATEGORIA",IF(COUNTIFS(CADASTROS!$L$7:$L$93,D12,CADASTROS!$D$7:$D$93,E12)=0,"INCOMPATÍVEL","OK")))) -> OK
A13: BAN-00010 | B13: =IF(A13="","",IF(INDEX(EXTRATO!$C$2:$C$3000,MATCH($A13,EXTRATO!$A$2:$A$3000,0))="","",INDEX(EXTRATO!$C$2:$C$3000,MATCH($A13,EXTRATO!$A$2:$A$3000,0)))) -> 46027 | C13: =IF(B13="","",MONTH(B13)) -> 1 | D13: ENTRADAS | E13: Resgate de Aplicações Financeiras (CDI BB) | F13: 2500 | G13: RESGATE BB CDB DI | H13: =IF(A13="","",IF(INDEX(EXTRATO!$F$2:$F$3000,MATCH($A13,EXTRATO!$A$2:$A$3000,0))="","",INDEX(EXTRATO!$F$2:$F$3000,MATCH($A13,EXTRATO!$A$2:$A$3000,0)))) -> RESGATE | I13: =IF(A13="","",IF(INDEX(EXTRATO!$H$2:$H$3000,MATCH($A13,EXTRATO!$A$2:$A$3000,0))="","",INDEX(EXTRATO!$H$2:$H$3000,MATCH($A13,EXTRATO!$A$2:$A$3000,0)))) -> BANCO DO BRASIL - CDB DI | J13: AUTOMÁTICO | K13: =IF(AND(A13="",D13="",E13="",F13=""),"",IF(D13="","SEM CATEGORIA",IF(E13="","SEM SUBCATEGORIA",IF(COUNTIFS(CADASTROS!$L$7:$L$93,D13,CADASTROS!$D$7:$D$93,E13)=0,"INCOMPATÍVEL","OK")))) -> OK
... A36: BAN-00033 | B36: =IF(A36="","",IF(INDEX(EXTRATO!$C$2:$C$3000,MATCH($A36,EXTRATO!$A$2:$A$3000,0))="","",INDEX(EXTRATO!$C$2:$C$3000,MATCH($A36,EXTRATO!$A$2:$A$3000,0)))) -> 46034 | C36: =IF(B36="","",MONTH(B36)) -> 1 | D36: ENTRADAS | E36: Resgate de Aplicações Financeiras (CDI BB) | F36: 57.72 | G36: CDB/RDB | H36: =IF(A36="","",IF(INDEX(EXTRATO!$F$2:$F$3000,MATCH($A36,EXTRATO!$A$2:$A$3000,0))="","",INDEX(EXTRATO!$F$2:$F$3000,MATCH($A36,EXTRATO!$A$2:$A$3000,0)))) -> RESGATE | I36: =IF(A36="","",IF(INDEX(EXTRATO!$H$2:$H$3000,MATCH($A36,EXTRATO!$A$2:$A$3000,0))="","",INDEX(EXTRATO!$H$2:$H$3000,MATCH($A36,EXTRATO!$A$2:$A$3000,0)))) -> BANCO DO BRASIL - CDB DI | J36: AUTOMÁTICO | K36: =IF(AND(A36="",D36="",E36="",F36=""),"",IF(D36="","SEM CATEGORIA",IF(E36="","SEM SUBCATEGORIA",IF(COUNTIFS(CADASTROS!$L$7:$L$93,D36,CADASTROS!$D$7:$D$93,E36)=0,"INCOMPATÍVEL","OK")))) -> OK
A37: BAN-00034 | B37: =IF(A37="","",IF(INDEX(EXTRATO!$C$2:$C$3000,MATCH($A37,EXTRATO!$A$2:$A$3000,0))="","",INDEX(EXTRATO!$C$2:$C$3000,MATCH($A37,EXTRATO!$A$2:$A$3000,0)))) -> 46034 | C37: =IF(B37="","",MONTH(B37)) -> 1 | F37: 290.1 | G37: TIM S/A | H37: =IF(A37="","",IF(INDEX(EXTRATO!$F$2:$F$3000,MATCH($A37,EXTRATO!$A$2:$A$3000,0))="","",INDEX(EXTRATO!$F$2:$F$3000,MATCH($A37,EXTRATO!$A$2:$A$3000,0)))) -> SAÍDA | I37: =IF(A37="","",IF(INDEX(EXTRATO!$H$2:$H$3000,MATCH($A37,EXTRATO!$A$2:$A$3000,0))="","",INDEX(EXTRATO!$H$2:$H$3000,MATCH($A37,EXTRATO!$A$2:$A$3000,0)))) -> TIM S/A | J37: PENDENTE | K37: =IF(AND(A37="",D37="",E37="",F37=""),"",IF(D37="","SEM CATEGORIA",IF(E37="","SEM SUBCATEGORIA",IF(COUNTIFS(CADASTROS!$L$7:$L$93,D37,CADASTROS!$D$7:$D$93,E37)=0,"INCOMPATÍVEL","OK")))) -> SEM CATEGORIA
A38: BAN-00035 | B38: =IF(A38="","",IF(INDEX(EXTRATO!$C$2:$C$3000,MATCH($A38,EXTRATO!$A$2:$A$3000,0))="","",INDEX(EXTRATO!$C$2:$C$3000,MATCH($A38,EXTRATO!$A$2:$A$3000,0)))) -> 46034 | C38: =IF(B38="","",MONTH(B38)) -> 1 | F38: 290.1 | G38: BRITO, TORRES & LOBO (REF. ESTORNO DO PAGAMENTO TIM S/A) | H38: =IF(A38="","",IF(INDEX(EXTRATO!$F$2:$F$3000,MATCH($A38,EXTRATO!$A$2:$A$3000,0))="","",INDEX(EXTRATO!$F$2:$F$3000,MATCH($A38,EXTRATO!$A$2:$A$3000,0)))) -> ENTRADA | I38: =IF(A38="","",IF(INDEX(EXTRATO!$H$2:$H$3000,MATCH($A38,EXTRATO!$A$2:$A$3000,0))="","",INDEX(EXTRATO!$H$2:$H$3000,MATCH($A38,EXTRATO!$A$2:$A$3000,0)))) -> BRITO, TORRES & LOBO | J38: PENDENTE | K38: =IF(AND(A38="",D38="",E38="",F38=""),"",IF(D38="","SEM CATEGORIA",IF(E38="","SEM SUBCATEGORIA",IF(COUNTIFS(CADASTROS!$L$7:$L$93,D38,CADASTROS!$D$7:$D$93,E38)=0,"INCOMPATÍVEL","OK")))) -> SEM CATEGORIA
A39: BAN-00036 | B39: =IF(A39="","",IF(INDEX(EXTRATO!$C$2:$C$3000,MATCH($A39,EXTRATO!$A$2:$A$3000,0))="","",INDEX(EXTRATO!$C$2:$C$3000,MATCH($A39,EXTRATO!$A$2:$A$3000,0)))) -> 46034 | C39: =IF(B39="","",MONTH(B39)) -> 1 | D39: DESPESAS COM SALÁRIOS E BENEFÍCIOS | E39: EPIs e Fardamentos | F39: 169.77 | G39: FERCASTRO (REF. BOTAS PARA COLABORADORES) | H39: =IF(A39="","",IF(INDEX(EXTRATO!$F$2:$F$3000,MATCH($A39,EXTRATO!$A$2:$A$3000,0))="","",INDEX(EXTRATO!$F$2:$F$3000,MATCH($A39,EXTRATO!$A$2:$A$3000,0)))) -> SAÍDA | I39: =IF(A39="","",IF(INDEX(EXTRATO!$H$2:$H$3000,MATCH($A39,EXTRATO!$A$2:$A$3000,0))="","",INDEX(EXTRATO!$H$2:$H$3000,MATCH($A39,EXTRATO!$A$2:$A$3000,0)))) -> FERCASTRO | J39: MAPEADO | K39: =IF(AND(A39="",D39="",E39="",F39=""),"",IF(D39="","SEM CATEGORIA",IF(E39="","SEM SUBCATEGORIA",IF(COUNTIFS(CADASTROS!$L$7:$L$93,D39,CADASTROS!$D$7:$D$93,E39)=0,"INCOMPATÍVEL","OK")))) -> OK
A40: BAN-00036 | B40: =IF(A40="","",IF(INDEX(EXTRATO!$C$2:$C$3000,MATCH($A40,EXTRATO!$A$2:$A$3000,0))="","",INDEX(EXTRATO!$C$2:$C$3000,MATCH($A40,EXTRATO!$A$2:$A$3000,0)))) -> 46034 | C40: =IF(B40="","",MONTH(B40)) -> 1 | D40: MANUTENÇÃO E INFRAESTRUTURA | E40: Manutenção - Máquinas HD, Gerador, Osmose | F40: 18.23 | G40: FERCASTRO (REF. COLA DE SILICONE E PARAFUSOS) | H40: =IF(A40="","",IF(INDEX(EXTRATO!$F$2:$F$3000,MATCH($A40,EXTRATO!$A$2:$A$3000,0))="","",INDEX(EXTRATO!$F$2:$F$3000,MATCH($A40,EXTRATO!$A$2:$A$3000,0)))) -> SAÍDA | I40: =IF(A40="","",IF(INDEX(EXTRATO!$H$2:$H$3000,MATCH($A40,EXTRATO!$A$2:$A$3000,0))="","",INDEX(EXTRATO!$H$2:$H$3000,MATCH($A40,EXTRATO!$A$2:$A$3000,0)))) -> FERCASTRO | J40: MAPEADO | K40: =IF(AND(A40="",D40="",E40="",F40=""),"",IF(D40="","SEM CATEGORIA",IF(E40="","SEM SUBCATEGORIA",IF(COUNTIFS(CADASTROS!$L$7:$L$93,D40,CADASTROS!$D$7:$D$93,E40)=0,"INCOMPATÍVEL","OK")))) -> OK
A41: BAN-00037 | B41: =IF(A41="","",IF(INDEX(EXTRATO!$C$2:$C$3000,MATCH($A41,EXTRATO!$A$2:$A$3000,0))="","",INDEX(EXTRATO!$C$2:$C$3000,MATCH($A41,EXTRATO!$A$2:$A$3000,0)))) -> 46034 | C41: =IF(B41="","",MONTH(B41)) -> 1 | D41: DESPESAS COM MATERIAIS PARA HEMODIÁLISE E DEMAIS CUSTOS | E41: Oxigênio | F41: 360 | G41: M E S XAVIER (REF. CARGA DE 02 OXIGÊNIOS MEDICINAL) | H41: =IF(A41="","",IF(INDEX(EXTRATO!$F$2:$F$3000,MATCH($A41,EXTRATO!$A$2:$A$3000,0))="","",INDEX(EXTRATO!$F$2:$F$3000,MATCH($A41,EXTRATO!$A$2:$A$3000,0)))) -> SAÍDA | I41: =IF(A41="","",IF(INDEX(EXTRATO!$H$2:$H$3000,MATCH($A41,EXTRATO!$A$2:$A$3000,0))="","",INDEX(EXTRATO!$H$2:$H$3000,MATCH($A41,EXTRATO!$A$2:$A$3000,0)))) -> M E S XAVIER | J41: MAPEADO | K41: =IF(AND(A41="",D41="",E41="",F41=""),"",IF(D41="","SEM CATEGORIA",IF(E41="","SEM SUBCATEGORIA",IF(COUNTIFS(CADASTROS!$L$7:$L$93,D41,CADASTROS!$D$7:$D$93,E41)=0,"INCOMPATÍVEL","OK")))) -> OK
A42: BAN-00038 | B42: =IF(A42="","",IF(INDEX(EXTRATO!$C$2:$C$3000,MATCH($A42,EXTRATO!$A$2:$A$3000,0))="","",INDEX(EXTRATO!$C$2:$C$3000,MATCH($A42,EXTRATO!$A$2:$A$3000,0)))) -> 46034 | C42: =IF(B42="","",MONTH(B42)) -> 1 | D42: DESPESAS COM MATERIAIS PARA HEMODIÁLISE E DEMAIS CUSTOS | E42: Capilar, Filtros, Agulhas | F42: 1428.14 | G42: INDIFILTROS FILTROS (RE. FILTROS, CARCAÇA, CHAVES) 2/2 | H42: =IF(A42="","",IF(INDEX(EXTRATO!$F$2:$F$3000,MATCH($A42,EXTRATO!$A$2:$A$3000,0))="","",INDEX(EXTRATO!$F$2:$F$3000,MATCH($A42,EXTRATO!$A$2:$A$3000,0)))) -> SAÍDA | I42: =IF(A42="","",IF(INDEX(EXTRATO!$H$2:$H$3000,MATCH($A42,EXTRATO!$A$2:$A$3000,0))="","",INDEX(EXTRATO!$H$2:$H$3000,MATCH($A42,EXTRATO!$A$2:$A$3000,0)))) -> INDIFILTROS FILTROS | J42: MAPEADO | K42: =IF(AND(A42="",D42="",E42="",F42=""),"",IF(D42="","SEM CATEGORIA",IF(E42="","SEM SUBCATEGORIA",IF(COUNTIFS(CADASTROS!$L$7:$L$93,D42,CADASTROS!$D$7:$D$93,E42)=0,"INCOMPATÍVEL","OK")))) -> OK
A43: BAN-00039 | B43: =IF(A43="","",IF(INDEX(EXTRATO!$C$2:$C$3000,MATCH($A43,EXTRATO!$A$2:$A$3000,0))="","",INDEX(EXTRATO!$C$2:$C$3000,MATCH($A43,EXTRATO!$A$2:$A$3000,0)))) -> 46034 | C43: =IF(B43="","",MONTH(B43)) -> 1 | D43: DESPESAS ADMINISTRATIVAS | E43: Taxas e Tarifas | F43: 263 | G43: TARIFA PACOTE DE SERVIÇOS | H43: =IF(A43="","",IF(INDEX(EXTRATO!$F$2:$F$3000,MATCH($A43,EXTRATO!$A$2:$A$3000,0))="","",INDEX(EXTRATO!$F$2:$F$3000,MATCH($A43,EXTRATO!$A$2:$A$3000,0)))) -> SAÍDA | I43: =IF(A43="","",IF(INDEX(EXTRATO!$H$2:$H$3000,MATCH($A43,EXTRATO!$A$2:$A$3000,0))="","",INDEX(EXTRATO!$H$2:$H$3000,MATCH($A43,EXTRATO!$A$2:$A$3000,0)))) -> TARIFA PACOTE DE SERVIÇOS | J43: MAPEADO | K43: =IF(AND(A43="",D43="",E43="",F43=""),"",IF(D43="","SEM CATEGORIA",IF(E43="","SEM SUBCATEGORIA",IF(COUNTIFS(CADASTROS!$L$7:$L$93,D43,CADASTROS!$D$7:$D$93,E43)=0,"INCOMPATÍVEL","OK")))) -> OK
A44: BAN-00040 | B44: =IF(A44="","",IF(INDEX(EXTRATO!$C$2:$C$3000,MATCH($A44,EXTRATO!$A$2:$A$3000,0))="","",INDEX(EXTRATO!$C$2:$C$3000,MATCH($A44,EXTRATO!$A$2:$A$3000,0)))) -> 46034 | C44: =IF(B44="","",MONTH(B44)) -> 1 | D44: DESPESAS ADMINISTRATIVAS | E44: Suporte Informatica - Hardware, Internet, Sistemas e Câmeras | F44: 149.9 | G44: MARANET TELECOM (REF. INTERNET) | H44: =IF(A44="","",IF(INDEX(EXTRATO!$F$2:$F$3000,MATCH($A44,EXTRATO!$A$2:$A$3000,0))="","",INDEX(EXTRATO!$F$2:$F$3000,MATCH($A44,EXTRATO!$A$2:$A$3000,0)))) -> SAÍDA | I44: =IF(A44="","",IF(INDEX(EXTRATO!$H$2:$H$3000,MATCH($A44,EXTRATO!$A$2:$A$3000,0))="","",INDEX(EXTRATO!$H$2:$H$3000,MATCH($A44,EXTRATO!$A$2:$A$3000,0)))) -> MARANET TELECOM | J44: MAPEADO | K44: =IF(AND(A44="",D44="",E44="",F44=""),"",IF(D44="","SEM CATEGORIA",IF(E44="","SEM SUBCATEGORIA",IF(COUNTIFS(CADASTROS!$L$7:$L$93,D44,CADASTROS!$D$7:$D$93,E44)=0,"INCOMPATÍVEL","OK")))) -> OK
A45: BAN-00041 | B45: =IF(A45="","",IF(INDEX(EXTRATO!$C$2:$C$3000,MATCH($A45,EXTRATO!$A$2:$A$3000,0))="","",INDEX(EXTRATO!$C$2:$C$3000,MATCH($A45,EXTRATO!$A$2:$A$3000,0)))) -> 46034 | C45: =IF(B45="","",MONTH(B45)) -> 1 | D45: ENTRADAS | E45: Resgate de Aplicações Financeiras (CDI BB) | F45: 2500 | G45: RESGATE BB CDB DI | H45: =IF(A45="","",IF(INDEX(EXTRATO!$F$2:$F$3000,MATCH($A45,EXTRATO!$A$2:$A$3000,0))="","",INDEX(EXTRATO!$F$2:$F$3000,MATCH($A45,EXTRATO!$A$2:$A$3000,0)))) -> RESGATE | I45: =IF(A45="","",IF(INDEX(EXTRATO!$H$2:$H$3000,MATCH($A45,EXTRATO!$A$2:$A$3000,0))="","",INDEX(EXTRATO!$H$2:$H$3000,MATCH($A45,EXTRATO!$A$2:$A$3000,0)))) -> BANCO DO BRASIL - CDB DI | J45: AUTOMÁTICO | K45: =IF(AND(A45="",D45="",E45="",F45=""),"",IF(D45="","SEM CATEGORIA",IF(E45="","SEM SUBCATEGORIA",IF(COUNTIFS(CADASTROS!$L$7:$L$93,D45,CADASTROS!$D$7:$D$93,E45)=0,"INCOMPATÍVEL","OK")))) -> OK
A46: BAN-00042 | B46: =IF(A46="","",IF(INDEX(EXTRATO!$C$2:$C$3000,MATCH($A46,EXTRATO!$A$2:$A$3000,0))="","",INDEX(EXTRATO!$C$2:$C$3000,MATCH($A46,EXTRATO!$A$2:$A$3000,0)))) -> 46035 | C46: =IF(B46="","",MONTH(B46)) -> 1 | D46: ENTRADAS | E46: Resgate de Aplicações Financeiras (CDI BB) | F46: 7.2 | G46: RESGATE BB CDB DI | H46: =IF(A46="","",IF(INDEX(EXTRATO!$F$2:$F$3000,MATCH($A46,EXTRATO!$A$2:$A$3000,0))="","",INDEX(EXTRATO!$F$2:$F$3000,MATCH($A46,EXTRATO!$A$2:$A$3000,0)))) -> RESGATE | I46: =IF(A46="","",IF(INDEX(EXTRATO!$H$2:$H$3000,MATCH($A46,EXTRATO!$A$2:$A$3000,0))="","",INDEX(EXTRATO!$H$2:$H$3000,MATCH($A46,EXTRATO!$A$2:$A$3000,0)))) -> BANCO DO BRASIL - CDB DI | J46: AUTOMÁTICO | K46: =IF(AND(A46="",D46="",E46="",F46=""),"",IF(D46="","SEM CATEGORIA",IF(E46="","SEM SUBCATEGORIA",IF(COUNTIFS(CADASTROS!$L$7:$L$93,D46,CADASTROS!$D$7:$D$93,E46)=0,"INCOMPATÍVEL","OK")))) -> OK
A47: BAN-00043 | B47: =IF(A47="","",IF(INDEX(EXTRATO!$C$2:$C$3000,MATCH($A47,EXTRATO!$A$2:$A$3000,0))="","",INDEX(EXTRATO!$C$2:$C$3000,MATCH($A47,EXTRATO!$A$2:$A$3000,0)))) -> 46035 | C47: =IF(B47="","",MONTH(B47)) -> 1 | D47: DESPESAS COM SALÁRIOS E BENEFÍCIOS | E47: Folha de Pagamento (Repasse de piso da Enfermagem) | F47: 30897.61 | G47: FOLHA DE PAGAMENTO (REF. PISO SALARIAL DA ENFERMAGEM - COMP. DEZ/2025) | H47: =IF(A47="","",IF(INDEX(EXTRATO!$F$2:$F$3000,MATCH($A47,EXTRATO!$A$2:$A$3000,0))="","",INDEX(EXTRATO!$F$2:$F$3000,MATCH($A47,EXTRATO!$A$2:$A$3000,0)))) -> SAÍDA | I47: =IF(A47="","",IF(INDEX(EXTRATO!$H$2:$H$3000,MATCH($A47,EXTRATO!$A$2:$A$3000,0))="","",INDEX(EXTRATO!$H$2:$H$3000,MATCH($A47,EXTRATO!$A$2:$A$3000,0)))) -> FOLHA DE PAGAMENTO - PISO | J47: MAPEADO | K47: =IF(AND(A47="",D47="",E47="",F47=""),"",IF(D47="","SEM CATEGORIA",IF(E47="","SEM SUBCATEGORIA",IF(COUNTIFS(CADASTROS!$L$7:$L$93,D47,CADASTROS!$D$7:$D$93,E47)=0,"INCOMPATÍVEL","OK")))) -> OK
A48: BAN-00044 | B48: =IF(A48="","",IF(INDEX(EXTRATO!$C$2:$C$3000,MATCH($A48,EXTRATO!$A$2:$A$3000,0))="","",INDEX(EXTRATO!$C$2:$C$3000,MATCH($A48,EXTRATO!$A$2:$A$3000,0)))) -> 46035 | C48: =IF(B48="","",MONTH(B48)) -> 1 | D48: DESPESAS ADMINISTRATIVAS | E48: Taxas e Tarifas | F48: 31.5 | G48: TARIFA PAGAMENTO DE SALÁRIO | H48: =IF(A48="","",IF(INDEX(EXTRATO!$F$2:$F$3000,MATCH($A48,EXTRATO!$A$2:$A$3000,0))="","",INDEX(EXTRATO!$F$2:$F$3000,MATCH($A48,EXTRATO!$A$2:$A$3000,0)))) -> SAÍDA | I48: =IF(A48="","",IF(INDEX(EXTRATO!$H$2:$H$3000,MATCH($A48,EXTRATO!$A$2:$A$3000,0))="","",INDEX(EXTRATO!$H$2:$H$3000,MATCH($A48,EXTRATO!$A$2:$A$3000,0)))) -> TARIFA BANCÁRIA | J48: MAPEADO | K48: =IF(AND(A48="",D48="",E48="",F48=""),"",IF(D48="","SEM CATEGORIA",IF(E48="","SEM SUBCATEGORIA",IF(COUNTIFS(CADASTROS!$L$7:$L$93,D48,CADASTROS!$D$7:$D$93,E48)=0,"INCOMPATÍVEL","OK")))) -> OK
A49: BAN-00045 | B49: =IF(A49="","",IF(INDEX(EXTRATO!$C$2:$C$3000,MATCH($A49,EXTRATO!$A$2:$A$3000,0))="","",INDEX(EXTRATO!$C$2:$C$3000,MATCH($A49,EXTRATO!$A$2:$A$3000,0)))) -> 46035 | C49: =IF(B49="","",MONTH(B49)) -> 1 | D49: ENTRADAS | E49: Resgate de Aplicações Financeiras (CDI BB) | F49: 31000 | G49: RESGATE BB CDB DI | H49: =IF(A49="","",IF(INDEX(EXTRATO!$F$2:$F$3000,MATCH($A49,EXTRATO!$A$2:$A$3000,0))="","",INDEX(EXTRATO!$F$2:$F$3000,MATCH($A49,EXTRATO!$A$2:$A$3000,0)))) -> RESGATE | I49: =IF(A49="","",IF(INDEX(EXTRATO!$H$2:$H$3000,MATCH($A49,EXTRATO!$A$2:$A$3000,0))="","",INDEX(EXTRATO!$H$2:$H$3000,MATCH($A49,EXTRATO!$A$2:$A$3000,0)))) -> BANCO DO BRASIL - CDB DI | J49: AUTOMÁTICO | K49: =IF(AND(A49="",D49="",E49="",F49=""),"",IF(D49="","SEM CATEGORIA",IF(E49="","SEM SUBCATEGORIA",IF(COUNTIFS(CADASTROS!$L$7:$L$93,D49,CADASTROS!$D$7:$D$93,E49)=0,"INCOMPATÍVEL","OK")))) -> OK
A50: BAN-00046 | B50: =IF(A50="","",IF(INDEX(EXTRATO!$C$2:$C$3000,MATCH($A50,EXTRATO!$A$2:$A$3000,0))="","",INDEX(EXTRATO!$C$2:$C$3000,MATCH($A50,EXTRATO!$A$2:$A$3000,0)))) -> 46036 | C50: =IF(B50="","",MONTH(B50)) -> 1 | D50: ENTRADAS | E50: Resgate de Aplicações Financeiras (CDI BB) | F50: 102.3 | G50: RESGATE BB CDB DI | H50: =IF(A50="","",IF(INDEX(EXTRATO!$F$2:$F$3000,MATCH($A50,EXTRATO!$A$2:$A$3000,0))="","",INDEX(EXTRATO!$F$2:$F$3000,MATCH($A50,EXTRATO!$A$2:$A$3000,0)))) -> RESGATE | I50: =IF(A50="","",IF(INDEX(EXTRATO!$H$2:$H$3000,MATCH($A50,EXTRATO!$A$2:$A$3000,0))="","",INDEX(EXTRATO!$H$2:$H$3000,MATCH($A50,EXTRATO!$A$2:$A$3000,0)))) -> BANCO DO BRASIL - CDB DI | J50: AUTOMÁTICO | K50: =IF(AND(A50="",D50="",E50="",F50=""),"",IF(D50="","SEM CATEGORIA",IF(E50="","SEM SUBCATEGORIA",IF(COUNTIFS(CADASTROS!$L$7:$L$93,D50,CADASTROS!$D$7:$D$93,E50)=0,"INCOMPATÍVEL","OK")))) -> OK
... A312: BAN-00289 | B312: =IF(A312="","",IF(INDEX(EXTRATO!$C$2:$C$3000,MATCH($A312,EXTRATO!$A$2:$A$3000,0))="","",INDEX(EXTRATO!$C$2:$C$3000,MATCH($A312,EXTRATO!$A$2:$A$3000,0)))) -> 46097 | C312: =IF(B312="","",MONTH(B312)) -> 3 | D312: DESPESAS ADMINISTRATIVAS | E312: Taxas e Tarifas | F312: 35 | G312: TARIFA BANCÁRIA (SALÁRIO CRÉD. CONTA) | H312: =IF(A312="","",IF(INDEX(EXTRATO!$F$2:$F$3000,MATCH($A312,EXTRATO!$A$2:$A$3000,0))="","",INDEX(EXTRATO!$F$2:$F$3000,MATCH($A312,EXTRATO!$A$2:$A$3000,0)))) -> SAÍDA | I312: =IF(A312="","",IF(INDEX(EXTRATO!$H$2:$H$3000,MATCH($A312,EXTRATO!$A$2:$A$3000,0))="","",INDEX(EXTRATO!$H$2:$H$3000,MATCH($A312,EXTRATO!$A$2:$A$3000,0)))) -> TARIFA BANCÁRIA | J312: MAPEADO | K312: =IF(AND(A312="",D312="",E312="",F312=""),"",IF(D312="","SEM CATEGORIA",IF(E312="","SEM SUBCATEGORIA",IF(COUNTIFS(CADASTROS!$L$7:$L$93,D312,CADASTROS!$D$7:$D$93,E312)=0,"INCOMPATÍVEL","OK")))) -> OK
A313: BAN-00290 | B313: =IF(A313="","",IF(INDEX(EXTRATO!$C$2:$C$3000,MATCH($A313,EXTRATO!$A$2:$A$3000,0))="","",INDEX(EXTRATO!$C$2:$C$3000,MATCH($A313,EXTRATO!$A$2:$A$3000,0)))) -> 46098 | C313: =IF(B313="","",MONTH(B313)) -> 3 | D313: DESPESAS COM MATERIAIS PARA HEMODIÁLISE E DEMAIS CUSTOS | E313: Solução e Soro para HD | F313: =19012+31.04 -> 19043.04 | G313: FARMACE (REF. SOROS E SOLUÇÕES ) 1/2 | H313: =IF(A313="","",IF(INDEX(EXTRATO!$F$2:$F$3000,MATCH($A313,EXTRATO!$A$2:$A$3000,0))="","",INDEX(EXTRATO!$F$2:$F$3000,MATCH($A313,EXTRATO!$A$2:$A$3000,0)))) -> SAÍDA | I313: =IF(A313="","",IF(INDEX(EXTRATO!$H$2:$H$3000,MATCH($A313,EXTRATO!$A$2:$A$3000,0))="","",INDEX(EXTRATO!$H$2:$H$3000,MATCH($A313,EXTRATO!$A$2:$A$3000,0)))) -> FARMACE | J313: MAPEADO | K313: =IF(AND(A313="",D313="",E313="",F313=""),"",IF(D313="","SEM CATEGORIA",IF(E313="","SEM SUBCATEGORIA",IF(COUNTIFS(CADASTROS!$L$7:$L$93,D313,CADASTROS!$D$7:$D$93,E313)=0,"INCOMPATÍVEL","OK")))) -> OK
A314: BAN-00290 | B314: =IF(A314="","",IF(INDEX(EXTRATO!$C$2:$C$3000,MATCH($A314,EXTRATO!$A$2:$A$3000,0))="","",INDEX(EXTRATO!$C$2:$C$3000,MATCH($A314,EXTRATO!$A$2:$A$3000,0)))) -> 46098 | C314: =IF(B314="","",MONTH(B314)) -> 3 | D314: DESPESAS COM MATERIAIS PARA HEMODIÁLISE E DEMAIS CUSTOS | E314: Agulhas, Seringas, Máscaras, Luvas, Equipo e Med. Div. | F314: 43.57 | G314: FARMACE (REF. DIPIRONA INJETÁVEL) 1/2 | H314: =IF(A314="","",IF(INDEX(EXTRATO!$F$2:$F$3000,MATCH($A314,EXTRATO!$A$2:$A$3000,0))="","",INDEX(EXTRATO!$F$2:$F$3000,MATCH($A314,EXTRATO!$A$2:$A$3000,0)))) -> SAÍDA | I314: =IF(A314="","",IF(INDEX(EXTRATO!$H$2:$H$3000,MATCH($A314,EXTRATO!$A$2:$A$3000,0))="","",INDEX(EXTRATO!$H$2:$H$3000,MATCH($A314,EXTRATO!$A$2:$A$3000,0)))) -> FARMACE | J314: MAPEADO | K314: =IF(AND(A314="",D314="",E314="",F314=""),"",IF(D314="","SEM CATEGORIA",IF(E314="","SEM SUBCATEGORIA",IF(COUNTIFS(CADASTROS!$L$7:$L$93,D314,CADASTROS!$D$7:$D$93,E314)=0,"INCOMPATÍVEL","OK")))) -> OK
A315: BAN-00291 | B315: =IF(A315="","",IF(INDEX(EXTRATO!$C$2:$C$3000,MATCH($A315,EXTRATO!$A$2:$A$3000,0))="","",INDEX(EXTRATO!$C$2:$C$3000,MATCH($A315,EXTRATO!$A$2:$A$3000,0)))) -> 46098 | C315: =IF(B315="","",MONTH(B315)) -> 3 | D315: MANUTENÇÃO E INFRAESTRUTURA | E315: Manutenção - Ar Condicionados | F315: 2450 | G315: TOTAL FRIO COMERCIO SERVICOS LTDA (REF. A LIMPEZA DOS 04 ARES-CONDICIONADOS DA SALA DE HD, CAPACITOR AR CONDICIONADO DA RECEPÇÃO E RECARGA DE GÁS) | H315: =IF(A315="","",IF(INDEX(EXTRATO!$F$2:$F$3000,MATCH($A315,EXTRATO!$A$2:$A$3000,0))="","",INDEX(EXTRATO!$F$2:$F$3000,MATCH($A315,EXTRATO!$A$2:$A$3000,0)))) -> SAÍDA | I315: =IF(A315="","",IF(INDEX(EXTRATO!$H$2:$H$3000,MATCH($A315,EXTRATO!$A$2:$A$3000,0))="","",INDEX(EXTRATO!$H$2:$H$3000,MATCH($A315,EXTRATO!$A$2:$A$3000,0)))) -> TOTAL FRIO COMERCIO SERVICOS LTDA | J315: MAPEADO | K315: =IF(AND(A315="",D315="",E315="",F315=""),"",IF(D315="","SEM CATEGORIA",IF(E315="","SEM SUBCATEGORIA",IF(COUNTIFS(CADASTROS!$L$7:$L$93,D315,CADASTROS!$D$7:$D$93,E315)=0,"INCOMPATÍVEL","OK")))) -> OK
A316: BAN-00292 | B316: =IF(A316="","",IF(INDEX(EXTRATO!$C$2:$C$3000,MATCH($A316,EXTRATO!$A$2:$A$3000,0))="","",INDEX(EXTRATO!$C$2:$C$3000,MATCH($A316,EXTRATO!$A$2:$A$3000,0)))) -> 46098 | C316: =IF(B316="","",MONTH(B316)) -> 3 | D316: DESPESAS ADMINISTRATIVAS | E316: Taxas e Tarifas | F316: 1500 | G316: JOSE RAIMUNDO VASCONCELOS - NF AGUAGEO-COMERCIO E CONSTRUCAO DE POCOS TUBULARES LTDA (REF. CORREÇÃO DE LICENÇA DE PERFURAÇÃO DO POÇO) | H316: =IF(A316="","",IF(INDEX(EXTRATO!$F$2:$F$3000,MATCH($A316,EXTRATO!$A$2:$A$3000,0))="","",INDEX(EXTRATO!$F$2:$F$3000,MATCH($A316,EXTRATO!$A$2:$A$3000,0)))) -> SAÍDA | I316: =IF(A316="","",IF(INDEX(EXTRATO!$H$2:$H$3000,MATCH($A316,EXTRATO!$A$2:$A$3000,0))="","",INDEX(EXTRATO!$H$2:$H$3000,MATCH($A316,EXTRATO!$A$2:$A$3000,0)))) -> JOSE RAIMUNDO VASCONCELOS | J316: MAPEADO | K316: =IF(AND(A316="",D316="",E316="",F316=""),"",IF(D316="","SEM CATEGORIA",IF(E316="","SEM SUBCATEGORIA",IF(COUNTIFS(CADASTROS!$L$7:$L$93,D316,CADASTROS!$D$7:$D$93,E316)=0,"INCOMPATÍVEL","OK")))) -> OK
A317: BAN-00293 | B317: =IF(A317="","",IF(INDEX(EXTRATO!$C$2:$C$3000,MATCH($A317,EXTRATO!$A$2:$A$3000,0))="","",INDEX(EXTRATO!$C$2:$C$3000,MATCH($A317,EXTRATO!$A$2:$A$3000,0)))) -> 46098 | C317: =IF(B317="","",MONTH(B317)) -> 3 | D317: DESPESAS ADMINISTRATIVAS | E317: Materiais de Construção, Elétrico e de Escritório | F317: 692.03 | G317: MARKETPLACE MERCADO LIVRE (VÁRIOS FORNECEDORES) - REF. MATERIAIS DE ESCRITÓRIO | H317: =IF(A317="","",IF(INDEX(EXTRATO!$F$2:$F$3000,MATCH($A317,EXTRATO!$A$2:$A$3000,0))="","",INDEX(EXTRATO!$F$2:$F$3000,MATCH($A317,EXTRATO!$A$2:$A$3000,0)))) -> SAÍDA | I317: =IF(A317="","",IF(INDEX(EXTRATO!$H$2:$H$3000,MATCH($A317,EXTRATO!$A$2:$A$3000,0))="","",INDEX(EXTRATO!$H$2:$H$3000,MATCH($A317,EXTRATO!$A$2:$A$3000,0)))) -> MARKETPLACE MERCADO LIVRE | J317: MAPEADO | K317: =IF(AND(A317="",D317="",E317="",F317=""),"",IF(D317="","SEM CATEGORIA",IF(E317="","SEM SUBCATEGORIA",IF(COUNTIFS(CADASTROS!$L$7:$L$93,D317,CADASTROS!$D$7:$D$93,E317)=0,"INCOMPATÍVEL","OK")))) -> OK
A318: BAN-00293 | B318: =IF(A318="","",IF(INDEX(EXTRATO!$C$2:$C$3000,MATCH($A318,EXTRATO!$A$2:$A$3000,0))="","",INDEX(EXTRATO!$C$2:$C$3000,MATCH($A318,EXTRATO!$A$2:$A$3000,0)))) -> 46098 | C318: =IF(B318="","",MONTH(B318)) -> 3 | D318: AQUISIÇÃO DE BENS E EQUIPAMENTOS | E318: Mobiliário e utensílios duráveis | F318: 135.12 | G318: MARKETPLACE MERCADO LIVRE (VÁRIOS FORNECEDORES) - REF. BANDEJAS P/ MÁQUINAS | H318: =IF(A318="","",IF(INDEX(EXTRATO!$F$2:$F$3000,MATCH($A318,EXTRATO!$A$2:$A$3000,0))="","",INDEX(EXTRATO!$F$2:$F$3000,MATCH($A318,EXTRATO!$A$2:$A$3000,0)))) -> SAÍDA | I318: =IF(A318="","",IF(INDEX(EXTRATO!$H$2:$H$3000,MATCH($A318,EXTRATO!$A$2:$A$3000,0))="","",INDEX(EXTRATO!$H$2:$H$3000,MATCH($A318,EXTRATO!$A$2:$A$3000,0)))) -> MARKETPLACE MERCADO LIVRE | J318: MAPEADO | K318: =IF(AND(A318="",D318="",E318="",F318=""),"",IF(D318="","SEM CATEGORIA",IF(E318="","SEM SUBCATEGORIA",IF(COUNTIFS(CADASTROS!$L$7:$L$93,D318,CADASTROS!$D$7:$D$93,E318)=0,"INCOMPATÍVEL","OK")))) -> OK
A319: BAN-00293 | B319: =IF(A319="","",IF(INDEX(EXTRATO!$C$2:$C$3000,MATCH($A319,EXTRATO!$A$2:$A$3000,0))="","",INDEX(EXTRATO!$C$2:$C$3000,MATCH($A319,EXTRATO!$A$2:$A$3000,0)))) -> 46098 | C319: =IF(B319="","",MONTH(B319)) -> 3 | D319: MANUTENÇÃO E INFRAESTRUTURA | E319: Manutenção Predial (Reformas e Reparos) | F319: 44.68 | G319: MARKETPLACE MERCADO LIVRE (VÁRIOS FORNECEDORES) - REF. COLA PARA TUBULAÇÃO | H319: =IF(A319="","",IF(INDEX(EXTRATO!$F$2:$F$3000,MATCH($A319,EXTRATO!$A$2:$A$3000,0))="","",INDEX(EXTRATO!$F$2:$F$3000,MATCH($A319,EXTRATO!$A$2:$A$3000,0)))) -> SAÍDA | I319: =IF(A319="","",IF(INDEX(EXTRATO!$H$2:$H$3000,MATCH($A319,EXTRATO!$A$2:$A$3000,0))="","",INDEX(EXTRATO!$H$2:$H$3000,MATCH($A319,EXTRATO!$A$2:$A$3000,0)))) -> MARKETPLACE MERCADO LIVRE | J319: MAPEADO | K319: =IF(AND(A319="",D319="",E319="",F319=""),"",IF(D319="","SEM CATEGORIA",IF(E319="","SEM SUBCATEGORIA",IF(COUNTIFS(CADASTROS!$L$7:$L$93,D319,CADASTROS!$D$7:$D$93,E319)=0,"INCOMPATÍVEL","OK")))) -> OK
A320: BAN-00294 | B320: =IF(A320="","",IF(INDEX(EXTRATO!$C$2:$C$3000,MATCH($A320,EXTRATO!$A$2:$A$3000,0))="","",INDEX(EXTRATO!$C$2:$C$3000,MATCH($A320,EXTRATO!$A$2:$A$3000,0)))) -> 46098 | C320: =IF(B320="","",MONTH(B320)) -> 3 | D320: DESPESAS ADMINISTRATIVAS | E320: Taxas e Tarifas | F320: 200 | G320: GUIA DE RECOLHIMENTO DE ALVARÁ FUNCIONAMENTO 2026 | H320: =IF(A320="","",IF(INDEX(EXTRATO!$F$2:$F$3000,MATCH($A320,EXTRATO!$A$2:$A$3000,0))="","",INDEX(EXTRATO!$F$2:$F$3000,MATCH($A320,EXTRATO!$A$2:$A$3000,0)))) -> SAÍDA | I320: =IF(A320="","",IF(INDEX(EXTRATO!$H$2:$H$3000,MATCH($A320,EXTRATO!$A$2:$A$3000,0))="","",INDEX(EXTRATO!$H$2:$H$3000,MATCH($A320,EXTRATO!$A$2:$A$3000,0)))) -> GUIA DE RECOLHIMENTO DE ALVARÁ FUNCIONAMENTO 2026 | J320: MAPEADO | K320: =IF(AND(A320="",D320="",E320="",F320=""),"",IF(D320="","SEM CATEGORIA",IF(E320="","SEM SUBCATEGORIA",IF(COUNTIFS(CADASTROS!$L$7:$L$93,D320,CADASTROS!$D$7:$D$93,E320)=0,"INCOMPATÍVEL","OK")))) -> OK
A321: BAN-00295 | B321: =IF(A321="","",IF(INDEX(EXTRATO!$C$2:$C$3000,MATCH($A321,EXTRATO!$A$2:$A$3000,0))="","",INDEX(EXTRATO!$C$2:$C$3000,MATCH($A321,EXTRATO!$A$2:$A$3000,0)))) -> 46099 | C321: =IF(B321="","",MONTH(B321)) -> 3 | D321: DESPESAS ADMINISTRATIVAS | E321: Assessoria Administrativa | F321: 7700 | G321: HR MANUTENÇÃO HOSPITALAR (REF. PREST. DE SERV. ASSESSORIA ADMINISTRATIVA - REF. DEZ/25) | H321: =IF(A321="","",IF(INDEX(EXTRATO!$F$2:$F$3000,MATCH($A321,EXTRATO!$A$2:$A$3000,0))="","",INDEX(EXTRATO!$F$2:$F$3000,MATCH($A321,EXTRATO!$A$2:$A$3000,0)))) -> SAÍDA | I321: =IF(A321="","",IF(INDEX(EXTRATO!$H$2:$H$3000,MATCH($A321,EXTRATO!$A$2:$A$3000,0))="","",INDEX(EXTRATO!$H$2:$H$3000,MATCH($A321,EXTRATO!$A$2:$A$3000,0)))) -> ASSESSORIA ADMINISTRATIVA | J321: MAPEADO | K321: =IF(AND(A321="",D321="",E321="",F321=""),"",IF(D321="","SEM CATEGORIA",IF(E321="","SEM SUBCATEGORIA",IF(COUNTIFS(CADASTROS!$L$7:$L$93,D321,CADASTROS!$D$7:$D$93,E321)=0,"INCOMPATÍVEL","OK")))) -> OK
A322: BAN-00296 | B322: =IF(A322="","",IF(INDEX(EXTRATO!$C$2:$C$3000,MATCH($A322,EXTRATO!$A$2:$A$3000,0))="","",INDEX(EXTRATO!$C$2:$C$3000,MATCH($A322,EXTRATO!$A$2:$A$3000,0)))) -> 46099 | C322: =IF(B322="","",MONTH(B322)) -> 3 | D322: DESPESAS COM MATERIAIS PARA HEMODIÁLISE E DEMAIS CUSTOS | E322: Capilar, Filtros, Agulhas | F322: 2750 | G322: NIPRO MEDICAL (REF. FILTROS DE ENDOTOXINA) 2/2 | H322: =IF(A322="","",IF(INDEX(EXTRATO!$F$2:$F$3000,MATCH($A322,EXTRATO!$A$2:$A$3000,0))="","",INDEX(EXTRATO!$F$2:$F$3000,MATCH($A322,EXTRATO!$A$2:$A$3000,0)))) -> SAÍDA | I322: =IF(A322="","",IF(INDEX(EXTRATO!$H$2:$H$3000,MATCH($A322,EXTRATO!$A$2:$A$3000,0))="","",INDEX(EXTRATO!$H$2:$H$3000,MATCH($A322,EXTRATO!$A$2:$A$3000,0)))) -> NIPRO | J322: MAPEADO | K322: =IF(AND(A322="",D322="",E322="",F322=""),"",IF(D322="","SEM CATEGORIA",IF(E322="","SEM SUBCATEGORIA",IF(COUNTIFS(CADASTROS!$L$7:$L$93,D322,CADASTROS!$D$7:$D$93,E322)=0,"INCOMPATÍVEL","OK")))) -> OK
A323: BAN-00297 | B323: =IF(A323="","",IF(INDEX(EXTRATO!$C$2:$C$3000,MATCH($A323,EXTRATO!$A$2:$A$3000,0))="","",INDEX(EXTRATO!$C$2:$C$3000,MATCH($A323,EXTRATO!$A$2:$A$3000,0)))) -> 46099 | C323: =IF(B323="","",MONTH(B323)) -> 3 | D323: LOGÍSTICA E FROTA | E323: Transporte de pacientes e viagens para HTI | F323: 1246 | G323: CLAUDIANE CARDOSO SILVA (REF. VIAGEM HTI) | H323: =IF(A323="","",IF(INDEX(EXTRATO!$F$2:$F$3000,MATCH($A323,EXTRATO!$A$2:$A$3000,0))="","",INDEX(EXTRATO!$F$2:$F$3000,MATCH($A323,EXTRATO!$A$2:$A$3000,0)))) -> SAÍDA | I323: =IF(A323="","",IF(INDEX(EXTRATO!$H$2:$H$3000,MATCH($A323,EXTRATO!$A$2:$A$3000,0))="","",INDEX(EXTRATO!$H$2:$H$3000,MATCH($A323,EXTRATO!$A$2:$A$3000,0)))) -> CLAUDIANE CARDOSO DA SILVA (CARRO HTI) | J323: MAPEADO | K323: =IF(AND(A323="",D323="",E323="",F323=""),"",IF(D323="","SEM CATEGORIA",IF(E323="","SEM SUBCATEGORIA",IF(COUNTIFS(CADASTROS!$L$7:$L$93,D323,CADASTROS!$D$7:$D$93,E323)=0,"INCOMPATÍVEL","OK")))) -> OK
A324: BAN-00298 | B324: =IF(A324="","",IF(INDEX(EXTRATO!$C$2:$C$3000,MATCH($A324,EXTRATO!$A$2:$A$3000,0))="","",INDEX(EXTRATO!$C$2:$C$3000,MATCH($A324,EXTRATO!$A$2:$A$3000,0)))) -> 46099 | C324: =IF(B324="","",MONTH(B324)) -> 3 | D324: DESPESAS ADMINISTRATIVAS | E324: Taxas e Tarifas | F324: 400 | G324: BIO RENAL LTDA (REF. TAXA DE MANUTENÇÃO DA CONTA - BANCO DO NORDESTE) | H324: =IF(A324="","",IF(INDEX(EXTRATO!$F$2:$F$3000,MATCH($A324,EXTRATO!$A$2:$A$3000,0))="","",INDEX(EXTRATO!$F$2:$F$3000,MATCH($A324,EXTRATO!$A$2:$A$3000,0)))) -> SAÍDA | I324: =IF(A324="","",IF(INDEX(EXTRATO!$H$2:$H$3000,MATCH($A324,EXTRATO!$A$2:$A$3000,0))="","",INDEX(EXTRATO!$H$2:$H$3000,MATCH($A324,EXTRATO!$A$2:$A$3000,0)))) -> BIORENAL LTDA | J324: MAPEADO | K324: =IF(AND(A324="",D324="",E324="",F324=""),"",IF(D324="","SEM CATEGORIA",IF(E324="","SEM SUBCATEGORIA",IF(COUNTIFS(CADASTROS!$L$7:$L$93,D324,CADASTROS!$D$7:$D$93,E324)=0,"INCOMPATÍVEL","OK")))) -> OK
A325: BAN-00299 | B325: =IF(A325="","",IF(INDEX(EXTRATO!$C$2:$C$3000,MATCH($A325,EXTRATO!$A$2:$A$3000,0))="","",INDEX(EXTRATO!$C$2:$C$3000,MATCH($A325,EXTRATO!$A$2:$A$3000,0)))) -> 46099 | C325: =IF(B325="","",MONTH(B325)) -> 3 | D325: DESPESAS ADMINISTRATIVAS | E325: Contador | F325: 300 | G325: CASSIANO E CASSIANO (REF. SISTEMA FINANCEIRO) | H325: =IF(A325="","",IF(INDEX(EXTRATO!$F$2:$F$3000,MATCH($A325,EXTRATO!$A$2:$A$3000,0))="","",INDEX(EXTRATO!$F$2:$F$3000,MATCH($A325,EXTRATO!$A$2:$A$3000,0)))) -> SAÍDA | I325: =IF(A325="","",IF(INDEX(EXTRATO!$H$2:$H$3000,MATCH($A325,EXTRATO!$A$2:$A$3000,0))="","",INDEX(EXTRATO!$H$2:$H$3000,MATCH($A325,EXTRATO!$A$2:$A$3000,0)))) -> CASSIANO & CASSINOS CONTABILIDADE | J325: MAPEADO | K325: =IF(AND(A325="",D325="",E325="",F325=""),"",IF(D325="","SEM CATEGORIA",IF(E325="","SEM SUBCATEGORIA",IF(COUNTIFS(CADASTROS!$L$7:$L$93,D325,CADASTROS!$D$7:$D$93,E325)=0,"INCOMPATÍVEL","OK")))) -> OK
... A572: BAN-00510 | B572: =IF(A572="","",IF(INDEX(EXTRATO!$C$2:$C$3000,MATCH($A572,EXTRATO!$A$2:$A$3000,0))="","",INDEX(EXTRATO!$C$2:$C$3000,MATCH($A572,EXTRATO!$A$2:$A$3000,0)))) -> 46163 | C572: =IF(B572="","",MONTH(B572)) -> 5 | D572: DESPESAS COM PRESTADORES DE SERVIÇOS EM SAÚDE - TERCEIROS | E572: Pagamento de plantão médico - Dr. Hozano | F572: 4000 | G572: MARTINS MACHADO SAUDE E E (DR. HOZANO - REF. PLANTÕES MÉDICOS EM MAR/26) | H572: =IF(A572="","",IF(INDEX(EXTRATO!$F$2:$F$3000,MATCH($A572,EXTRATO!$A$2:$A$3000,0))="","",INDEX(EXTRATO!$F$2:$F$3000,MATCH($A572,EXTRATO!$A$2:$A$3000,0)))) -> SAÍDA | I572: =IF(A572="","",IF(INDEX(EXTRATO!$H$2:$H$3000,MATCH($A572,EXTRATO!$A$2:$A$3000,0))="","",INDEX(EXTRATO!$H$2:$H$3000,MATCH($A572,EXTRATO!$A$2:$A$3000,0)))) -> MARTINS MACHADO SAUDE E E | J572: MAPEADO | K572: =IF(AND(A572="",D572="",E572="",F572=""),"",IF(D572="","SEM CATEGORIA",IF(E572="","SEM SUBCATEGORIA",IF(COUNTIFS(CADASTROS!$L$7:$L$93,D572,CADASTROS!$D$7:$D$93,E572)=0,"INCOMPATÍVEL","OK")))) -> OK
A573: BAN-00511 | B573: =IF(A573="","",IF(INDEX(EXTRATO!$C$2:$C$3000,MATCH($A573,EXTRATO!$A$2:$A$3000,0))="","",INDEX(EXTRATO!$C$2:$C$3000,MATCH($A573,EXTRATO!$A$2:$A$3000,0)))) -> 46163 | C573: =IF(B573="","",MONTH(B573)) -> 5 | F573: 997.92 | H573: =IF(A573="","",IF(INDEX(EXTRATO!$F$2:$F$3000,MATCH($A573,EXTRATO!$A$2:$A$3000,0))="","",INDEX(EXTRATO!$F$2:$F$3000,MATCH($A573,EXTRATO!$A$2:$A$3000,0)))) -> ENTRADA | I573: =IF(A573="","",IF(INDEX(EXTRATO!$H$2:$H$3000,MATCH($A573,EXTRATO!$A$2:$A$3000,0))="","",INDEX(EXTRATO!$H$2:$H$3000,MATCH($A573,EXTRATO!$A$2:$A$3000,0)))) -> ADELIA DALVA DA SILVA | J573: AUTOMÁTICO | K573: =IF(AND(A573="",D573="",E573="",F573=""),"",IF(D573="","SEM CATEGORIA",IF(E573="","SEM SUBCATEGORIA",IF(COUNTIFS(CADASTROS!$L$7:$L$93,D573,CADASTROS!$D$7:$D$93,E573)=0,"INCOMPATÍVEL","OK")))) -> SEM CATEGORIA
A574: BAN-00512 | B574: =IF(A574="","",IF(INDEX(EXTRATO!$C$2:$C$3000,MATCH($A574,EXTRATO!$A$2:$A$3000,0))="","",INDEX(EXTRATO!$C$2:$C$3000,MATCH($A574,EXTRATO!$A$2:$A$3000,0)))) -> 46163 | C574: =IF(B574="","",MONTH(B574)) -> 5 | D574: ENTRADAS | E574: Resgate do Financiamento (Banco do Nordeste) | F574: 100000 | G574: BIORENAL LTDA (REF. DEPÓSITO DO FINANCIAMENTO) | H574: =IF(A574="","",IF(INDEX(EXTRATO!$F$2:$F$3000,MATCH($A574,EXTRATO!$A$2:$A$3000,0))="","",INDEX(EXTRATO!$F$2:$F$3000,MATCH($A574,EXTRATO!$A$2:$A$3000,0)))) -> ENTRADA | I574: =IF(A574="","",IF(INDEX(EXTRATO!$H$2:$H$3000,MATCH($A574,EXTRATO!$A$2:$A$3000,0))="","",INDEX(EXTRATO!$H$2:$H$3000,MATCH($A574,EXTRATO!$A$2:$A$3000,0)))) -> BIORENAL LTDA | J574: AUTOMÁTICO | K574: =IF(AND(A574="",D574="",E574="",F574=""),"",IF(D574="","SEM CATEGORIA",IF(E574="","SEM SUBCATEGORIA",IF(COUNTIFS(CADASTROS!$L$7:$L$93,D574,CADASTROS!$D$7:$D$93,E574)=0,"INCOMPATÍVEL","OK")))) -> OK
A575: BAN-00513 | B575: =IF(A575="","",IF(INDEX(EXTRATO!$C$2:$C$3000,MATCH($A575,EXTRATO!$A$2:$A$3000,0))="","",INDEX(EXTRATO!$C$2:$C$3000,MATCH($A575,EXTRATO!$A$2:$A$3000,0)))) -> 46164 | C575: =IF(B575="","",MONTH(B575)) -> 5 | D575: DESPESAS COM MATERIAIS PARA HEMODIÁLISE E DEMAIS CUSTOS | E575: Solução e Soro para HD | F575: 16999.6 | G575: FARMACE (REF. SOROS E SOLUÇÕES) 1/2 | H575: =IF(A575="","",IF(INDEX(EXTRATO!$F$2:$F$3000,MATCH($A575,EXTRATO!$A$2:$A$3000,0))="","",INDEX(EXTRATO!$F$2:$F$3000,MATCH($A575,EXTRATO!$A$2:$A$3000,0)))) -> SAÍDA | I575: =IF(A575="","",IF(INDEX(EXTRATO!$H$2:$H$3000,MATCH($A575,EXTRATO!$A$2:$A$3000,0))="","",INDEX(EXTRATO!$H$2:$H$3000,MATCH($A575,EXTRATO!$A$2:$A$3000,0)))) -> FARMACE | J575: MAPEADO | K575: =IF(AND(A575="",D575="",E575="",F575=""),"",IF(D575="","SEM CATEGORIA",IF(E575="","SEM SUBCATEGORIA",IF(COUNTIFS(CADASTROS!$L$7:$L$93,D575,CADASTROS!$D$7:$D$93,E575)=0,"INCOMPATÍVEL","OK")))) -> OK
A576: BAN-00513 | B576: =IF(A576="","",IF(INDEX(EXTRATO!$C$2:$C$3000,MATCH($A576,EXTRATO!$A$2:$A$3000,0))="","",INDEX(EXTRATO!$C$2:$C$3000,MATCH($A576,EXTRATO!$A$2:$A$3000,0)))) -> 46164 | C576: =IF(B576="","",MONTH(B576)) -> 5 | D576: DESPESAS COM MATERIAIS PARA HEMODIÁLISE E DEMAIS CUSTOS | E576: Agulhas, Seringas, Máscaras, Luvas, Equipo e Med. Div. | F576: 340 | G576: FARMACE (REF. DIPIRONA INJETÁVEL, CLORETO DE SÓDIO 10%, ÁGUA DESTILADA E PARACETAMOL) 1/2 | H576: =IF(A576="","",IF(INDEX(EXTRATO!$F$2:$F$3000,MATCH($A576,EXTRATO!$A$2:$A$3000,0))="","",INDEX(EXTRATO!$F$2:$F$3000,MATCH($A576,EXTRATO!$A$2:$A$3000,0)))) -> SAÍDA | I576: =IF(A576="","",IF(INDEX(EXTRATO!$H$2:$H$3000,MATCH($A576,EXTRATO!$A$2:$A$3000,0))="","",INDEX(EXTRATO!$H$2:$H$3000,MATCH($A576,EXTRATO!$A$2:$A$3000,0)))) -> FARMACE | J576: MAPEADO | K576: =IF(AND(A576="",D576="",E576="",F576=""),"",IF(D576="","SEM CATEGORIA",IF(E576="","SEM SUBCATEGORIA",IF(COUNTIFS(CADASTROS!$L$7:$L$93,D576,CADASTROS!$D$7:$D$93,E576)=0,"INCOMPATÍVEL","OK")))) -> OK
A577: BAN-00514 | B577: =IF(A577="","",IF(INDEX(EXTRATO!$C$2:$C$3000,MATCH($A577,EXTRATO!$A$2:$A$3000,0))="","",INDEX(EXTRATO!$C$2:$C$3000,MATCH($A577,EXTRATO!$A$2:$A$3000,0)))) -> 46164 | C577: =IF(B577="","",MONTH(B577)) -> 5 | D577: DESPESAS COM PRESTADORES DE SERVIÇOS EM SAÚDE - TERCEIROS | E577: Exames Laboratorias dos Pacientes | F577: 16357.94 | G577: UNICLINICA (REF. EXAMES DE PACIENTES) - MAR/26 | H577: =IF(A577="","",IF(INDEX(EXTRATO!$F$2:$F$3000,MATCH($A577,EXTRATO!$A$2:$A$3000,0))="","",INDEX(EXTRATO!$F$2:$F$3000,MATCH($A577,EXTRATO!$A$2:$A$3000,0)))) -> SAÍDA | I577: =IF(A577="","",IF(INDEX(EXTRATO!$H$2:$H$3000,MATCH($A577,EXTRATO!$A$2:$A$3000,0))="","",INDEX(EXTRATO!$H$2:$H$3000,MATCH($A577,EXTRATO!$A$2:$A$3000,0)))) -> UNICLINICA | J577: MAPEADO | K577: =IF(AND(A577="",D577="",E577="",F577=""),"",IF(D577="","SEM CATEGORIA",IF(E577="","SEM SUBCATEGORIA",IF(COUNTIFS(CADASTROS!$L$7:$L$93,D577,CADASTROS!$D$7:$D$93,E577)=0,"INCOMPATÍVEL","OK")))) -> OK
A578: BAN-00515 | B578: =IF(A578="","",IF(INDEX(EXTRATO!$C$2:$C$3000,MATCH($A578,EXTRATO!$A$2:$A$3000,0))="","",INDEX(EXTRATO!$C$2:$C$3000,MATCH($A578,EXTRATO!$A$2:$A$3000,0)))) -> 46164 | C578: =IF(B578="","",MONTH(B578)) -> 5 | D578: DESPESAS ADMINISTRATIVAS | E578: Assessoria Administrativa | F578: 7700 | G578: HR MANUTENÇÃO HOSPITALAR (REF. PREST. DE SERV. ASSESSORIA ADMINISTRATIVA - REF. FEV/26) | H578: =IF(A578="","",IF(INDEX(EXTRATO!$F$2:$F$3000,MATCH($A578,EXTRATO!$A$2:$A$3000,0))="","",INDEX(EXTRATO!$F$2:$F$3000,MATCH($A578,EXTRATO!$A$2:$A$3000,0)))) -> SAÍDA | I578: =IF(A578="","",IF(INDEX(EXTRATO!$H$2:$H$3000,MATCH($A578,EXTRATO!$A$2:$A$3000,0))="","",INDEX(EXTRATO!$H$2:$H$3000,MATCH($A578,EXTRATO!$A$2:$A$3000,0)))) -> ASSESSORIA ADMINISTRATIVA | J578: MAPEADO | K578: =IF(AND(A578="",D578="",E578="",F578=""),"",IF(D578="","SEM CATEGORIA",IF(E578="","SEM SUBCATEGORIA",IF(COUNTIFS(CADASTROS!$L$7:$L$93,D578,CADASTROS!$D$7:$D$93,E578)=0,"INCOMPATÍVEL","OK")))) -> OK
A579: BAN-00516 | B579: =IF(A579="","",IF(INDEX(EXTRATO!$C$2:$C$3000,MATCH($A579,EXTRATO!$A$2:$A$3000,0))="","",INDEX(EXTRATO!$C$2:$C$3000,MATCH($A579,EXTRATO!$A$2:$A$3000,0)))) -> 46164 | C579: =IF(B579="","",MONTH(B579)) -> 5 | D579: DESPESAS ADMINISTRATIVAS | E579: Assessoria Administrativa | F579: 7700 | G579: HR MANUTENÇÃO HOSPITALAR (REF. PREST. DE SERV. ASSESSORIA ADMINISTRATIVA - REF. MAR/26) | H579: =IF(A579="","",IF(INDEX(EXTRATO!$F$2:$F$3000,MATCH($A579,EXTRATO!$A$2:$A$3000,0))="","",INDEX(EXTRATO!$F$2:$F$3000,MATCH($A579,EXTRATO!$A$2:$A$3000,0)))) -> SAÍDA | I579: =IF(A579="","",IF(INDEX(EXTRATO!$H$2:$H$3000,MATCH($A579,EXTRATO!$A$2:$A$3000,0))="","",INDEX(EXTRATO!$H$2:$H$3000,MATCH($A579,EXTRATO!$A$2:$A$3000,0)))) -> ASSESSORIA ADMINISTRATIVA | J579: MAPEADO | K579: =IF(AND(A579="",D579="",E579="",F579=""),"",IF(D579="","SEM CATEGORIA",IF(E579="","SEM SUBCATEGORIA",IF(COUNTIFS(CADASTROS!$L$7:$L$93,D579,CADASTROS!$D$7:$D$93,E579)=0,"INCOMPATÍVEL","OK")))) -> OK
A580: BAN-00517 | B580: =IF(A580="","",IF(INDEX(EXTRATO!$C$2:$C$3000,MATCH($A580,EXTRATO!$A$2:$A$3000,0))="","",INDEX(EXTRATO!$C$2:$C$3000,MATCH($A580,EXTRATO!$A$2:$A$3000,0)))) -> 46164 | C580: =IF(B580="","",MONTH(B580)) -> 5 | D580: DESPESAS COM MATERIAIS PARA HEMODIÁLISE E DEMAIS CUSTOS | E580: Capilar, Filtros, Agulhas | F580: 7583.75 | G580: NIPRO MEDICAL (REF. AGULHA 16, CAPILAR ELISIO 19H E FILTRO DE ENDOTOXINA) 1/2 | H580: =IF(A580="","",IF(INDEX(EXTRATO!$F$2:$F$3000,MATCH($A580,EXTRATO!$A$2:$A$3000,0))="","",INDEX(EXTRATO!$F$2:$F$3000,MATCH($A580,EXTRATO!$A$2:$A$3000,0)))) -> SAÍDA | I580: =IF(A580="","",IF(INDEX(EXTRATO!$H$2:$H$3000,MATCH($A580,EXTRATO!$A$2:$A$3000,0))="","",INDEX(EXTRATO!$H$2:$H$3000,MATCH($A580,EXTRATO!$A$2:$A$3000,0)))) -> NIPRO | J580: MAPEADO | K580: =IF(AND(A580="",D580="",E580="",F580=""),"",IF(D580="","SEM CATEGORIA",IF(E580="","SEM SUBCATEGORIA",IF(COUNTIFS(CADASTROS!$L$7:$L$93,D580,CADASTROS!$D$7:$D$93,E580)=0,"INCOMPATÍVEL","OK")))) -> OK
A581: BAN-00518 | B581: =IF(A581="","",IF(INDEX(EXTRATO!$C$2:$C$3000,MATCH($A581,EXTRATO!$A$2:$A$3000,0))="","",INDEX(EXTRATO!$C$2:$C$3000,MATCH($A581,EXTRATO!$A$2:$A$3000,0)))) -> 46164 | C581: =IF(B581="","",MONTH(B581)) -> 5 | D581: MANUTENÇÃO E INFRAESTRUTURA | E581: Manutenção - Máquinas HD, Gerador, Osmose | F581: 5100 | G581: HR MANUTENCAO HOSPITALAR E TRAT. DE AGUA (REF. PREST. DE SERV. HUGO RAMON) - MAR/26 + DUAS VISITAS EXTRAS | H581: =IF(A581="","",IF(INDEX(EXTRATO!$F$2:$F$3000,MATCH($A581,EXTRATO!$A$2:$A$3000,0))="","",INDEX(EXTRATO!$F$2:$F$3000,MATCH($A581,EXTRATO!$A$2:$A$3000,0)))) -> SAÍDA | I581: =IF(A581="","",IF(INDEX(EXTRATO!$H$2:$H$3000,MATCH($A581,EXTRATO!$A$2:$A$3000,0))="","",INDEX(EXTRATO!$H$2:$H$3000,MATCH($A581,EXTRATO!$A$2:$A$3000,0)))) -> HR MANUTENCAO HOSPITALAR | J581: MAPEADO | K581: =IF(AND(A581="",D581="",E581="",F581=""),"",IF(D581="","SEM CATEGORIA",IF(E581="","SEM SUBCATEGORIA",IF(COUNTIFS(CADASTROS!$L$7:$L$93,D581,CADASTROS!$D$7:$D$93,E581)=0,"INCOMPATÍVEL","OK")))) -> OK
A582: BAN-00519 | B582: =IF(A582="","",IF(INDEX(EXTRATO!$C$2:$C$3000,MATCH($A582,EXTRATO!$A$2:$A$3000,0))="","",INDEX(EXTRATO!$C$2:$C$3000,MATCH($A582,EXTRATO!$A$2:$A$3000,0)))) -> 46164 | C582: =IF(B582="","",MONTH(B582)) -> 5 | D582: DESPESAS COM MATERIAIS PARA HEMODIÁLISE E DEMAIS CUSTOS | E582: Solução e Soro para HD | F582: 3884.4 | G582: FARMACE (REF. SOROS) 1/2 | H582: =IF(A582="","",IF(INDEX(EXTRATO!$F$2:$F$3000,MATCH($A582,EXTRATO!$A$2:$A$3000,0))="","",INDEX(EXTRATO!$F$2:$F$3000,MATCH($A582,EXTRATO!$A$2:$A$3000,0)))) -> SAÍDA | I582: =IF(A582="","",IF(INDEX(EXTRATO!$H$2:$H$3000,MATCH($A582,EXTRATO!$A$2:$A$3000,0))="","",INDEX(EXTRATO!$H$2:$H$3000,MATCH($A582,EXTRATO!$A$2:$A$3000,0)))) -> FARMACE | J582: MAPEADO | K582: =IF(AND(A582="",D582="",E582="",F582=""),"",IF(D582="","SEM CATEGORIA",IF(E582="","SEM SUBCATEGORIA",IF(COUNTIFS(CADASTROS!$L$7:$L$93,D582,CADASTROS!$D$7:$D$93,E582)=0,"INCOMPATÍVEL","OK")))) -> OK
A583: BAN-00520 | B583: =IF(A583="","",IF(INDEX(EXTRATO!$C$2:$C$3000,MATCH($A583,EXTRATO!$A$2:$A$3000,0))="","",INDEX(EXTRATO!$C$2:$C$3000,MATCH($A583,EXTRATO!$A$2:$A$3000,0)))) -> 46164 | C583: =IF(B583="","",MONTH(B583)) -> 5 | D583: DESPESAS COM PRESTADORES DE SERVIÇOS EM SAÚDE - TERCEIROS | E583: CasaMater - Confecção Fístula | F583: 3600 | G583: CASAMATER (REF. MAR/2026) | H583: =IF(A583="","",IF(INDEX(EXTRATO!$F$2:$F$3000,MATCH($A583,EXTRATO!$A$2:$A$3000,0))="","",INDEX(EXTRATO!$F$2:$F$3000,MATCH($A583,EXTRATO!$A$2:$A$3000,0)))) -> SAÍDA | I583: =IF(A583="","",IF(INDEX(EXTRATO!$H$2:$H$3000,MATCH($A583,EXTRATO!$A$2:$A$3000,0))="","",INDEX(EXTRATO!$H$2:$H$3000,MATCH($A583,EXTRATO!$A$2:$A$3000,0)))) -> CASAMATER | J583: MAPEADO | K583: =IF(AND(A583="",D583="",E583="",F583=""),"",IF(D583="","SEM CATEGORIA",IF(E583="","SEM SUBCATEGORIA",IF(COUNTIFS(CADASTROS!$L$7:$L$93,D583,CADASTROS!$D$7:$D$93,E583)=0,"INCOMPATÍVEL","OK")))) -> OK
A584: BAN-00521 | B584: =IF(A584="","",IF(INDEX(EXTRATO!$C$2:$C$3000,MATCH($A584,EXTRATO!$A$2:$A$3000,0))="","",INDEX(EXTRATO!$C$2:$C$3000,MATCH($A584,EXTRATO!$A$2:$A$3000,0)))) -> 46164 | C584: =IF(B584="","",MONTH(B584)) -> 5 | D584: LOGÍSTICA E FROTA | E584: Transporte de pacientes e viagens para HTI | F584: 1246 | G584: CLAUDIANE CARDOSO SILVA (REF. VIAGEM HTI) | H584: =IF(A584="","",IF(INDEX(EXTRATO!$F$2:$F$3000,MATCH($A584,EXTRATO!$A$2:$A$3000,0))="","",INDEX(EXTRATO!$F$2:$F$3000,MATCH($A584,EXTRATO!$A$2:$A$3000,0)))) -> SAÍDA | I584: =IF(A584="","",IF(INDEX(EXTRATO!$H$2:$H$3000,MATCH($A584,EXTRATO!$A$2:$A$3000,0))="","",INDEX(EXTRATO!$H$2:$H$3000,MATCH($A584,EXTRATO!$A$2:$A$3000,0)))) -> CLAUDIANE CARDOSO DA SILVA (CARRO HTI) | J584: MAPEADO | K584: =IF(AND(A584="",D584="",E584="",F584=""),"",IF(D584="","SEM CATEGORIA",IF(E584="","SEM SUBCATEGORIA",IF(COUNTIFS(CADASTROS!$L$7:$L$93,D584,CADASTROS!$D$7:$D$93,E584)=0,"INCOMPATÍVEL","OK")))) -> OK
A585: BAN-00522 | B585: =IF(A585="","",IF(INDEX(EXTRATO!$C$2:$C$3000,MATCH($A585,EXTRATO!$A$2:$A$3000,0))="","",INDEX(EXTRATO!$C$2:$C$3000,MATCH($A585,EXTRATO!$A$2:$A$3000,0)))) -> 46164 | C585: =IF(B585="","",MONTH(B585)) -> 5 | D585: DESPESAS ADMINISTRATIVAS | E585: Panificadora | F585: 890 | G585: E M GONÇALVES PADARIA (REF. FORNEC. DE PÃES E BOLOS - ABR/26) - FAVORECIDO: EDILBERTO M. GONÇALVES | H585: =IF(A585="","",IF(INDEX(EXTRATO!$F$2:$F$3000,MATCH($A585,EXTRATO!$A$2:$A$3000,0))="","",INDEX(EXTRATO!$F$2:$F$3000,MATCH($A585,EXTRATO!$A$2:$A$3000,0)))) -> SAÍDA | I585: =IF(A585="","",IF(INDEX(EXTRATO!$H$2:$H$3000,MATCH($A585,EXTRATO!$A$2:$A$3000,0))="","",INDEX(EXTRATO!$H$2:$H$3000,MATCH($A585,EXTRATO!$A$2:$A$3000,0)))) -> E M GONÇALVES PADARIA | J585: MAPEADO | K585: =IF(AND(A585="",D585="",E585="",F585=""),"",IF(D585="","SEM CATEGORIA",IF(E585="","SEM SUBCATEGORIA",IF(COUNTIFS(CADASTROS!$L$7:$L$93,D585,CADASTROS!$D$7:$D$93,E585)=0,"INCOMPATÍVEL","OK")))) -> OK
... A603: BAN-00534 | B603: =IF(A603="","",IF(INDEX(EXTRATO!$C$2:$C$3000,MATCH($A603,EXTRATO!$A$2:$A$3000,0))="","",INDEX(EXTRATO!$C$2:$C$3000,MATCH($A603,EXTRATO!$A$2:$A$3000,0)))) -> 46167 | C603: =IF(B603="","",MONTH(B603)) -> 5 | D603: DESPESAS COM MATERIAIS PARA HEMODIÁLISE E DEMAIS CUSTOS | E603: Agulhas, Seringas, Máscaras, Luvas, Equipo e Med. Div. | F603: 1496 | G603: COOP. UNIMED (REF. COMPRESA DE GAZE) 3/3 | H603: =IF(A603="","",IF(INDEX(EXTRATO!$F$2:$F$3000,MATCH($A603,EXTRATO!$A$2:$A$3000,0))="","",INDEX(EXTRATO!$F$2:$F$3000,MATCH($A603,EXTRATO!$A$2:$A$3000,0)))) -> SAÍDA | I603: =IF(A603="","",IF(INDEX(EXTRATO!$H$2:$H$3000,MATCH($A603,EXTRATO!$A$2:$A$3000,0))="","",INDEX(EXTRATO!$H$2:$H$3000,MATCH($A603,EXTRATO!$A$2:$A$3000,0)))) -> COOP. UNIMED | J603: MAPEADO | K603: =IF(AND(A603="",D603="",E603="",F603=""),"",IF(D603="","SEM CATEGORIA",IF(E603="","SEM SUBCATEGORIA",IF(COUNTIFS(CADASTROS!$L$7:$L$93,D603,CADASTROS!$D$7:$D$93,E603)=0,"INCOMPATÍVEL","OK")))) -> OK
A604: BAN-00535 | B604: =IF(A604="","",IF(INDEX(EXTRATO!$C$2:$C$3000,MATCH($A604,EXTRATO!$A$2:$A$3000,0))="","",INDEX(EXTRATO!$C$2:$C$3000,MATCH($A604,EXTRATO!$A$2:$A$3000,0)))) -> 46167 | C604: =IF(B604="","",MONTH(B604)) -> 5 | F604: 997.92 | H604: =IF(A604="","",IF(INDEX(EXTRATO!$F$2:$F$3000,MATCH($A604,EXTRATO!$A$2:$A$3000,0))="","",INDEX(EXTRATO!$F$2:$F$3000,MATCH($A604,EXTRATO!$A$2:$A$3000,0)))) -> SAÍDA | I604: =IF(A604="","",IF(INDEX(EXTRATO!$H$2:$H$3000,MATCH($A604,EXTRATO!$A$2:$A$3000,0))="","",INDEX(EXTRATO!$H$2:$H$3000,MATCH($A604,EXTRATO!$A$2:$A$3000,0)))) -> JG CONSTRUCOES | J604: PENDENTE | K604: =IF(AND(A604="",D604="",E604="",F604=""),"",IF(D604="","SEM CATEGORIA",IF(E604="","SEM SUBCATEGORIA",IF(COUNTIFS(CADASTROS!$L$7:$L$93,D604,CADASTROS!$D$7:$D$93,E604)=0,"INCOMPATÍVEL","OK")))) -> SEM CATEGORIA
A605: BAN-00536 | B605: =IF(A605="","",IF(INDEX(EXTRATO!$C$2:$C$3000,MATCH($A605,EXTRATO!$A$2:$A$3000,0))="","",INDEX(EXTRATO!$C$2:$C$3000,MATCH($A605,EXTRATO!$A$2:$A$3000,0)))) -> 46167 | C605: =IF(B605="","",MONTH(B605)) -> 5 | D605: DESPESAS ADMINISTRATIVAS | E605: Taxas e Tarifas | F605: 400 | G605: ABCDT - ASSOC BRAS C D TRANSPLANTE - REF. MENSALIDADE | H605: =IF(A605="","",IF(INDEX(EXTRATO!$F$2:$F$3000,MATCH($A605,EXTRATO!$A$2:$A$3000,0))="","",INDEX(EXTRATO!$F$2:$F$3000,MATCH($A605,EXTRATO!$A$2:$A$3000,0)))) -> SAÍDA | I605: =IF(A605="","",IF(INDEX(EXTRATO!$H$2:$H$3000,MATCH($A605,EXTRATO!$A$2:$A$3000,0))="","",INDEX(EXTRATO!$H$2:$H$3000,MATCH($A605,EXTRATO!$A$2:$A$3000,0)))) -> ABCDT | J605: MAPEADO | K605: =IF(AND(A605="",D605="",E605="",F605=""),"",IF(D605="","SEM CATEGORIA",IF(E605="","SEM SUBCATEGORIA",IF(COUNTIFS(CADASTROS!$L$7:$L$93,D605,CADASTROS!$D$7:$D$93,E605)=0,"INCOMPATÍVEL","OK")))) -> OK
A606: BAN-00537 | B606: =IF(A606="","",IF(INDEX(EXTRATO!$C$2:$C$3000,MATCH($A606,EXTRATO!$A$2:$A$3000,0))="","",INDEX(EXTRATO!$C$2:$C$3000,MATCH($A606,EXTRATO!$A$2:$A$3000,0)))) -> 46167 | C606: =IF(B606="","",MONTH(B606)) -> 5 | D606: DESPESAS COM SALÁRIOS E BENEFÍCIOS | E606: EPIs e Fardamentos | F606: 170 | G606: FERCASTRO BR (REF. BOTA DE EPI PARA FUNCIONÁRIOS) | H606: =IF(A606="","",IF(INDEX(EXTRATO!$F$2:$F$3000,MATCH($A606,EXTRATO!$A$2:$A$3000,0))="","",INDEX(EXTRATO!$F$2:$F$3000,MATCH($A606,EXTRATO!$A$2:$A$3000,0)))) -> SAÍDA | I606: =IF(A606="","",IF(INDEX(EXTRATO!$H$2:$H$3000,MATCH($A606,EXTRATO!$A$2:$A$3000,0))="","",INDEX(EXTRATO!$H$2:$H$3000,MATCH($A606,EXTRATO!$A$2:$A$3000,0)))) -> FERCASTRO | J606: MAPEADO | K606: =IF(AND(A606="",D606="",E606="",F606=""),"",IF(D606="","SEM CATEGORIA",IF(E606="","SEM SUBCATEGORIA",IF(COUNTIFS(CADASTROS!$L$7:$L$93,D606,CADASTROS!$D$7:$D$93,E606)=0,"INCOMPATÍVEL","OK")))) -> OK
A607: BAN-00538 | B607: =IF(A607="","",IF(INDEX(EXTRATO!$C$2:$C$3000,MATCH($A607,EXTRATO!$A$2:$A$3000,0))="","",INDEX(EXTRATO!$C$2:$C$3000,MATCH($A607,EXTRATO!$A$2:$A$3000,0)))) -> 46167 | C607: =IF(B607="","",MONTH(B607)) -> 5 | D607: ENTRADAS | E607: Resgate do Financiamento (Banco do Nordeste) | F607: 100000 | G607: BIORENAL LTDA (REF. DEPÓSITO DO FINANCIAMENTO) | H607: =IF(A607="","",IF(INDEX(EXTRATO!$F$2:$F$3000,MATCH($A607,EXTRATO!$A$2:$A$3000,0))="","",INDEX(EXTRATO!$F$2:$F$3000,MATCH($A607,EXTRATO!$A$2:$A$3000,0)))) -> ENTRADA | I607: =IF(A607="","",IF(INDEX(EXTRATO!$H$2:$H$3000,MATCH($A607,EXTRATO!$A$2:$A$3000,0))="","",INDEX(EXTRATO!$H$2:$H$3000,MATCH($A607,EXTRATO!$A$2:$A$3000,0)))) -> BIORENAL LTDA | J607: AUTOMÁTICO | K607: =IF(AND(A607="",D607="",E607="",F607=""),"",IF(D607="","SEM CATEGORIA",IF(E607="","SEM SUBCATEGORIA",IF(COUNTIFS(CADASTROS!$L$7:$L$93,D607,CADASTROS!$D$7:$D$93,E607)=0,"INCOMPATÍVEL","OK")))) -> OK
A608: BAN-00539 | B608: =IF(A608="","",IF(INDEX(EXTRATO!$C$2:$C$3000,MATCH($A608,EXTRATO!$A$2:$A$3000,0))="","",INDEX(EXTRATO!$C$2:$C$3000,MATCH($A608,EXTRATO!$A$2:$A$3000,0)))) -> 46168 | C608: =IF(B608="","",MONTH(B608)) -> 5 | D608: DESPESAS COM MATERIAIS PARA HEMODIÁLISE E DEMAIS CUSTOS | E608: Capilar, Filtros, Agulhas | F608: 3600 | G608: NIPRO (REF. CAPILAR 21H) 2/2 | H608: =IF(A608="","",IF(INDEX(EXTRATO!$F$2:$F$3000,MATCH($A608,EXTRATO!$A$2:$A$3000,0))="","",INDEX(EXTRATO!$F$2:$F$3000,MATCH($A608,EXTRATO!$A$2:$A$3000,0)))) -> SAÍDA | I608: =IF(A608="","",IF(INDEX(EXTRATO!$H$2:$H$3000,MATCH($A608,EXTRATO!$A$2:$A$3000,0))="","",INDEX(EXTRATO!$H$2:$H$3000,MATCH($A608,EXTRATO!$A$2:$A$3000,0)))) -> NIPRO | J608: MAPEADO | K608: =IF(AND(A608="",D608="",E608="",F608=""),"",IF(D608="","SEM CATEGORIA",IF(E608="","SEM SUBCATEGORIA",IF(COUNTIFS(CADASTROS!$L$7:$L$93,D608,CADASTROS!$D$7:$D$93,E608)=0,"INCOMPATÍVEL","OK")))) -> OK
A609: BAN-00540 | B609: =IF(A609="","",IF(INDEX(EXTRATO!$C$2:$C$3000,MATCH($A609,EXTRATO!$A$2:$A$3000,0))="","",INDEX(EXTRATO!$C$2:$C$3000,MATCH($A609,EXTRATO!$A$2:$A$3000,0)))) -> 46168 | C609: =IF(B609="","",MONTH(B609)) -> 5 | D609: MANUTENÇÃO E INFRAESTRUTURA | E609: Manutenção - Máquinas HD, Gerador, Osmose | F609: 1320 | G609: DMW ELETROMEDICINA LTDA (REF. POTENCIOMETRO, SENSOR DO FLUXOMETRO E CHAVE DO SENSOR) 1/2 | H609: =IF(A609="","",IF(INDEX(EXTRATO!$F$2:$F$3000,MATCH($A609,EXTRATO!$A$2:$A$3000,0))="","",INDEX(EXTRATO!$F$2:$F$3000,MATCH($A609,EXTRATO!$A$2:$A$3000,0)))) -> SAÍDA | I609: =IF(A609="","",IF(INDEX(EXTRATO!$H$2:$H$3000,MATCH($A609,EXTRATO!$A$2:$A$3000,0))="","",INDEX(EXTRATO!$H$2:$H$3000,MATCH($A609,EXTRATO!$A$2:$A$3000,0)))) -> DMW ELETROMEDICINA LTDA | J609: MAPEADO | K609: =IF(AND(A609="",D609="",E609="",F609=""),"",IF(D609="","SEM CATEGORIA",IF(E609="","SEM SUBCATEGORIA",IF(COUNTIFS(CADASTROS!$L$7:$L$93,D609,CADASTROS!$D$7:$D$93,E609)=0,"INCOMPATÍVEL","OK")))) -> OK
A610: BAN-00541 | B610: =IF(A610="","",IF(INDEX(EXTRATO!$C$2:$C$3000,MATCH($A610,EXTRATO!$A$2:$A$3000,0))="","",INDEX(EXTRATO!$C$2:$C$3000,MATCH($A610,EXTRATO!$A$2:$A$3000,0)))) -> 46170 | C610: =IF(B610="","",MONTH(B610)) -> 5 | D610: DESPESAS COM MATERIAIS PARA HEMODIÁLISE E DEMAIS CUSTOS | E610: Hipoclorito | F610: 605.55 | G610: RICEK INDUSTRIA E COMÉRCIO (REF. HIPOCLORITO) 2/2 | H610: =IF(A610="","",IF(INDEX(EXTRATO!$F$2:$F$3000,MATCH($A610,EXTRATO!$A$2:$A$3000,0))="","",INDEX(EXTRATO!$F$2:$F$3000,MATCH($A610,EXTRATO!$A$2:$A$3000,0)))) -> SAÍDA | I610: =IF(A610="","",IF(INDEX(EXTRATO!$H$2:$H$3000,MATCH($A610,EXTRATO!$A$2:$A$3000,0))="","",INDEX(EXTRATO!$H$2:$H$3000,MATCH($A610,EXTRATO!$A$2:$A$3000,0)))) -> RICEK INDUSTRIA E COMÉRCIO | J610: MAPEADO | K610: =IF(AND(A610="",D610="",E610="",F610=""),"",IF(D610="","SEM CATEGORIA",IF(E610="","SEM SUBCATEGORIA",IF(COUNTIFS(CADASTROS!$L$7:$L$93,D610,CADASTROS!$D$7:$D$93,E610)=0,"INCOMPATÍVEL","OK")))) -> OK
A611: BAN-00541 | B611: =IF(A611="","",IF(INDEX(EXTRATO!$C$2:$C$3000,MATCH($A611,EXTRATO!$A$2:$A$3000,0))="","",INDEX(EXTRATO!$C$2:$C$3000,MATCH($A611,EXTRATO!$A$2:$A$3000,0)))) -> 46170 | C611: =IF(B611="","",MONTH(B611)) -> 5 | D611: DESPESAS ADMINISTRATIVAS | E611: Material de Limpeza | F611: 392.37 | G611: RICEK INDUSTRIA E COMÉRCIO (REF. SACO DE LIXO) 2/2 | H611: =IF(A611="","",IF(INDEX(EXTRATO!$F$2:$F$3000,MATCH($A611,EXTRATO!$A$2:$A$3000,0))="","",INDEX(EXTRATO!$F$2:$F$3000,MATCH($A611,EXTRATO!$A$2:$A$3000,0)))) -> SAÍDA | I611: =IF(A611="","",IF(INDEX(EXTRATO!$H$2:$H$3000,MATCH($A611,EXTRATO!$A$2:$A$3000,0))="","",INDEX(EXTRATO!$H$2:$H$3000,MATCH($A611,EXTRATO!$A$2:$A$3000,0)))) -> RICEK INDUSTRIA E COMÉRCIO | J611: MAPEADO | K611: =IF(AND(A611="",D611="",E611="",F611=""),"",IF(D611="","SEM CATEGORIA",IF(E611="","SEM SUBCATEGORIA",IF(COUNTIFS(CADASTROS!$L$7:$L$93,D611,CADASTROS!$D$7:$D$93,E611)=0,"INCOMPATÍVEL","OK")))) -> OK
A612: BAN-00542 | B612: =IF(A612="","",IF(INDEX(EXTRATO!$C$2:$C$3000,MATCH($A612,EXTRATO!$A$2:$A$3000,0))="","",INDEX(EXTRATO!$C$2:$C$3000,MATCH($A612,EXTRATO!$A$2:$A$3000,0)))) -> 46170 | C612: =IF(B612="","",MONTH(B612)) -> 5 | D612: DESPESAS ADMINISTRATIVAS | E612: Material de Limpeza | F612: 647.3 | G612: ALECRIM INDUSTRIA E COMÉRCIO (REF. PAPEL TOALHA E PAPEL HIGIÊNICO) 2/2 | H612: =IF(A612="","",IF(INDEX(EXTRATO!$F$2:$F$3000,MATCH($A612,EXTRATO!$A$2:$A$3000,0))="","",INDEX(EXTRATO!$F$2:$F$3000,MATCH($A612,EXTRATO!$A$2:$A$3000,0)))) -> SAÍDA | I612: =IF(A612="","",IF(INDEX(EXTRATO!$H$2:$H$3000,MATCH($A612,EXTRATO!$A$2:$A$3000,0))="","",INDEX(EXTRATO!$H$2:$H$3000,MATCH($A612,EXTRATO!$A$2:$A$3000,0)))) -> ALECRIM INDUSTRIA E COMÉRCIO | J612: MAPEADO | K612: =IF(AND(A612="",D612="",E612="",F612=""),"",IF(D612="","SEM CATEGORIA",IF(E612="","SEM SUBCATEGORIA",IF(COUNTIFS(CADASTROS!$L$7:$L$93,D612,CADASTROS!$D$7:$D$93,E612)=0,"INCOMPATÍVEL","OK")))) -> OK
A613: BAN-00543 | B613: =IF(A613="","",IF(INDEX(EXTRATO!$C$2:$C$3000,MATCH($A613,EXTRATO!$A$2:$A$3000,0))="","",INDEX(EXTRATO!$C$2:$C$3000,MATCH($A613,EXTRATO!$A$2:$A$3000,0)))) -> 46171 | C613: =IF(B613="","",MONTH(B613)) -> 5 | D613: MANUTENÇÃO E INFRAESTRUTURA | E613: Manutenção - Máquinas HD, Gerador, Osmose | F613: 4500 | G613: HR MANUTENCAO HOSPITALAR E TRAT. DE AGUA (REF. PREST. DE SERV. HUGO RAMON) - FEV/26 | H613: =IF(A613="","",IF(INDEX(EXTRATO!$F$2:$F$3000,MATCH($A613,EXTRATO!$A$2:$A$3000,0))="","",INDEX(EXTRATO!$F$2:$F$3000,MATCH($A613,EXTRATO!$A$2:$A$3000,0)))) -> SAÍDA | I613: =IF(A613="","",IF(INDEX(EXTRATO!$H$2:$H$3000,MATCH($A613,EXTRATO!$A$2:$A$3000,0))="","",INDEX(EXTRATO!$H$2:$H$3000,MATCH($A613,EXTRATO!$A$2:$A$3000,0)))) -> HR MANUTENCAO HOSPITALAR | J613: MAPEADO | K613: =IF(AND(A613="",D613="",E613="",F613=""),"",IF(D613="","SEM CATEGORIA",IF(E613="","SEM SUBCATEGORIA",IF(COUNTIFS(CADASTROS!$L$7:$L$93,D613,CADASTROS!$D$7:$D$93,E613)=0,"INCOMPATÍVEL","OK")))) -> OK
A614: BAN-00544 | B614: =IF(A614="","",IF(INDEX(EXTRATO!$C$2:$C$3000,MATCH($A614,EXTRATO!$A$2:$A$3000,0))="","",INDEX(EXTRATO!$C$2:$C$3000,MATCH($A614,EXTRATO!$A$2:$A$3000,0)))) -> 46171 | C614: =IF(B614="","",MONTH(B614)) -> 5 | D614: DESPESAS COM PRESTADORES DE SERVIÇOS EM SAÚDE - TERCEIROS | E614: Pagamento Cirurgião Vascular - Dr. Renato | F614: 1470 | G614: DR. RENATO (CIRURGIÃO VASCULAR) - S M D MATOS ASSOC. (REF.MAR/26) | H614: =IF(A614="","",IF(INDEX(EXTRATO!$F$2:$F$3000,MATCH($A614,EXTRATO!$A$2:$A$3000,0))="","",INDEX(EXTRATO!$F$2:$F$3000,MATCH($A614,EXTRATO!$A$2:$A$3000,0)))) -> SAÍDA | I614: =IF(A614="","",IF(INDEX(EXTRATO!$H$2:$H$3000,MATCH($A614,EXTRATO!$A$2:$A$3000,0))="","",INDEX(EXTRATO!$H$2:$H$3000,MATCH($A614,EXTRATO!$A$2:$A$3000,0)))) -> DR. RENATO | J614: MAPEADO | K614: =IF(AND(A614="",D614="",E614="",F614=""),"",IF(D614="","SEM CATEGORIA",IF(E614="","SEM SUBCATEGORIA",IF(COUNTIFS(CADASTROS!$L$7:$L$93,D614,CADASTROS!$D$7:$D$93,E614)=0,"INCOMPATÍVEL","OK")))) -> OK
A615: BAN-00545 | B615: =IF(A615="","",IF(INDEX(EXTRATO!$C$2:$C$3000,MATCH($A615,EXTRATO!$A$2:$A$3000,0))="","",INDEX(EXTRATO!$C$2:$C$3000,MATCH($A615,EXTRATO!$A$2:$A$3000,0)))) -> 46171 | C615: =IF(B615="","",MONTH(B615)) -> 5 | D615: DESPESAS ADMINISTRATIVAS | E615: Materiais de Construção, Elétrico e de Escritório | F615: 300 | G615: MASTER GRAFICA DIGITAL (REF. PRODUÇÃO DE 10 BLOCOS DE FICHAS DE SALA E 10 BLOCOS DE SOLICITAÇÃO DE MATERIAL) | H615: =IF(A615="","",IF(INDEX(EXTRATO!$F$2:$F$3000,MATCH($A615,EXTRATO!$A$2:$A$3000,0))="","",INDEX(EXTRATO!$F$2:$F$3000,MATCH($A615,EXTRATO!$A$2:$A$3000,0)))) -> SAÍDA | I615: =IF(A615="","",IF(INDEX(EXTRATO!$H$2:$H$3000,MATCH($A615,EXTRATO!$A$2:$A$3000,0))="","",INDEX(EXTRATO!$H$2:$H$3000,MATCH($A615,EXTRATO!$A$2:$A$3000,0)))) -> MASTER GRAFICA DIGITAL | J615: MAPEADO | K615: =IF(AND(A615="",D615="",E615="",F615=""),"",IF(D615="","SEM CATEGORIA",IF(E615="","SEM SUBCATEGORIA",IF(COUNTIFS(CADASTROS!$L$7:$L$93,D615,CADASTROS!$D$7:$D$93,E615)=0,"INCOMPATÍVEL","OK")))) -> OK
A616: BAN-00546 | B616: =IF(A616="","",IF(INDEX(EXTRATO!$C$2:$C$3000,MATCH($A616,EXTRATO!$A$2:$A$3000,0))="","",INDEX(EXTRATO!$C$2:$C$3000,MATCH($A616,EXTRATO!$A$2:$A$3000,0)))) -> 46174 | C616: =IF(B616="","",MONTH(B616)) -> 6 | D616: AQUISIÇÃO DE BENS E EQUIPAMENTOS | E616: Aquisição de Máquinas de Hemodiálise | F616: 48992.16 | G616: NIPRO (REF. COMPRA DE 21 MÁQUINAS DE HD) - PARCELA 08/24 | H616: =IF(A616="","",IF(INDEX(EXTRATO!$F$2:$F$3000,MATCH($A616,EXTRATO!$A$2:$A$3000,0))="","",INDEX(EXTRATO!$F$2:$F$3000,MATCH($A616,EXTRATO!$A$2:$A$3000,0)))) -> SAÍDA | I616: =IF(A616="","",IF(INDEX(EXTRATO!$H$2:$H$3000,MATCH($A616,EXTRATO!$A$2:$A$3000,0))="","",INDEX(EXTRATO!$H$2:$H$3000,MATCH($A616,EXTRATO!$A$2:$A$3000,0)))) -> NIPRO | J616: MAPEADO | K616: =IF(AND(A616="",D616="",E616="",F616=""),"",IF(D616="","SEM CATEGORIA",IF(E616="","SEM SUBCATEGORIA",IF(COUNTIFS(CADASTROS!$L$7:$L$93,D616,CADASTROS!$D$7:$D$93,E616)=0,"INCOMPATÍVEL","OK")))) -> OK
... A782: BAN-00681 | B782: =IF(A782="","",IF(INDEX(EXTRATO!$C$2:$C$3000,MATCH($A782,EXTRATO!$A$2:$A$3000,0))="","",INDEX(EXTRATO!$C$2:$C$3000,MATCH($A782,EXTRATO!$A$2:$A$3000,0)))) -> 46211 | C782: =IF(B782="","",MONTH(B782)) -> 7 | D782: DESPESAS COM MATERIAIS PARA HEMODIÁLISE E DEMAIS CUSTOS | E782: Capilar, Filtros, Agulhas | F782: 3266.25 | G782: NIPRO MEDICAL (REF. AGULHA 16G) - 1/2 | H782: =IF(A782="","",IF(INDEX(EXTRATO!$F$2:$F$3000,MATCH($A782,EXTRATO!$A$2:$A$3000,0))="","",INDEX(EXTRATO!$F$2:$F$3000,MATCH($A782,EXTRATO!$A$2:$A$3000,0)))) -> SAÍDA | I782: =IF(A782="","",IF(INDEX(EXTRATO!$H$2:$H$3000,MATCH($A782,EXTRATO!$A$2:$A$3000,0))="","",INDEX(EXTRATO!$H$2:$H$3000,MATCH($A782,EXTRATO!$A$2:$A$3000,0)))) -> NIPRO | J782: SUGERIDO | K782: =IF(AND(A782="",D782="",E782="",F782=""),"",IF(D782="","SEM CATEGORIA",IF(E782="","SEM SUBCATEGORIA",IF(COUNTIFS(CADASTROS!$L$7:$L$93,D782,CADASTROS!$D$7:$D$93,E782)=0,"INCOMPATÍVEL","OK")))) -> OK
A783: BAN-00682 | B783: =IF(A783="","",IF(INDEX(EXTRATO!$C$2:$C$3000,MATCH($A783,EXTRATO!$A$2:$A$3000,0))="","",INDEX(EXTRATO!$C$2:$C$3000,MATCH($A783,EXTRATO!$A$2:$A$3000,0)))) -> 46213 | C783: =IF(B783="","",MONTH(B783)) -> 7 | D783: DESPESAS COM MATERIAIS PARA HEMODIÁLISE E DEMAIS CUSTOS | E783: Capilar, Filtros, Agulhas | F783: =4800/2 -> 2400 | G783: DIÁLISE COMÉRCIO (REF. CAPILAR 20 H) 2/2 | H783: =IF(A783="","",IF(INDEX(EXTRATO!$F$2:$F$3000,MATCH($A783,EXTRATO!$A$2:$A$3000,0))="","",INDEX(EXTRATO!$F$2:$F$3000,MATCH($A783,EXTRATO!$A$2:$A$3000,0)))) -> SAÍDA | I783: =IF(A783="","",IF(INDEX(EXTRATO!$H$2:$H$3000,MATCH($A783,EXTRATO!$A$2:$A$3000,0))="","",INDEX(EXTRATO!$H$2:$H$3000,MATCH($A783,EXTRATO!$A$2:$A$3000,0)))) -> DIALISE COMERCIO | J783: PENDENTE | K783: =IF(AND(A783="",D783="",E783="",F783=""),"",IF(D783="","SEM CATEGORIA",IF(E783="","SEM SUBCATEGORIA",IF(COUNTIFS(CADASTROS!$L$7:$L$93,D783,CADASTROS!$D$7:$D$93,E783)=0,"INCOMPATÍVEL","OK")))) -> OK
A784: BAN-00682 | B784: =IF(A784="","",IF(INDEX(EXTRATO!$C$2:$C$3000,MATCH($A784,EXTRATO!$A$2:$A$3000,0))="","",INDEX(EXTRATO!$C$2:$C$3000,MATCH($A784,EXTRATO!$A$2:$A$3000,0)))) -> 46213 | C784: =IF(B784="","",MONTH(B784)) -> 7 | D784: DESPESAS COM MATERIAIS PARA HEMODIÁLISE E DEMAIS CUSTOS | E784: Agulhas, Seringas, Máscaras, Luvas, Equipo e Med. Div. | F784: 540 | G784: DIÁLISE COMÉRCIO (REF. FITA INDICADORA DE ÁCIDO PERACÉTICO) 2/2 | H784: =IF(A784="","",IF(INDEX(EXTRATO!$F$2:$F$3000,MATCH($A784,EXTRATO!$A$2:$A$3000,0))="","",INDEX(EXTRATO!$F$2:$F$3000,MATCH($A784,EXTRATO!$A$2:$A$3000,0)))) -> SAÍDA | I784: =IF(A784="","",IF(INDEX(EXTRATO!$H$2:$H$3000,MATCH($A784,EXTRATO!$A$2:$A$3000,0))="","",INDEX(EXTRATO!$H$2:$H$3000,MATCH($A784,EXTRATO!$A$2:$A$3000,0)))) -> DIALISE COMERCIO | J784: PENDENTE | K784: =IF(AND(A784="",D784="",E784="",F784=""),"",IF(D784="","SEM CATEGORIA",IF(E784="","SEM SUBCATEGORIA",IF(COUNTIFS(CADASTROS!$L$7:$L$93,D784,CADASTROS!$D$7:$D$93,E784)=0,"INCOMPATÍVEL","OK")))) -> OK
A785: BAN-00683 | B785: =IF(A785="","",IF(INDEX(EXTRATO!$C$2:$C$3000,MATCH($A785,EXTRATO!$A$2:$A$3000,0))="","",INDEX(EXTRATO!$C$2:$C$3000,MATCH($A785,EXTRATO!$A$2:$A$3000,0)))) -> 46213 | C785: =IF(B785="","",MONTH(B785)) -> 7 | D785: DESPESAS ADMINISTRATIVAS | E785: Suporte Informatica - Hardware, Internet, Sistemas e Câmeras | F785: 149.9 | G785: MARANET TELECOM (REF. INTERNET) | H785: =IF(A785="","",IF(INDEX(EXTRATO!$F$2:$F$3000,MATCH($A785,EXTRATO!$A$2:$A$3000,0))="","",INDEX(EXTRATO!$F$2:$F$3000,MATCH($A785,EXTRATO!$A$2:$A$3000,0)))) -> SAÍDA | I785: =IF(A785="","",IF(INDEX(EXTRATO!$H$2:$H$3000,MATCH($A785,EXTRATO!$A$2:$A$3000,0))="","",INDEX(EXTRATO!$H$2:$H$3000,MATCH($A785,EXTRATO!$A$2:$A$3000,0)))) -> MARANET TELECOM | J785: SUGERIDO | K785: =IF(AND(A785="",D785="",E785="",F785=""),"",IF(D785="","SEM CATEGORIA",IF(E785="","SEM SUBCATEGORIA",IF(COUNTIFS(CADASTROS!$L$7:$L$93,D785,CADASTROS!$D$7:$D$93,E785)=0,"INCOMPATÍVEL","OK")))) -> OK
A786: BAN-00684 | B786: =IF(A786="","",IF(INDEX(EXTRATO!$C$2:$C$3000,MATCH($A786,EXTRATO!$A$2:$A$3000,0))="","",INDEX(EXTRATO!$C$2:$C$3000,MATCH($A786,EXTRATO!$A$2:$A$3000,0)))) -> 46213 | C786: =IF(B786="","",MONTH(B786)) -> 7 | D786: DESPESAS ADMINISTRATIVAS | E786: Coleta de Lixo | F786: 1600 | G786: BIOGREEN INCINERAÇÃO DE RESIDUOS (REF. COLETO LIXO INFECTANTE) - REF. 06/26 | H786: =IF(A786="","",IF(INDEX(EXTRATO!$F$2:$F$3000,MATCH($A786,EXTRATO!$A$2:$A$3000,0))="","",INDEX(EXTRATO!$F$2:$F$3000,MATCH($A786,EXTRATO!$A$2:$A$3000,0)))) -> SAÍDA | I786: =IF(A786="","",IF(INDEX(EXTRATO!$H$2:$H$3000,MATCH($A786,EXTRATO!$A$2:$A$3000,0))="","",INDEX(EXTRATO!$H$2:$H$3000,MATCH($A786,EXTRATO!$A$2:$A$3000,0)))) -> BIOGREEN | J786: SUGERIDO | K786: =IF(AND(A786="",D786="",E786="",F786=""),"",IF(D786="","SEM CATEGORIA",IF(E786="","SEM SUBCATEGORIA",IF(COUNTIFS(CADASTROS!$L$7:$L$93,D786,CADASTROS!$D$7:$D$93,E786)=0,"INCOMPATÍVEL","OK")))) -> OK
A787: BAN-00685 | B787: =IF(A787="","",IF(INDEX(EXTRATO!$C$2:$C$3000,MATCH($A787,EXTRATO!$A$2:$A$3000,0))="","",INDEX(EXTRATO!$C$2:$C$3000,MATCH($A787,EXTRATO!$A$2:$A$3000,0)))) -> 46213 | C787: =IF(B787="","",MONTH(B787)) -> 7 | D787: DESPESAS COM IMPOSTOS | E787: ISS | F787: 30275.67 | G787: ISS (MUNICIPIO DE SANTA INÊS) - NF 202600000000005 (REF. COMP. 04/2026 - EMITIDA EM 08/06/2026) | H787: =IF(A787="","",IF(INDEX(EXTRATO!$F$2:$F$3000,MATCH($A787,EXTRATO!$A$2:$A$3000,0))="","",INDEX(EXTRATO!$F$2:$F$3000,MATCH($A787,EXTRATO!$A$2:$A$3000,0)))) -> SAÍDA | I787: =IF(A787="","",IF(INDEX(EXTRATO!$H$2:$H$3000,MATCH($A787,EXTRATO!$A$2:$A$3000,0))="","",INDEX(EXTRATO!$H$2:$H$3000,MATCH($A787,EXTRATO!$A$2:$A$3000,0)))) -> ISS | J787: SUGERIDO | K787: =IF(AND(A787="",D787="",E787="",F787=""),"",IF(D787="","SEM CATEGORIA",IF(E787="","SEM SUBCATEGORIA",IF(COUNTIFS(CADASTROS!$L$7:$L$93,D787,CADASTROS!$D$7:$D$93,E787)=0,"INCOMPATÍVEL","OK")))) -> OK
A788: BAN-00686 | B788: =IF(A788="","",IF(INDEX(EXTRATO!$C$2:$C$3000,MATCH($A788,EXTRATO!$A$2:$A$3000,0))="","",INDEX(EXTRATO!$C$2:$C$3000,MATCH($A788,EXTRATO!$A$2:$A$3000,0)))) -> 46213 | C788: =IF(B788="","",MONTH(B788)) -> 7 | D788: LOGÍSTICA E FROTA | E788: Combustível (Gasolina) | F788: 400 | G788: LEMOS BRANCO & CIA - POSTO PREMIUM (COMBUSTÍVEL CARRO) | H788: =IF(A788="","",IF(INDEX(EXTRATO!$F$2:$F$3000,MATCH($A788,EXTRATO!$A$2:$A$3000,0))="","",INDEX(EXTRATO!$F$2:$F$3000,MATCH($A788,EXTRATO!$A$2:$A$3000,0)))) -> SAÍDA | I788: =IF(A788="","",IF(INDEX(EXTRATO!$H$2:$H$3000,MATCH($A788,EXTRATO!$A$2:$A$3000,0))="","",INDEX(EXTRATO!$H$2:$H$3000,MATCH($A788,EXTRATO!$A$2:$A$3000,0)))) -> LEMOS BRANCO & CIA | J788: SUGERIDO | K788: =IF(AND(A788="",D788="",E788="",F788=""),"",IF(D788="","SEM CATEGORIA",IF(E788="","SEM SUBCATEGORIA",IF(COUNTIFS(CADASTROS!$L$7:$L$93,D788,CADASTROS!$D$7:$D$93,E788)=0,"INCOMPATÍVEL","OK")))) -> OK
A789: BAN-00687 | B789: =IF(A789="","",IF(INDEX(EXTRATO!$C$2:$C$3000,MATCH($A789,EXTRATO!$A$2:$A$3000,0))="","",INDEX(EXTRATO!$C$2:$C$3000,MATCH($A789,EXTRATO!$A$2:$A$3000,0)))) -> 46213 | C789: =IF(B789="","",MONTH(B789)) -> 7 | D789: DESPESAS ADMINISTRATIVAS | E789: Taxas e Tarifas | F789: 275 | G789: TARIFA BANCÁRIA (PACOTE DE SERVIÇOS) | H789: =IF(A789="","",IF(INDEX(EXTRATO!$F$2:$F$3000,MATCH($A789,EXTRATO!$A$2:$A$3000,0))="","",INDEX(EXTRATO!$F$2:$F$3000,MATCH($A789,EXTRATO!$A$2:$A$3000,0)))) -> SAÍDA | I789: =IF(A789="","",IF(INDEX(EXTRATO!$H$2:$H$3000,MATCH($A789,EXTRATO!$A$2:$A$3000,0))="","",INDEX(EXTRATO!$H$2:$H$3000,MATCH($A789,EXTRATO!$A$2:$A$3000,0)))) -> TARIFA PACOTE DE SERVIÇOS | J789: SUGERIDO | K789: =IF(AND(A789="",D789="",E789="",F789=""),"",IF(D789="","SEM CATEGORIA",IF(E789="","SEM SUBCATEGORIA",IF(COUNTIFS(CADASTROS!$L$7:$L$93,D789,CADASTROS!$D$7:$D$93,E789)=0,"INCOMPATÍVEL","OK")))) -> OK
A790: BAN-00688 | B790: =IF(A790="","",IF(INDEX(EXTRATO!$C$2:$C$3000,MATCH($A790,EXTRATO!$A$2:$A$3000,0))="","",INDEX(EXTRATO!$C$2:$C$3000,MATCH($A790,EXTRATO!$A$2:$A$3000,0)))) -> 46216 | C790: =IF(B790="","",MONTH(B790)) -> 7 | D790: ENTRADAS | E790: Resgate do Financiamento (Banco do Nordeste) | F790: 50000 | G790: BIORENAL LTDA (REF. DEPÓSITO DO FINANCIAMENTO) | H790: =IF(A790="","",IF(INDEX(EXTRATO!$F$2:$F$3000,MATCH($A790,EXTRATO!$A$2:$A$3000,0))="","",INDEX(EXTRATO!$F$2:$F$3000,MATCH($A790,EXTRATO!$A$2:$A$3000,0)))) -> ENTRADA | I790: =IF(A790="","",IF(INDEX(EXTRATO!$H$2:$H$3000,MATCH($A790,EXTRATO!$A$2:$A$3000,0))="","",INDEX(EXTRATO!$H$2:$H$3000,MATCH($A790,EXTRATO!$A$2:$A$3000,0)))) -> BIORENAL LTDA | J790: AUTOMÁTICO | K790: =IF(AND(A790="",D790="",E790="",F790=""),"",IF(D790="","SEM CATEGORIA",IF(E790="","SEM SUBCATEGORIA",IF(COUNTIFS(CADASTROS!$L$7:$L$93,D790,CADASTROS!$D$7:$D$93,E790)=0,"INCOMPATÍVEL","OK")))) -> OK
A791: BAN-00689 | B791: =IF(A791="","",IF(INDEX(EXTRATO!$C$2:$C$3000,MATCH($A791,EXTRATO!$A$2:$A$3000,0))="","",INDEX(EXTRATO!$C$2:$C$3000,MATCH($A791,EXTRATO!$A$2:$A$3000,0)))) -> 46216 | C791: =IF(B791="","",MONTH(B791)) -> 7 | D791: ENTRADAS | E791: Resgate do Financiamento (Banco do Nordeste) | F791: 50000 | G791: BIORENAL LTDA (REF. DEPÓSITO DO FINANCIAMENTO) | H791: =IF(A791="","",IF(INDEX(EXTRATO!$F$2:$F$3000,MATCH($A791,EXTRATO!$A$2:$A$3000,0))="","",INDEX(EXTRATO!$F$2:$F$3000,MATCH($A791,EXTRATO!$A$2:$A$3000,0)))) -> ENTRADA | I791: =IF(A791="","",IF(INDEX(EXTRATO!$H$2:$H$3000,MATCH($A791,EXTRATO!$A$2:$A$3000,0))="","",INDEX(EXTRATO!$H$2:$H$3000,MATCH($A791,EXTRATO!$A$2:$A$3000,0)))) -> BIORENAL LTDA | J791: AUTOMÁTICO | K791: =IF(AND(A791="",D791="",E791="",F791=""),"",IF(D791="","SEM CATEGORIA",IF(E791="","SEM SUBCATEGORIA",IF(COUNTIFS(CADASTROS!$L$7:$L$93,D791,CADASTROS!$D$7:$D$93,E791)=0,"INCOMPATÍVEL","OK")))) -> OK
A792: BAN-00690 | B792: =IF(A792="","",IF(INDEX(EXTRATO!$C$2:$C$3000,MATCH($A792,EXTRATO!$A$2:$A$3000,0))="","",INDEX(EXTRATO!$C$2:$C$3000,MATCH($A792,EXTRATO!$A$2:$A$3000,0)))) -> 46216 | C792: =IF(B792="","",MONTH(B792)) -> 7 | D792: DESPESAS ADMINISTRATIVAS | E792: Supermercado | F792: 4320.74 | G792: A C R DA SILVA E CIA (SUPERMERCADO CAMINO - REF. COMPRAS QUINZENAIS - DATAS 09/06 E 23/06) | H792: =IF(A792="","",IF(INDEX(EXTRATO!$F$2:$F$3000,MATCH($A792,EXTRATO!$A$2:$A$3000,0))="","",INDEX(EXTRATO!$F$2:$F$3000,MATCH($A792,EXTRATO!$A$2:$A$3000,0)))) -> SAÍDA | I792: =IF(A792="","",IF(INDEX(EXTRATO!$H$2:$H$3000,MATCH($A792,EXTRATO!$A$2:$A$3000,0))="","",INDEX(EXTRATO!$H$2:$H$3000,MATCH($A792,EXTRATO!$A$2:$A$3000,0)))) -> CAMINO | J792: SUGERIDO | K792: =IF(AND(A792="",D792="",E792="",F792=""),"",IF(D792="","SEM CATEGORIA",IF(E792="","SEM SUBCATEGORIA",IF(COUNTIFS(CADASTROS!$L$7:$L$93,D792,CADASTROS!$D$7:$D$93,E792)=0,"INCOMPATÍVEL","OK")))) -> OK
A793: BAN-00691 | B793: =IF(A793="","",IF(INDEX(EXTRATO!$C$2:$C$3000,MATCH($A793,EXTRATO!$A$2:$A$3000,0))="","",INDEX(EXTRATO!$C$2:$C$3000,MATCH($A793,EXTRATO!$A$2:$A$3000,0)))) -> 46216 | C793: =IF(B793="","",MONTH(B793)) -> 7 | D793: DESPESAS COM MATERIAIS PARA HEMODIÁLISE E DEMAIS CUSTOS | E793: Medicações (Heparina, Taurolock) | F793: 7251.45 | G793: CRISTALIA PRODUTOS (REF. HEPARINAS) 1/3 | H793: =IF(A793="","",IF(INDEX(EXTRATO!$F$2:$F$3000,MATCH($A793,EXTRATO!$A$2:$A$3000,0))="","",INDEX(EXTRATO!$F$2:$F$3000,MATCH($A793,EXTRATO!$A$2:$A$3000,0)))) -> SAÍDA | I793: =IF(A793="","",IF(INDEX(EXTRATO!$H$2:$H$3000,MATCH($A793,EXTRATO!$A$2:$A$3000,0))="","",INDEX(EXTRATO!$H$2:$H$3000,MATCH($A793,EXTRATO!$A$2:$A$3000,0)))) -> CRISTALIA PRODUTOS | J793: SUGERIDO | K793: =IF(AND(A793="",D793="",E793="",F793=""),"",IF(D793="","SEM CATEGORIA",IF(E793="","SEM SUBCATEGORIA",IF(COUNTIFS(CADASTROS!$L$7:$L$93,D793,CADASTROS!$D$7:$D$93,E793)=0,"INCOMPATÍVEL","OK")))) -> OK
A794: BAN-00692 | B794: =IF(A794="","",IF(INDEX(EXTRATO!$C$2:$C$3000,MATCH($A794,EXTRATO!$A$2:$A$3000,0))="","",INDEX(EXTRATO!$C$2:$C$3000,MATCH($A794,EXTRATO!$A$2:$A$3000,0)))) -> 46216 | C794: =IF(B794="","",MONTH(B794)) -> 7 | D794: DESPESAS ADMINISTRATIVAS | E794: Material de Limpeza | F794: 617.5 | G794: BRANDÃO E BRANDÃO (REF. MATERIAL DE LIMPEZA) 1/2) | H794: =IF(A794="","",IF(INDEX(EXTRATO!$F$2:$F$3000,MATCH($A794,EXTRATO!$A$2:$A$3000,0))="","",INDEX(EXTRATO!$F$2:$F$3000,MATCH($A794,EXTRATO!$A$2:$A$3000,0)))) -> SAÍDA | I794: =IF(A794="","",IF(INDEX(EXTRATO!$H$2:$H$3000,MATCH($A794,EXTRATO!$A$2:$A$3000,0))="","",INDEX(EXTRATO!$H$2:$H$3000,MATCH($A794,EXTRATO!$A$2:$A$3000,0)))) -> BRANDÃO & BRANDÃO | J794: SUGERIDO | K794: =IF(AND(A794="",D794="",E794="",F794=""),"",IF(D794="","SEM CATEGORIA",IF(E794="","SEM SUBCATEGORIA",IF(COUNTIFS(CADASTROS!$L$7:$L$93,D794,CADASTROS!$D$7:$D$93,E794)=0,"INCOMPATÍVEL","OK")))) -> OK
A795: BAN-00693 | B795: =IF(A795="","",IF(INDEX(EXTRATO!$C$2:$C$3000,MATCH($A795,EXTRATO!$A$2:$A$3000,0))="","",INDEX(EXTRATO!$C$2:$C$3000,MATCH($A795,EXTRATO!$A$2:$A$3000,0)))) -> 46216 | C795: =IF(B795="","",MONTH(B795)) -> 7 | D795: DESPESAS COM MATERIAIS PARA HEMODIÁLISE E DEMAIS CUSTOS | E795: Agulhas, Seringas, Máscaras, Luvas, Equipo e Med. Div. | F795: 2135.1 | G795: SUPERMÉDICA (REF. MEDICAMENTO E INSUMOS) 1/2 | H795: =IF(A795="","",IF(INDEX(EXTRATO!$F$2:$F$3000,MATCH($A795,EXTRATO!$A$2:$A$3000,0))="","",INDEX(EXTRATO!$F$2:$F$3000,MATCH($A795,EXTRATO!$A$2:$A$3000,0)))) -> SAÍDA | I795: =IF(A795="","",IF(INDEX(EXTRATO!$H$2:$H$3000,MATCH($A795,EXTRATO!$A$2:$A$3000,0))="","",INDEX(EXTRATO!$H$2:$H$3000,MATCH($A795,EXTRATO!$A$2:$A$3000,0)))) -> SUPERMÉDICA | J795: SUGERIDO | K795: =IF(AND(A795="",D795="",E795="",F795=""),"",IF(D795="","SEM CATEGORIA",IF(E795="","SEM SUBCATEGORIA",IF(COUNTIFS(CADASTROS!$L$7:$L$93,D795,CADASTROS!$D$7:$D$93,E795)=0,"INCOMPATÍVEL","OK")))) -> OK
... A908: BAN-00780 | B908: =IF(A908="","",IF(INDEX(EXTRATO!$C$2:$C$3000,MATCH($A908,EXTRATO!$A$2:$A$3000,0))="","",INDEX(EXTRATO!$C$2:$C$3000,MATCH($A908,EXTRATO!$A$2:$A$3000,0)))) -> 46239 | C908: =IF(B908="","",MONTH(B908)) -> 8 | D908: DESPESAS ADMINISTRATIVAS | E908: Contador | F908: 2593 | G908: CASSIANO & CASSINOS CONTABILIDADE | H908: =IF(A908="","",IF(INDEX(EXTRATO!$F$2:$F$3000,MATCH($A908,EXTRATO!$A$2:$A$3000,0))="","",INDEX(EXTRATO!$F$2:$F$3000,MATCH($A908,EXTRATO!$A$2:$A$3000,0)))) -> SAÍDA | I908: =IF(A908="","",IF(INDEX(EXTRATO!$H$2:$H$3000,MATCH($A908,EXTRATO!$A$2:$A$3000,0))="","",INDEX(EXTRATO!$H$2:$H$3000,MATCH($A908,EXTRATO!$A$2:$A$3000,0)))) -> CASSIANO & CASSINOS CONTABILIDADE | J908: SUGERIDO | K908: =IF(AND(A908="",D908="",E908="",F908=""),"",IF(D908="","SEM CATEGORIA",IF(E908="","SEM SUBCATEGORIA",IF(COUNTIFS(CADASTROS!$L$7:$L$93,D908,CADASTROS!$D$7:$D$93,E908)=0,"INCOMPATÍVEL","OK")))) -> OK
A909: BAN-00781 | B909: =IF(A909="","",IF(INDEX(EXTRATO!$C$2:$C$3000,MATCH($A909,EXTRATO!$A$2:$A$3000,0))="","",INDEX(EXTRATO!$C$2:$C$3000,MATCH($A909,EXTRATO!$A$2:$A$3000,0)))) -> 46240 | C909: =IF(B909="","",MONTH(B909)) -> 8 | F909: 61.99 | G909: PIX - REJEITADO | H909: =IF(A909="","",IF(INDEX(EXTRATO!$F$2:$F$3000,MATCH($A909,EXTRATO!$A$2:$A$3000,0))="","",INDEX(EXTRATO!$F$2:$F$3000,MATCH($A909,EXTRATO!$A$2:$A$3000,0)))) -> ENTRADA | I909: =IF(A909="","",IF(INDEX(EXTRATO!$H$2:$H$3000,MATCH($A909,EXTRATO!$A$2:$A$3000,0))="","",INDEX(EXTRATO!$H$2:$H$3000,MATCH($A909,EXTRATO!$A$2:$A$3000,0)))) -> PIX | J909: PENDENTE | K909: =IF(AND(A909="",D909="",E909="",F909=""),"",IF(D909="","SEM CATEGORIA",IF(E909="","SEM SUBCATEGORIA",IF(COUNTIFS(CADASTROS!$L$7:$L$93,D909,CADASTROS!$D$7:$D$93,E909)=0,"INCOMPATÍVEL","OK")))) -> SEM CATEGORIA
A910: BAN-00782 | B910: =IF(A910="","",IF(INDEX(EXTRATO!$C$2:$C$3000,MATCH($A910,EXTRATO!$A$2:$A$3000,0))="","",INDEX(EXTRATO!$C$2:$C$3000,MATCH($A910,EXTRATO!$A$2:$A$3000,0)))) -> 46240 | C910: =IF(B910="","",MONTH(B910)) -> 8 | F910: 61.99 | G910: MARKETPLACE MARKETPLACE MERCADO LIVRE (??????) | H910: =IF(A910="","",IF(INDEX(EXTRATO!$F$2:$F$3000,MATCH($A910,EXTRATO!$A$2:$A$3000,0))="","",INDEX(EXTRATO!$F$2:$F$3000,MATCH($A910,EXTRATO!$A$2:$A$3000,0)))) -> SAÍDA | I910: =IF(A910="","",IF(INDEX(EXTRATO!$H$2:$H$3000,MATCH($A910,EXTRATO!$A$2:$A$3000,0))="","",INDEX(EXTRATO!$H$2:$H$3000,MATCH($A910,EXTRATO!$A$2:$A$3000,0)))) -> MARKETPLACE MERCADO LIVRE | J910: PENDENTE | K910: =IF(AND(A910="",D910="",E910="",F910=""),"",IF(D910="","SEM CATEGORIA",IF(E910="","SEM SUBCATEGORIA",IF(COUNTIFS(CADASTROS!$L$7:$L$93,D910,CADASTROS!$D$7:$D$93,E910)=0,"INCOMPATÍVEL","OK")))) -> SEM CATEGORIA
A911: BAN-00783 | B911: =IF(A911="","",IF(INDEX(EXTRATO!$C$2:$C$3000,MATCH($A911,EXTRATO!$A$2:$A$3000,0))="","",INDEX(EXTRATO!$C$2:$C$3000,MATCH($A911,EXTRATO!$A$2:$A$3000,0)))) -> 46240 | C911: =IF(B911="","",MONTH(B911)) -> 8 | D911: DESPESAS COM MATERIAIS PARA HEMODIÁLISE E DEMAIS CUSTOS | E911: Capilar, Filtros, Agulhas | F911: 3266.25 | G911: NIPRO MEDICAL (REF. AGULHA 16G) - 2/2 | H911: =IF(A911="","",IF(INDEX(EXTRATO!$F$2:$F$3000,MATCH($A911,EXTRATO!$A$2:$A$3000,0))="","",INDEX(EXTRATO!$F$2:$F$3000,MATCH($A911,EXTRATO!$A$2:$A$3000,0)))) -> SAÍDA | I911: =IF(A911="","",IF(INDEX(EXTRATO!$H$2:$H$3000,MATCH($A911,EXTRATO!$A$2:$A$3000,0))="","",INDEX(EXTRATO!$H$2:$H$3000,MATCH($A911,EXTRATO!$A$2:$A$3000,0)))) -> NIPRO | J911: SUGERIDO | K911: =IF(AND(A911="",D911="",E911="",F911=""),"",IF(D911="","SEM CATEGORIA",IF(E911="","SEM SUBCATEGORIA",IF(COUNTIFS(CADASTROS!$L$7:$L$93,D911,CADASTROS!$D$7:$D$93,E911)=0,"INCOMPATÍVEL","OK")))) -> OK
A912: BAN-00784 | B912: =IF(A912="","",IF(INDEX(EXTRATO!$C$2:$C$3000,MATCH($A912,EXTRATO!$A$2:$A$3000,0))="","",INDEX(EXTRATO!$C$2:$C$3000,MATCH($A912,EXTRATO!$A$2:$A$3000,0)))) -> 46240 | C912: =IF(B912="","",MONTH(B912)) -> 8 | D912: DESPESAS COM MATERIAIS PARA HEMODIÁLISE E DEMAIS CUSTOS | E912: Agulhas, Seringas, Máscaras, Luvas, Equipo e Med. Div. | F912: 340 | G912: BIOCOMPANY (REF. CURATIVOS E TAMPA PARA CATETER) 1/2 | H912: =IF(A912="","",IF(INDEX(EXTRATO!$F$2:$F$3000,MATCH($A912,EXTRATO!$A$2:$A$3000,0))="","",INDEX(EXTRATO!$F$2:$F$3000,MATCH($A912,EXTRATO!$A$2:$A$3000,0)))) -> SAÍDA | I912: =IF(A912="","",IF(INDEX(EXTRATO!$H$2:$H$3000,MATCH($A912,EXTRATO!$A$2:$A$3000,0))="","",INDEX(EXTRATO!$H$2:$H$3000,MATCH($A912,EXTRATO!$A$2:$A$3000,0)))) -> BIOCOMPANY | J912: PENDENTE | K912: =IF(AND(A912="",D912="",E912="",F912=""),"",IF(D912="","SEM CATEGORIA",IF(E912="","SEM SUBCATEGORIA",IF(COUNTIFS(CADASTROS!$L$7:$L$93,D912,CADASTROS!$D$7:$D$93,E912)=0,"INCOMPATÍVEL","OK")))) -> OK
A913: BAN-00784 | B913: =IF(A913="","",IF(INDEX(EXTRATO!$C$2:$C$3000,MATCH($A913,EXTRATO!$A$2:$A$3000,0))="","",INDEX(EXTRATO!$C$2:$C$3000,MATCH($A913,EXTRATO!$A$2:$A$3000,0)))) -> 46240 | C913: =IF(B913="","",MONTH(B913)) -> 8 | D913: DESPESAS COM MATERIAIS PARA HEMODIÁLISE E DEMAIS CUSTOS | E913: CDL e Perm-cath | F913: 2220 | G913: BIOCOMPANY (REF. CATETER DE 15CM E 28CM, PERMCATCH 28CM) 1/2 | H913: =IF(A913="","",IF(INDEX(EXTRATO!$F$2:$F$3000,MATCH($A913,EXTRATO!$A$2:$A$3000,0))="","",INDEX(EXTRATO!$F$2:$F$3000,MATCH($A913,EXTRATO!$A$2:$A$3000,0)))) -> SAÍDA | I913: =IF(A913="","",IF(INDEX(EXTRATO!$H$2:$H$3000,MATCH($A913,EXTRATO!$A$2:$A$3000,0))="","",INDEX(EXTRATO!$H$2:$H$3000,MATCH($A913,EXTRATO!$A$2:$A$3000,0)))) -> BIOCOMPANY | J913: PENDENTE | K913: =IF(AND(A913="",D913="",E913="",F913=""),"",IF(D913="","SEM CATEGORIA",IF(E913="","SEM SUBCATEGORIA",IF(COUNTIFS(CADASTROS!$L$7:$L$93,D913,CADASTROS!$D$7:$D$93,E913)=0,"INCOMPATÍVEL","OK")))) -> OK
A914: BAN-00785 | B914: =IF(A914="","",IF(INDEX(EXTRATO!$C$2:$C$3000,MATCH($A914,EXTRATO!$A$2:$A$3000,0))="","",INDEX(EXTRATO!$C$2:$C$3000,MATCH($A914,EXTRATO!$A$2:$A$3000,0)))) -> 46241 | C914: =IF(B914="","",MONTH(B914)) -> 8 | D914: DESPESAS COM SALÁRIOS E BENEFÍCIOS | E914: Folha de Pagamento de Funcionários | F914: 72727.03 | G914: FOLHA DE PAGAMENTO (REF. PAGAMENTO DE SALÁRIO - COMP. 07/2026) | H914: =IF(A914="","",IF(INDEX(EXTRATO!$F$2:$F$3000,MATCH($A914,EXTRATO!$A$2:$A$3000,0))="","",INDEX(EXTRATO!$F$2:$F$3000,MATCH($A914,EXTRATO!$A$2:$A$3000,0)))) -> SAÍDA | I914: =IF(A914="","",IF(INDEX(EXTRATO!$H$2:$H$3000,MATCH($A914,EXTRATO!$A$2:$A$3000,0))="","",INDEX(EXTRATO!$H$2:$H$3000,MATCH($A914,EXTRATO!$A$2:$A$3000,0)))) -> FOLHA DE PAGAMENTO | J914: PENDENTE | K914: =IF(AND(A914="",D914="",E914="",F914=""),"",IF(D914="","SEM CATEGORIA",IF(E914="","SEM SUBCATEGORIA",IF(COUNTIFS(CADASTROS!$L$7:$L$93,D914,CADASTROS!$D$7:$D$93,E914)=0,"INCOMPATÍVEL","OK")))) -> OK
A915: BAN-00786 | B915: =IF(A915="","",IF(INDEX(EXTRATO!$C$2:$C$3000,MATCH($A915,EXTRATO!$A$2:$A$3000,0))="","",INDEX(EXTRATO!$C$2:$C$3000,MATCH($A915,EXTRATO!$A$2:$A$3000,0)))) -> 46241 | C915: =IF(B915="","",MONTH(B915)) -> 8 | D915: AQUISIÇÃO DE BENS E EQUIPAMENTOS | E915: Mobiliário e utensílios duráveis | F915: 219.9 | G915: A POTIGUAR (REF. VENTILADOR PARA COPA) | H915: =IF(A915="","",IF(INDEX(EXTRATO!$F$2:$F$3000,MATCH($A915,EXTRATO!$A$2:$A$3000,0))="","",INDEX(EXTRATO!$F$2:$F$3000,MATCH($A915,EXTRATO!$A$2:$A$3000,0)))) -> SAÍDA | I915: =IF(A915="","",IF(INDEX(EXTRATO!$H$2:$H$3000,MATCH($A915,EXTRATO!$A$2:$A$3000,0))="","",INDEX(EXTRATO!$H$2:$H$3000,MATCH($A915,EXTRATO!$A$2:$A$3000,0)))) -> A POTIGUAR | J915: PENDENTE | K915: =IF(AND(A915="",D915="",E915="",F915=""),"",IF(D915="","SEM CATEGORIA",IF(E915="","SEM SUBCATEGORIA",IF(COUNTIFS(CADASTROS!$L$7:$L$93,D915,CADASTROS!$D$7:$D$93,E915)=0,"INCOMPATÍVEL","OK")))) -> OK
A916: BAN-00787 | B916: =IF(A916="","",IF(INDEX(EXTRATO!$C$2:$C$3000,MATCH($A916,EXTRATO!$A$2:$A$3000,0))="","",INDEX(EXTRATO!$C$2:$C$3000,MATCH($A916,EXTRATO!$A$2:$A$3000,0)))) -> 46241 | C916: =IF(B916="","",MONTH(B916)) -> 8 | D916: DESPESAS ADMINISTRATIVAS | E916: Taxas e Tarifas | F916: 41.63 | G916: TARIFA BANCÁRIA (SALÁRIO CRÉD. CONTA) | H916: =IF(A916="","",IF(INDEX(EXTRATO!$F$2:$F$3000,MATCH($A916,EXTRATO!$A$2:$A$3000,0))="","",INDEX(EXTRATO!$F$2:$F$3000,MATCH($A916,EXTRATO!$A$2:$A$3000,0)))) -> SAÍDA | I916: =IF(A916="","",IF(INDEX(EXTRATO!$H$2:$H$3000,MATCH($A916,EXTRATO!$A$2:$A$3000,0))="","",INDEX(EXTRATO!$H$2:$H$3000,MATCH($A916,EXTRATO!$A$2:$A$3000,0)))) -> TARIFA BANCÁRIA | J916: SUGERIDO | K916: =IF(AND(A916="",D916="",E916="",F916=""),"",IF(D916="","SEM CATEGORIA",IF(E916="","SEM SUBCATEGORIA",IF(COUNTIFS(CADASTROS!$L$7:$L$93,D916,CADASTROS!$D$7:$D$93,E916)=0,"INCOMPATÍVEL","OK")))) -> OK
A917: BAN-00788 | B917: =IF(A917="","",IF(INDEX(EXTRATO!$C$2:$C$3000,MATCH($A917,EXTRATO!$A$2:$A$3000,0))="","",INDEX(EXTRATO!$C$2:$C$3000,MATCH($A917,EXTRATO!$A$2:$A$3000,0)))) -> 46241 | C917: =IF(B917="","",MONTH(B917)) -> 8 | D917: DESPESAS ADMINISTRATIVAS | E917: Material de Limpeza | F917: 1030.94 | G917: RICEK (REF. PAPEL TOALHA, HIGIÊNICO E SACO DE LIXO COMUM) 1/2 | H917: =IF(A917="","",IF(INDEX(EXTRATO!$F$2:$F$3000,MATCH($A917,EXTRATO!$A$2:$A$3000,0))="","",INDEX(EXTRATO!$F$2:$F$3000,MATCH($A917,EXTRATO!$A$2:$A$3000,0)))) -> SAÍDA | I917: =IF(A917="","",IF(INDEX(EXTRATO!$H$2:$H$3000,MATCH($A917,EXTRATO!$A$2:$A$3000,0))="","",INDEX(EXTRATO!$H$2:$H$3000,MATCH($A917,EXTRATO!$A$2:$A$3000,0)))) -> RICEK | J917: PENDENTE | K917: =IF(AND(A917="",D917="",E917="",F917=""),"",IF(D917="","SEM CATEGORIA",IF(E917="","SEM SUBCATEGORIA",IF(COUNTIFS(CADASTROS!$L$7:$L$93,D917,CADASTROS!$D$7:$D$93,E917)=0,"INCOMPATÍVEL","OK")))) -> OK
A918: BAN-00789 | B918: =IF(A918="","",IF(INDEX(EXTRATO!$C$2:$C$3000,MATCH($A918,EXTRATO!$A$2:$A$3000,0))="","",INDEX(EXTRATO!$C$2:$C$3000,MATCH($A918,EXTRATO!$A$2:$A$3000,0)))) -> 46244 | C918: =IF(B918="","",MONTH(B918)) -> 8 | D918: AQUISIÇÃO DE BENS E EQUIPAMENTOS | E918: Financiamento do veículo | F918: 1935.4 | G918: BANCO VOLKSWAGEN (NF - CAVEPEL - REF. PRESTAÇÃO CARRO) 12/48 | H918: =IF(A918="","",IF(INDEX(EXTRATO!$F$2:$F$3000,MATCH($A918,EXTRATO!$A$2:$A$3000,0))="","",INDEX(EXTRATO!$F$2:$F$3000,MATCH($A918,EXTRATO!$A$2:$A$3000,0)))) -> SAÍDA | I918: =IF(A918="","",IF(INDEX(EXTRATO!$H$2:$H$3000,MATCH($A918,EXTRATO!$A$2:$A$3000,0))="","",INDEX(EXTRATO!$H$2:$H$3000,MATCH($A918,EXTRATO!$A$2:$A$3000,0)))) -> BANCO VOLKSWAGEN | J918: SUGERIDO | K918: =IF(AND(A918="",D918="",E918="",F918=""),"",IF(D918="","SEM CATEGORIA",IF(E918="","SEM SUBCATEGORIA",IF(COUNTIFS(CADASTROS!$L$7:$L$93,D918,CADASTROS!$D$7:$D$93,E918)=0,"INCOMPATÍVEL","OK")))) -> OK
A919: BAN-00790 | B919: =IF(A919="","",IF(INDEX(EXTRATO!$C$2:$C$3000,MATCH($A919,EXTRATO!$A$2:$A$3000,0))="","",INDEX(EXTRATO!$C$2:$C$3000,MATCH($A919,EXTRATO!$A$2:$A$3000,0)))) -> 46244 | C919: =IF(B919="","",MONTH(B919)) -> 8 | D919: DESPESAS COM MATERIAIS PARA HEMODIÁLISE E DEMAIS CUSTOS | E919: Medicações (Heparina, Taurolock) | F919: 7251.45 | G919: CRISTALIA PRODUTOS (REF. HEPARINAS) 1/3 | H919: =IF(A919="","",IF(INDEX(EXTRATO!$F$2:$F$3000,MATCH($A919,EXTRATO!$A$2:$A$3000,0))="","",INDEX(EXTRATO!$F$2:$F$3000,MATCH($A919,EXTRATO!$A$2:$A$3000,0)))) -> SAÍDA | I919: =IF(A919="","",IF(INDEX(EXTRATO!$H$2:$H$3000,MATCH($A919,EXTRATO!$A$2:$A$3000,0))="","",INDEX(EXTRATO!$H$2:$H$3000,MATCH($A919,EXTRATO!$A$2:$A$3000,0)))) -> CRISTALIA PRODUTOS | J919: SUGERIDO | K919: =IF(AND(A919="",D919="",E919="",F919=""),"",IF(D919="","SEM CATEGORIA",IF(E919="","SEM SUBCATEGORIA",IF(COUNTIFS(CADASTROS!$L$7:$L$93,D919,CADASTROS!$D$7:$D$93,E919)=0,"INCOMPATÍVEL","OK")))) -> OK
A920: BAN-00791 | B920: =IF(A920="","",IF(INDEX(EXTRATO!$C$2:$C$3000,MATCH($A920,EXTRATO!$A$2:$A$3000,0))="","",INDEX(EXTRATO!$C$2:$C$3000,MATCH($A920,EXTRATO!$A$2:$A$3000,0)))) -> 46244 | C920: =IF(B920="","",MONTH(B920)) -> 8 | D920: DESPESAS COM MATERIAIS PARA HEMODIÁLISE E DEMAIS CUSTOS | E920: Agulhas, Seringas, Máscaras, Luvas, Equipo e Med. Div. | F920: 1909.4 | G920: REMORA HOSPITALAR (REF. MATERIAIS E MEDICAMENTOS) 1/2 | H920: =IF(A920="","",IF(INDEX(EXTRATO!$F$2:$F$3000,MATCH($A920,EXTRATO!$A$2:$A$3000,0))="","",INDEX(EXTRATO!$F$2:$F$3000,MATCH($A920,EXTRATO!$A$2:$A$3000,0)))) -> SAÍDA | I920: =IF(A920="","",IF(INDEX(EXTRATO!$H$2:$H$3000,MATCH($A920,EXTRATO!$A$2:$A$3000,0))="","",INDEX(EXTRATO!$H$2:$H$3000,MATCH($A920,EXTRATO!$A$2:$A$3000,0)))) -> REMORA HOSPITALAR | J920: SUGERIDO | K920: =IF(AND(A920="",D920="",E920="",F920=""),"",IF(D920="","SEM CATEGORIA",IF(E920="","SEM SUBCATEGORIA",IF(COUNTIFS(CADASTROS!$L$7:$L$93,D920,CADASTROS!$D$7:$D$93,E920)=0,"INCOMPATÍVEL","OK")))) -> OK
A921: BAN-00792 | B921: =IF(A921="","",IF(INDEX(EXTRATO!$C$2:$C$3000,MATCH($A921,EXTRATO!$A$2:$A$3000,0))="","",INDEX(EXTRATO!$C$2:$C$3000,MATCH($A921,EXTRATO!$A$2:$A$3000,0)))) -> 46244 | C921: =IF(B921="","",MONTH(B921)) -> 8 | D921: AQUISIÇÃO DE BENS E EQUIPAMENTOS | E921: Aquisição de Máquinas de Hemodiálise | F921: 8208.5 | G921: NIPRO (REF. CAPILAR 21H, AGULHA 16G E FILTRO DE ENDOTOXINA) 1/2 | H921: =IF(A921="","",IF(INDEX(EXTRATO!$F$2:$F$3000,MATCH($A921,EXTRATO!$A$2:$A$3000,0))="","",INDEX(EXTRATO!$F$2:$F$3000,MATCH($A921,EXTRATO!$A$2:$A$3000,0)))) -> SAÍDA | I921: =IF(A921="","",IF(INDEX(EXTRATO!$H$2:$H$3000,MATCH($A921,EXTRATO!$A$2:$A$3000,0))="","",INDEX(EXTRATO!$H$2:$H$3000,MATCH($A921,EXTRATO!$A$2:$A$3000,0)))) -> NIPRO | J921: SUGERIDO | K921: =IF(AND(A921="",D921="",E921="",F921=""),"",IF(D921="","SEM CATEGORIA",IF(E921="","SEM SUBCATEGORIA",IF(COUNTIFS(CADASTROS!$L$7:$L$93,D921,CADASTROS!$D$7:$D$93,E921)=0,"INCOMPATÍVEL","OK")))) -> OK
A922: BAN-00793 | B922: =IF(A922="","",IF(INDEX(EXTRATO!$C$2:$C$3000,MATCH($A922,EXTRATO!$A$2:$A$3000,0))="","",INDEX(EXTRATO!$C$2:$C$3000,MATCH($A922,EXTRATO!$A$2:$A$3000,0)))) -> 46244 | C922: =IF(B922="","",MONTH(B922)) -> 8 | D922: DESPESAS ADMINISTRATIVAS | E922: Suporte Informatica - Hardware, Internet, Sistemas e Câmeras | F922: 149.9 | G922: MARANET TELECOM (REF. INTERNET) | H922: =IF(A922="","",IF(INDEX(EXTRATO!$F$2:$F$3000,MATCH($A922,EXTRATO!$A$2:$A$3000,0))="","",INDEX(EXTRATO!$F$2:$F$3000,MATCH($A922,EXTRATO!$A$2:$A$3000,0)))) -> SAÍDA | I922: =IF(A922="","",IF(INDEX(EXTRATO!$H$2:$H$3000,MATCH($A922,EXTRATO!$A$2:$A$3000,0))="","",INDEX(EXTRATO!$H$2:$H$3000,MATCH($A922,EXTRATO!$A$2:$A$3000,0)))) -> MARANET TELECOM | J922: SUGERIDO | K922: =IF(AND(A922="",D922="",E922="",F922=""),"",IF(D922="","SEM CATEGORIA",IF(E922="","SEM SUBCATEGORIA",IF(COUNTIFS(CADASTROS!$L$7:$L$93,D922,CADASTROS!$D$7:$D$93,E922)=0,"INCOMPATÍVEL","OK")))) -> OK
... A995: BAN-00852 | B995: =IF(A995="","",IF(INDEX(EXTRATO!$C$2:$C$3000,MATCH($A995,EXTRATO!$A$2:$A$3000,0))="","",INDEX(EXTRATO!$C$2:$C$3000,MATCH($A995,EXTRATO!$A$2:$A$3000,0)))) -> 46265 | C995: =IF(B995="","",MONTH(B995)) -> 8 | D995: DESPESAS COM MATERIAIS PARA HEMODIÁLISE E DEMAIS CUSTOS | E995: Agulhas, Seringas, Máscaras, Luvas, Equipo e Med. Div. | F995: 43.5 | G995: FARMACE (REF. DIPIRONA INJETÁVEL) 2/2 | H995: =IF(A995="","",IF(INDEX(EXTRATO!$F$2:$F$3000,MATCH($A995,EXTRATO!$A$2:$A$3000,0))="","",INDEX(EXTRATO!$F$2:$F$3000,MATCH($A995,EXTRATO!$A$2:$A$3000,0)))) -> SAÍDA | I995: =IF(A995="","",IF(INDEX(EXTRATO!$H$2:$H$3000,MATCH($A995,EXTRATO!$A$2:$A$3000,0))="","",INDEX(EXTRATO!$H$2:$H$3000,MATCH($A995,EXTRATO!$A$2:$A$3000,0)))) -> FARMACE | J995: PENDENTE | K995: =IF(AND(A995="",D995="",E995="",F995=""),"",IF(D995="","SEM CATEGORIA",IF(E995="","SEM SUBCATEGORIA",IF(COUNTIFS(CADASTROS!$L$7:$L$93,D995,CADASTROS!$D$7:$D$93,E995)=0,"INCOMPATÍVEL","OK")))) -> OK
...

Sheet PRESTAÇÃO DE CONTAS
A1: PRESTAÇÃO DE CONTAS - BIORENAL 2026
A2: Relatório automático: movimentos de RATEIOS e saldo anterior de EXTRATO.
A3: PERÍODO: | B3: ANO TODO | C3: <- escolha o mês | D3: =IF($B$3="ANO TODO",">=1","="&MATCH($B$3,CADASTROS!$H$7:$H$18,0)) -> >=1
A5: DESCRIÇÃO | B5: VALOR
A6: ENTRADAS | B6: =SUM(B7:B13)-2*B13 -> 5203978.3
A7: (+) Repasse do Estado | B7: =SUMIFS(RATEIOS!$F$2:$F$3142,RATEIOS!$E$2:$E$3142,"Repasse do Estado",RATEIOS!$C$2:$C$3142,$D$3) -> 3822738.8
A8: (+) Repasse Piso Salarial enfermagem | B8: =SUMIFS(RATEIOS!$F$2:$F$3142,RATEIOS!$E$2:$E$3142,"Repasse Piso Salarial enfermagem",RATEIOS!$C$2:$C$3142,$D$3) -> 273853.88
A9: (+) Saldo anterior em Conta Corrente | B9: =IF(OR($B$3="ANO TODO",$B$3=CADASTROS!$H$7),CADASTROS!$B$4,IF(COUNTIFS(EXTRATO!$C$2:$C$3000,">="&DATE(2026,MATCH($B$3,CADASTROS!$H$7:$H$18,0)-1,1),EXTRATO!$C$2:$C$3000,"<"&DATE(2026,MATCH($B$3,CADASTROS!$H$7:$H$18,0),1))=0,"",LOOKUP(2,1/((EXTRATO!$C$2:$C$3000>=DATE(2026,MATCH($B$3,CADASTROS!$H$7:$H$18,0)-1,1))*(EXTRATO!$C$2:$C$3000<DATE(2026,MATCH($B$3,CADASTROS!$H$7:$H$18,0),1))),EXTRATO!$N$2:$N$3000))) -> 0
A10: (+) Transferências dos Sócios | B10: =SUMIFS(RATEIOS!$F$2:$F$3142,RATEIOS!$E$2:$E$3142,"Transferências dos Sócios",RATEIOS!$C$2:$C$3142,$D$3) -> 240100
A11: (+) Resgate do Financiamento (Banco do Nordeste) | B11: =SUMIFS(RATEIOS!$F$2:$F$3142,RATEIOS!$E$2:$E$3142,"Resgate do Financiamento (Banco do Nordeste)",RATEIOS!$C$2:$C$3142,$D$3) -> 690000
A12: (+) Resgate de Aplicações Financeiras (CDI BB) | B12: =SUMIFS(RATEIOS!$F$2:$F$3142,RATEIOS!$E$2:$E$3142,"Resgate de Aplicações Financeiras (CDI BB)",RATEIOS!$C$2:$C$3142,$D$3) -> 677285.67
A13: (-) Aplicações Financeiras | B13: =SUMIFS(RATEIOS!$F$2:$F$3142,RATEIOS!$E$2:$E$3142,"Aplicações Financeiras",RATEIOS!$C$2:$C$3142,$D$3) -> 500000
A15: DESPESAS | B15: =B16+B27+B40+B56+B62+B77+B95+B103+B110+B115+B122 -> 4881177.6
A16: DESPESAS COM IMPOSTOS | B16: =SUM(B17:B25) -> 431307.13
A17: ISS | B17: =SUMIFS(RATEIOS!$F$2:$F$3142,RATEIOS!$D$2:$D$3142,"DESPESAS COM IMPOSTOS",RATEIOS!$E$2:$E$3142,"ISS",RATEIOS!$C$2:$C$3142,$D$3) -> 243030.53
A18: PIS | B18: =SUMIFS(RATEIOS!$F$2:$F$3142,RATEIOS!$D$2:$D$3142,"DESPESAS COM IMPOSTOS",RATEIOS!$E$2:$E$3142,"PIS",RATEIOS!$C$2:$C$3142,$D$3) -> 23381.06
A19: COFINS | B19: =SUMIFS(RATEIOS!$F$2:$F$3142,RATEIOS!$D$2:$D$3142,"DESPESAS COM IMPOSTOS",RATEIOS!$E$2:$E$3142,"COFINS",RATEIOS!$C$2:$C$3142,$D$3) -> 107912.62
A20: DARF - RETENÇÕES (PIS/COFINS/CSLL) | B20: =SUMIFS(RATEIOS!$F$2:$F$3142,RATEIOS!$D$2:$D$3142,"DESPESAS COM IMPOSTOS",RATEIOS!$E$2:$E$3142,"DARF - RETENÇÕES (PIS/COFINS/CSLL)",RATEIOS!$C$2:$C$3142,$D$3) -> 630.11
A21: DARF - RETENÇÕES (IRRF) | B21: =SUMIFS(RATEIOS!$F$2:$F$3142,RATEIOS!$D$2:$D$3142,"DESPESAS COM IMPOSTOS",RATEIOS!$E$2:$E$3142,"DARF - RETENÇÕES (IRRF)",RATEIOS!$C$2:$C$3142,$D$3) -> 203.28
A22: DARF FÉRIAS | B22: =SUMIFS(RATEIOS!$F$2:$F$3142,RATEIOS!$D$2:$D$3142,"DESPESAS COM IMPOSTOS",RATEIOS!$E$2:$E$3142,"DARF FÉRIAS",RATEIOS!$C$2:$C$3142,$D$3) -> 0
A23: CSLL (Trimestral) | B23: =SUMIFS(RATEIOS!$F$2:$F$3142,RATEIOS!$D$2:$D$3142,"DESPESAS COM IMPOSTOS",RATEIOS!$E$2:$E$3142,"CSLL (Trimestral)",RATEIOS!$C$2:$C$3142,$D$3) -> 42456.7
A24: IRPJ (Trimestral) | B24: =SUMIFS(RATEIOS!$F$2:$F$3142,RATEIOS!$D$2:$D$3142,"DESPESAS COM IMPOSTOS",RATEIOS!$E$2:$E$3142,"IRPJ (Trimestral)",RATEIOS!$C$2:$C$3142,$D$3) -> 13692.83
A25: (sem subcategoria definida) | B25: =SUMIFS(RATEIOS!$F$2:$F$3142,RATEIOS!$D$2:$D$3142,"DESPESAS COM IMPOSTOS",RATEIOS!$E$2:$E$3142,"=",RATEIOS!$C$2:$C$3142,$D$3) -> 0
A27: DESPESAS COM SALÁRIOS E BENEFÍCIOS | B27: =SUM(B28:B38) -> 1165696.4
A28: Folha de Pagamento de Funcionários | B28: =SUMIFS(RATEIOS!$F$2:$F$3142,RATEIOS!$D$2:$D$3142,"DESPESAS COM SALÁRIOS E BENEFÍCIOS",RATEIOS!$E$2:$E$3142,"Folha de Pagamento de Funcionários",RATEIOS!$C$2:$C$3142,$D$3) -> 567394.04
A29: Folha de Pagamento (Repasse de piso da Enfermagem) | B29: =SUMIFS(RATEIOS!$F$2:$F$3142,RATEIOS!$D$2:$D$3142,"DESPESAS COM SALÁRIOS E BENEFÍCIOS",RATEIOS!$E$2:$E$3142,"Folha de Pagamento (Repasse de piso da Enfermagem)",RATEIOS!$C$2:$C$3142,$D$3) -> 273853.88
A30: FGTS | B30: =SUMIFS(RATEIOS!$F$2:$F$3142,RATEIOS!$D$2:$D$3142,"DESPESAS COM SALÁRIOS E BENEFÍCIOS",RATEIOS!$E$2:$E$3142,"FGTS",RATEIOS!$C$2:$C$3142,$D$3) -> 61663.83
A31: INSS | B31: =SUMIFS(RATEIOS!$F$2:$F$3142,RATEIOS!$D$2:$D$3142,"DESPESAS COM SALÁRIOS E BENEFÍCIOS",RATEIOS!$E$2:$E$3142,"INSS",RATEIOS!$C$2:$C$3142,$D$3) -> 219575.77
A32: Rescisão Contratual | B32: =SUMIFS(RATEIOS!$F$2:$F$3142,RATEIOS!$D$2:$D$3142,"DESPESAS COM SALÁRIOS E BENEFÍCIOS",RATEIOS!$E$2:$E$3142,"Rescisão Contratual",RATEIOS!$C$2:$C$3142,$D$3) -> 4534.74
A33: Multa Rescisória | B33: =SUMIFS(RATEIOS!$F$2:$F$3142,RATEIOS!$D$2:$D$3142,"DESPESAS COM SALÁRIOS E BENEFÍCIOS",RATEIOS!$E$2:$E$3142,"Multa Rescisória",RATEIOS!$C$2:$C$3142,$D$3) -> 0
A34: Férias de Funcionários | B34: =SUMIFS(RATEIOS!$F$2:$F$3142,RATEIOS!$D$2:$D$3142,"DESPESAS COM SALÁRIOS E BENEFÍCIOS",RATEIOS!$E$2:$E$3142,"Férias de Funcionários",RATEIOS!$C$2:$C$3142,$D$3) -> 5304.95
A35: Pagamento de Extras | B35: =SUMIFS(RATEIOS!$F$2:$F$3142,RATEIOS!$D$2:$D$3142,"DESPESAS COM SALÁRIOS E BENEFÍCIOS",RATEIOS!$E$2:$E$3142,"Pagamento de Extras",RATEIOS!$C$2:$C$3142,$D$3) -> 0
A36: Fornecimento de quentinhas para equipe da Enfermagem | B36: =SUMIFS(RATEIOS!$F$2:$F$3142,RATEIOS!$D$2:$D$3142,"DESPESAS COM SALÁRIOS E BENEFÍCIOS",RATEIOS!$E$2:$E$3142,"Fornecimento de quentinhas para equipe da Enfermagem",RATEIOS!$C$2:$C$3142,$D$3) -> 30537
A37: EPIs e Fardamentos | B37: =SUMIFS(RATEIOS!$F$2:$F$3142,RATEIOS!$D$2:$D$3142,"DESPESAS COM SALÁRIOS E BENEFÍCIOS",RATEIOS!$E$2:$E$3142,"EPIs e Fardamentos",RATEIOS!$C$2:$C$3142,$D$3) -> 2832.16
A38: (sem subcategoria definida) | B38: =SUMIFS(RATEIOS!$F$2:$F$3142,RATEIOS!$D$2:$D$3142,"DESPESAS COM SALÁRIOS E BENEFÍCIOS",RATEIOS!$E$2:$E$3142,"=",RATEIOS!$C$2:$C$3142,$D$3) -> 0
A40: DESPESAS COM PRESTADORES DE SERVIÇOS EM SAÚDE - TERCEIROS | B40: =SUM(B41:B54) -> 361656.21
A41: CasaMater - Confecção Fístula | B41: =SUMIFS(RATEIOS!$F$2:$F$3142,RATEIOS!$D$2:$D$3142,"DESPESAS COM PRESTADORES DE SERVIÇOS EM SAÚDE - TERCEIROS",RATEIOS!$E$2:$E$3142,"CasaMater - Confecção Fístula",RATEIOS!$C$2:$C$3142,$D$3) -> 36200
A42: Exames Laboratorias dos Colaboradores | B42: =SUMIFS(RATEIOS!$F$2:$F$3142,RATEIOS!$D$2:$D$3142,"DESPESAS COM PRESTADORES DE SERVIÇOS EM SAÚDE - TERCEIROS",RATEIOS!$E$2:$E$3142,"Exames Laboratorias dos Colaboradores",RATEIOS!$C$2:$C$3142,$D$3) -> 518.5
A43: Exames Laboratorias dos Pacientes | B43: =SUMIFS(RATEIOS!$F$2:$F$3142,RATEIOS!$D$2:$D$3142,"DESPESAS COM PRESTADORES DE SERVIÇOS EM SAÚDE - TERCEIROS",RATEIOS!$E$2:$E$3142,"Exames Laboratorias dos Pacientes",RATEIOS!$C$2:$C$3142,$D$3) -> 79457.07
A44: Pagamento Cirurgião Vascular - Dr. Renato | B44: =SUMIFS(RATEIOS!$F$2:$F$3142,RATEIOS!$D$2:$D$3142,"DESPESAS COM PRESTADORES DE SERVIÇOS EM SAÚDE - TERCEIROS",RATEIOS!$E$2:$E$3142,"Pagamento Cirurgião Vascular - Dr. Renato",RATEIOS!$C$2:$C$3142,$D$3) -> 8330
A45: Pagamento Cirurgião Vascular - Dr. Wilson | B45: =SUMIFS(RATEIOS!$F$2:$F$3142,RATEIOS!$D$2:$D$3142,"DESPESAS COM PRESTADORES DE SERVIÇOS EM SAÚDE - TERCEIROS",RATEIOS!$E$2:$E$3142,"Pagamento Cirurgião Vascular - Dr. Wilson",RATEIOS!$C$2:$C$3142,$D$3) -> 9800
A46: Pagamento Psicologa - Camilly | B46: =SUMIFS(RATEIOS!$F$2:$F$3142,RATEIOS!$D$2:$D$3142,"DESPESAS COM PRESTADORES DE SERVIÇOS EM SAÚDE - TERCEIROS",RATEIOS!$E$2:$E$3142,"Pagamento Psicologa - Camilly",RATEIOS!$C$2:$C$3142,$D$3) -> 4000
A47: Pagamento Farmaceutica - Gardênia | B47: =SUMIFS(RATEIOS!$F$2:$F$3142,RATEIOS!$D$2:$D$3142,"DESPESAS COM PRESTADORES DE SERVIÇOS EM SAÚDE - TERCEIROS",RATEIOS!$E$2:$E$3142,"Pagamento Farmaceutica - Gardênia",RATEIOS!$C$2:$C$3142,$D$3) -> 16800
A48: Pagamento Nutricionista - Elaine | B48: =SUMIFS(RATEIOS!$F$2:$F$3142,RATEIOS!$D$2:$D$3142,"DESPESAS COM PRESTADORES DE SERVIÇOS EM SAÚDE - TERCEIROS",RATEIOS!$E$2:$E$3142,"Pagamento Nutricionista - Elaine",RATEIOS!$C$2:$C$3142,$D$3) -> 28758.93
A49: Serviço de correção de ficha de sala - Ferronefro | B49: =SUMIFS(RATEIOS!$F$2:$F$3142,RATEIOS!$D$2:$D$3142,"DESPESAS COM PRESTADORES DE SERVIÇOS EM SAÚDE - TERCEIROS",RATEIOS!$E$2:$E$3142,"Serviço de correção de ficha de sala - Ferronefro",RATEIOS!$C$2:$C$3142,$D$3) -> 3200
A50: Serviço de enfermagem - Ferronefro | B50: =SUMIFS(RATEIOS!$F$2:$F$3142,RATEIOS!$D$2:$D$3142,"DESPESAS COM PRESTADORES DE SERVIÇOS EM SAÚDE - TERCEIROS",RATEIOS!$E$2:$E$3142,"Serviço de enfermagem - Ferronefro",RATEIOS!$C$2:$C$3142,$D$3) -> 30291.71
A51: Serviço de RT de enfermagem - Ferronefro | B51: =SUMIFS(RATEIOS!$F$2:$F$3142,RATEIOS!$D$2:$D$3142,"DESPESAS COM PRESTADORES DE SERVIÇOS EM SAÚDE - TERCEIROS",RATEIOS!$E$2:$E$3142,"Serviço de RT de enfermagem - Ferronefro",RATEIOS!$C$2:$C$3142,$D$3) -> 6300
A52: Pagamento de plantão médico - Dr. Lucas | B52: =SUMIFS(RATEIOS!$F$2:$F$3142,RATEIOS!$D$2:$D$3142,"DESPESAS COM PRESTADORES DE SERVIÇOS EM SAÚDE - TERCEIROS",RATEIOS!$E$2:$E$3142,"Pagamento de plantão médico - Dr. Lucas",RATEIOS!$C$2:$C$3142,$D$3) -> 70000
A53: Pagamento de plantão médico - Dr. Hozano | B53: =SUMIFS(RATEIOS!$F$2:$F$3142,RATEIOS!$D$2:$D$3142,"DESPESAS COM PRESTADORES DE SERVIÇOS EM SAÚDE - TERCEIROS",RATEIOS!$E$2:$E$3142,"Pagamento de plantão médico - Dr. Hozano",RATEIOS!$C$2:$C$3142,$D$3) -> 68000
A54: (sem subcategoria definida) | B54: =SUMIFS(RATEIOS!$F$2:$F$3142,RATEIOS!$D$2:$D$3142,"DESPESAS COM PRESTADORES DE SERVIÇOS EM SAÚDE - TERCEIROS",RATEIOS!$E$2:$E$3142,"=",RATEIOS!$C$2:$C$3142,$D$3) -> 0
A56: DESPESAS COM PRESTAÇÃO DE SERVIÇOS - SÓCIOS | B56: =SUM(B57:B60) -> 360089
A57: Plantões Médicos (Sócios) | B57: =SUMIFS(RATEIOS!$F$2:$F$3142,RATEIOS!$D$2:$D$3142,"DESPESAS COM PRESTAÇÃO DE SERVIÇOS - SÓCIOS",RATEIOS!$E$2:$E$3142,"Plantões Médicos (Sócios)",RATEIOS!$C$2:$C$3142,$D$3) -> 345500
A58: Despesas com Administração / PROLABORE | B58: =SUMIFS(RATEIOS!$F$2:$F$3142,RATEIOS!$D$2:$D$3142,"DESPESAS COM PRESTAÇÃO DE SERVIÇOS - SÓCIOS",RATEIOS!$E$2:$E$3142,"Despesas com Administração / PROLABORE",RATEIOS!$C$2:$C$3142,$D$3) -> 9726
A59: Responsabilidade Técnica - Dr. Anderson | B59: =SUMIFS(RATEIOS!$F$2:$F$3142,RATEIOS!$D$2:$D$3142,"DESPESAS COM PRESTAÇÃO DE SERVIÇOS - SÓCIOS",RATEIOS!$E$2:$E$3142,"Responsabilidade Técnica - Dr. Anderson",RATEIOS!$C$2:$C$3142,$D$3) -> 4863
A60: (sem subcategoria definida) | B60: =SUMIFS(RATEIOS!$F$2:$F$3142,RATEIOS!$D$2:$D$3142,"DESPESAS COM PRESTAÇÃO DE SERVIÇOS - SÓCIOS",RATEIOS!$E$2:$E$3142,"=",RATEIOS!$C$2:$C$3142,$D$3) -> 0
A62: DESPESAS COM MATERIAIS PARA HEMODIÁLISE E DEMAIS CUSTOS | B62: =SUM(B63:B75) -> 1175950.7
A63: Agulhas, Seringas, Máscaras, Luvas, Equipo e Med. Div. | B63: =SUMIFS(RATEIOS!$F$2:$F$3142,RATEIOS!$D$2:$D$3142,"DESPESAS COM MATERIAIS PARA HEMODIÁLISE E DEMAIS CUSTOS",RATEIOS!$E$2:$E$3142,"Agulhas, Seringas, Máscaras, Luvas, Equipo e Med. Div.",RATEIOS!$C$2:$C$3142,$D$3) -> 166235.16
A64: Capilar, Filtros, Agulhas | B64: =SUMIFS(RATEIOS!$F$2:$F$3142,RATEIOS!$D$2:$D$3142,"DESPESAS COM MATERIAIS PARA HEMODIÁLISE E DEMAIS CUSTOS",RATEIOS!$E$2:$E$3142,"Capilar, Filtros, Agulhas",RATEIOS!$C$2:$C$3142,$D$3) -> 192763.54
A65: CDL e Perm-cath | B65: =SUMIFS(RATEIOS!$F$2:$F$3142,RATEIOS!$D$2:$D$3142,"DESPESAS COM MATERIAIS PARA HEMODIÁLISE E DEMAIS CUSTOS",RATEIOS!$E$2:$E$3142,"CDL e Perm-cath",RATEIOS!$C$2:$C$3142,$D$3) -> 17370
A66: Linha Arterial e Venosa | B66: =SUMIFS(RATEIOS!$F$2:$F$3142,RATEIOS!$D$2:$D$3142,"DESPESAS COM MATERIAIS PARA HEMODIÁLISE E DEMAIS CUSTOS",RATEIOS!$E$2:$E$3142,"Linha Arterial e Venosa",RATEIOS!$C$2:$C$3142,$D$3) -> 35854.9
A67: Medicações (Heparina, Taurolock) | B67: =SUMIFS(RATEIOS!$F$2:$F$3142,RATEIOS!$D$2:$D$3142,"DESPESAS COM MATERIAIS PARA HEMODIÁLISE E DEMAIS CUSTOS",RATEIOS!$E$2:$E$3142,"Medicações (Heparina, Taurolock)",RATEIOS!$C$2:$C$3142,$D$3) -> 176485.1
A68: Solução e Soro para HD | B68: =SUMIFS(RATEIOS!$F$2:$F$3142,RATEIOS!$D$2:$D$3142,"DESPESAS COM MATERIAIS PARA HEMODIÁLISE E DEMAIS CUSTOS",RATEIOS!$E$2:$E$3142,"Solução e Soro para HD",RATEIOS!$C$2:$C$3142,$D$3) -> 545097.3
A69: Ácido Cítrico | B69: =SUMIFS(RATEIOS!$F$2:$F$3142,RATEIOS!$D$2:$D$3142,"DESPESAS COM MATERIAIS PARA HEMODIÁLISE E DEMAIS CUSTOS",RATEIOS!$E$2:$E$3142,"Ácido Cítrico",RATEIOS!$C$2:$C$3142,$D$3) -> 3900
A70: Peroxide | B70: =SUMIFS(RATEIOS!$F$2:$F$3142,RATEIOS!$D$2:$D$3142,"DESPESAS COM MATERIAIS PARA HEMODIÁLISE E DEMAIS CUSTOS",RATEIOS!$E$2:$E$3142,"Peroxide",RATEIOS!$C$2:$C$3142,$D$3) -> 20412
A71: Hipoclorito | B71: =SUMIFS(RATEIOS!$F$2:$F$3142,RATEIOS!$D$2:$D$3142,"DESPESAS COM MATERIAIS PARA HEMODIÁLISE E DEMAIS CUSTOS",RATEIOS!$E$2:$E$3142,"Hipoclorito",RATEIOS!$C$2:$C$3142,$D$3) -> 2745.16
A72: Oxigênio | B72: =SUMIFS(RATEIOS!$F$2:$F$3142,RATEIOS!$D$2:$D$3142,"DESPESAS COM MATERIAIS PARA HEMODIÁLISE E DEMAIS CUSTOS",RATEIOS!$E$2:$E$3142,"Oxigênio",RATEIOS!$C$2:$C$3142,$D$3) -> 690
A73: Solução para Desinfecção Poltronas - BELL FOAM | B73: =SUMIFS(RATEIOS!$F$2:$F$3142,RATEIOS!$D$2:$D$3142,"DESPESAS COM MATERIAIS PARA HEMODIÁLISE E DEMAIS CUSTOS",RATEIOS!$E$2:$E$3142,"Solução para Desinfecção Poltronas - BELL FOAM",RATEIOS!$C$2:$C$3142,$D$3) -> 1680
A74: Qualiagua - Analise Água | B74: =SUMIFS(RATEIOS!$F$2:$F$3142,RATEIOS!$D$2:$D$3142,"DESPESAS COM MATERIAIS PARA HEMODIÁLISE E DEMAIS CUSTOS",RATEIOS!$E$2:$E$3142,"Qualiagua - Analise Água",RATEIOS!$C$2:$C$3142,$D$3) -> 12717.5
A75: (sem subcategoria definida) | B75: =SUMIFS(RATEIOS!$F$2:$F$3142,RATEIOS!$D$2:$D$3142,"DESPESAS COM MATERIAIS PARA HEMODIÁLISE E DEMAIS CUSTOS",RATEIOS!$E$2:$E$3142,"=",RATEIOS!$C$2:$C$3142,$D$3) -> 0
A77: DESPESAS ADMINISTRATIVAS | B77: =SUM(B78:B94) -> 448927.08
A78: Assessoria Administrativa | B78: =SUMIFS(RATEIOS!$F$2:$F$3142,RATEIOS!$D$2:$D$3142,"DESPESAS ADMINISTRATIVAS",RATEIOS!$E$2:$E$3142,"Assessoria Administrativa",RATEIOS!$C$2:$C$3142,$D$3) -> 49400
A79: Contador | B79: =SUMIFS(RATEIOS!$F$2:$F$3142,RATEIOS!$D$2:$D$3142,"DESPESAS ADMINISTRATIVAS",RATEIOS!$E$2:$E$3142,"Contador",RATEIOS!$C$2:$C$3142,$D$3) -> 23699
A80: Energia Elétrica (Clínica + Casa de Apoio) | B80: =SUMIFS(RATEIOS!$F$2:$F$3142,RATEIOS!$D$2:$D$3142,"DESPESAS ADMINISTRATIVAS",RATEIOS!$E$2:$E$3142,"Energia Elétrica (Clínica + Casa de Apoio)",RATEIOS!$C$2:$C$3142,$D$3) -> 184797.62
A81: Aluguel casa de apoio | B81: =SUMIFS(RATEIOS!$F$2:$F$3142,RATEIOS!$D$2:$D$3142,"DESPESAS ADMINISTRATIVAS",RATEIOS!$E$2:$E$3142,"Aluguel casa de apoio",RATEIOS!$C$2:$C$3142,$D$3) -> 400
A82: Coleta de Lixo | B82: =SUMIFS(RATEIOS!$F$2:$F$3142,RATEIOS!$D$2:$D$3142,"DESPESAS ADMINISTRATIVAS",RATEIOS!$E$2:$E$3142,"Coleta de Lixo",RATEIOS!$C$2:$C$3142,$D$3) -> 12869.32
A83: Despesas com Gráfica | B83: =SUMIFS(RATEIOS!$F$2:$F$3142,RATEIOS!$D$2:$D$3142,"DESPESAS ADMINISTRATIVAS",RATEIOS!$E$2:$E$3142,"Despesas com Gráfica",RATEIOS!$C$2:$C$3142,$D$3) -> 160
A84: Despesas com viagens | B84: =SUMIFS(RATEIOS!$F$2:$F$3142,RATEIOS!$D$2:$D$3142,"DESPESAS ADMINISTRATIVAS",RATEIOS!$E$2:$E$3142,"Despesas com viagens",RATEIOS!$C$2:$C$3142,$D$3) -> 222.36
A85: Despesas com Cartório | B85: =SUMIFS(RATEIOS!$F$2:$F$3142,RATEIOS!$D$2:$D$3142,"DESPESAS ADMINISTRATIVAS",RATEIOS!$E$2:$E$3142,"Despesas com Cartório",RATEIOS!$C$2:$C$3142,$D$3) -> 10670.12
A86: Material de Limpeza | B86: =SUMIFS(RATEIOS!$F$2:$F$3142,RATEIOS!$D$2:$D$3142,"DESPESAS ADMINISTRATIVAS",RATEIOS!$E$2:$E$3142,"Material de Limpeza",RATEIOS!$C$2:$C$3142,$D$3) -> 18331.99
A87: Gás de cozinha para copa | B87: =SUMIFS(RATEIOS!$F$2:$F$3142,RATEIOS!$D$2:$D$3142,"DESPESAS ADMINISTRATIVAS",RATEIOS!$E$2:$E$3142,"Gás de cozinha para copa",RATEIOS!$C$2:$C$3142,$D$3) -> 805
A88: Materiais de Construção, Elétrico e de Escritório | B88: =SUMIFS(RATEIOS!$F$2:$F$3142,RATEIOS!$D$2:$D$3142,"DESPESAS ADMINISTRATIVAS",RATEIOS!$E$2:$E$3142,"Materiais de Construção, Elétrico e de Escritório",RATEIOS!$C$2:$C$3142,$D$3) -> 2476.27
A89: Panificadora | B89: =SUMIFS(RATEIOS!$F$2:$F$3142,RATEIOS!$D$2:$D$3142,"DESPESAS ADMINISTRATIVAS",RATEIOS!$E$2:$E$3142,"Panificadora",RATEIOS!$C$2:$C$3142,$D$3) -> 15690
A90: Supermercado | B90: =SUMIFS(RATEIOS!$F$2:$F$3142,RATEIOS!$D$2:$D$3142,"DESPESAS ADMINISTRATIVAS",RATEIOS!$E$2:$E$3142,"Supermercado",RATEIOS!$C$2:$C$3142,$D$3) -> 42403.28
A91: Suporte Informatica - Hardware, Internet, Sistemas e Câmeras | B91: =SUMIFS(RATEIOS!$F$2:$F$3142,RATEIOS!$D$2:$D$3142,"DESPESAS ADMINISTRATIVAS",RATEIOS!$E$2:$E$3142,"Suporte Informatica - Hardware, Internet, Sistemas e Câmeras",RATEIOS!$C$2:$C$3142,$D$3) -> 28858.31
A92: Taxas e Tarifas | B92: =SUMIFS(RATEIOS!$F$2:$F$3142,RATEIOS!$D$2:$D$3142,"DESPESAS ADMINISTRATIVAS",RATEIOS!$E$2:$E$3142,"Taxas e Tarifas",RATEIOS!$C$2:$C$3142,$D$3) -> 56643.81
A93: Treinamentos e Capacitação | B93: =SUMIFS(RATEIOS!$F$2:$F$3142,RATEIOS!$D$2:$D$3142,"DESPESAS ADMINISTRATIVAS",RATEIOS!$E$2:$E$3142,"Treinamentos e Capacitação",RATEIOS!$C$2:$C$3142,$D$3) -> 1500
A94: (sem subcategoria definida) | B94: =SUMIFS(RATEIOS!$F$2:$F$3142,RATEIOS!$D$2:$D$3142,"DESPESAS ADMINISTRATIVAS",RATEIOS!$E$2:$E$3142,"=",RATEIOS!$C$2:$C$3142,$D$3) -> 0
A95: LOGÍSTICA E FROTA | B95: =SUM(B96:B101) -> 21407.06
A96: Combustível (Gasolina) | B96: =SUMIFS(RATEIOS!$F$2:$F$3142,RATEIOS!$D$2:$D$3142,"LOGÍSTICA E FROTA",RATEIOS!$E$2:$E$3142,"Combustível (Gasolina)",RATEIOS!$C$2:$C$3142,$D$3) -> 5150.11
A97: Frete com mercadorias | B97: =SUMIFS(RATEIOS!$F$2:$F$3142,RATEIOS!$D$2:$D$3142,"LOGÍSTICA E FROTA",RATEIOS!$E$2:$E$3142,"Frete com mercadorias",RATEIOS!$C$2:$C$3142,$D$3) -> 4001.5
A98: Manutenção de Veículo | B98: =SUMIFS(RATEIOS!$F$2:$F$3142,RATEIOS!$D$2:$D$3142,"LOGÍSTICA E FROTA",RATEIOS!$E$2:$E$3142,"Manutenção de Veículo",RATEIOS!$C$2:$C$3142,$D$3) -> 4849.45
A99: Transporte de pacientes e viagens para HTI | B99: =SUMIFS(RATEIOS!$F$2:$F$3142,RATEIOS!$D$2:$D$3142,"LOGÍSTICA E FROTA",RATEIOS!$E$2:$E$3142,"Transporte de pacientes e viagens para HTI",RATEIOS!$C$2:$C$3142,$D$3) -> 7406
A100: IPVA / Licenciamento e Multas | B100: =SUMIFS(RATEIOS!$F$2:$F$3142,RATEIOS!$D$2:$D$3142,"LOGÍSTICA E FROTA",RATEIOS!$E$2:$E$3142,"IPVA / Licenciamento e Multas",RATEIOS!$C$2:$C$3142,$D$3) -> 0
A101: (sem subcategoria definida) | B101: =SUMIFS(RATEIOS!$F$2:$F$3142,RATEIOS!$D$2:$D$3142,"LOGÍSTICA E FROTA",RATEIOS!$E$2:$E$3142,"=",RATEIOS!$C$2:$C$3142,$D$3) -> 0
A103: MANUTENÇÃO E INFRAESTRUTURA | B103: =SUM(B104:B108) -> 59054.39
A104: Manutenção - Máquinas HD, Gerador, Osmose | B104: =SUMIFS(RATEIOS!$F$2:$F$3142,RATEIOS!$D$2:$D$3142,"MANUTENÇÃO E INFRAESTRUTURA",RATEIOS!$E$2:$E$3142,"Manutenção - Máquinas HD, Gerador, Osmose",RATEIOS!$C$2:$C$3142,$D$3) -> 49761.89
A105: Manutenção - Ar Condicionados | B105: =SUMIFS(RATEIOS!$F$2:$F$3142,RATEIOS!$D$2:$D$3142,"MANUTENÇÃO E INFRAESTRUTURA",RATEIOS!$E$2:$E$3142,"Manutenção - Ar Condicionados",RATEIOS!$C$2:$C$3142,$D$3) -> 3300
A106: Manutenção Predial (Reformas e Reparos) | B106: =SUMIFS(RATEIOS!$F$2:$F$3142,RATEIOS!$D$2:$D$3142,"MANUTENÇÃO E INFRAESTRUTURA",RATEIOS!$E$2:$E$3142,"Manutenção Predial (Reformas e Reparos)",RATEIOS!$C$2:$C$3142,$D$3) -> 5213.56
A107: Óleo diesel para gerador | B107: =SUMIFS(RATEIOS!$F$2:$F$3142,RATEIOS!$D$2:$D$3142,"MANUTENÇÃO E INFRAESTRUTURA",RATEIOS!$E$2:$E$3142,"Óleo diesel para gerador",RATEIOS!$C$2:$C$3142,$D$3) -> 778.94
A108: (sem subcategoria definida) | B108: =SUMIFS(RATEIOS!$F$2:$F$3142,RATEIOS!$D$2:$D$3142,"MANUTENÇÃO E INFRAESTRUTURA",RATEIOS!$E$2:$E$3142,"=",RATEIOS!$C$2:$C$3142,$D$3) -> 0
...

Sheet ANÁLISES
A1: ANÁLISES FINANCEIRAS - 2026
A2: Tudo calculado a partir da aba RATEIOS. Nenhum lançamento manual.
A4: 1. CATEGORIA POR MÊS
A5: CATEGORIA | B5: Janeiro | C5: Fevereiro | D5: Março | E5: Abril | F5: Maio | G5: Junho | H5: Julho | I5: Agosto | J5: Setembro | K5: Outubro | L5: Novembro | M5: Dezembro | N5: TOTAL
A6: ENTRADAS | B6: =SUMIFS(RATEIOS!$F$2:$F$3142,RATEIOS!$D$2:$D$3142,$A6,RATEIOS!$C$2:$C$3142,1) -> 458967.82 | C6: =SUMIFS(RATEIOS!$F$2:$F$3142,RATEIOS!$D$2:$D$3142,$A6,RATEIOS!$C$2:$C$3142,2) -> 279832.99 | D6: =SUMIFS(RATEIOS!$F$2:$F$3142,RATEIOS!$D$2:$D$3142,$A6,RATEIOS!$C$2:$C$3142,3) -> 1152298.1 | E6: =SUMIFS(RATEIOS!$F$2:$F$3142,RATEIOS!$D$2:$D$3142,$A6,RATEIOS!$C$2:$C$3142,4) -> 32760.61 | F6: =SUMIFS(RATEIOS!$F$2:$F$3142,RATEIOS!$D$2:$D$3142,$A6,RATEIOS!$C$2:$C$3142,5) -> 821934.58 | G6: =SUMIFS(RATEIOS!$F$2:$F$3142,RATEIOS!$D$2:$D$3142,$A6,RATEIOS!$C$2:$C$3142,6) -> 752376.89 | H6: =SUMIFS(RATEIOS!$F$2:$F$3142,RATEIOS!$D$2:$D$3142,$A6,RATEIOS!$C$2:$C$3142,7) -> 936010.56 | I6: =SUMIFS(RATEIOS!$F$2:$F$3142,RATEIOS!$D$2:$D$3142,$A6,RATEIOS!$C$2:$C$3142,8) -> 1769796.8 | J6: =SUMIFS(RATEIOS!$F$2:$F$3142,RATEIOS!$D$2:$D$3142,$A6,RATEIOS!$C$2:$C$3142,9) -> 0 | K6: =SUMIFS(RATEIOS!$F$2:$F$3142,RATEIOS!$D$2:$D$3142,$A6,RATEIOS!$C$2:$C$3142,10) -> 0 | L6: =SUMIFS(RATEIOS!$F$2:$F$3142,RATEIOS!$D$2:$D$3142,$A6,RATEIOS!$C$2:$C$3142,11) -> 0 | M6: =SUMIFS(RATEIOS!$F$2:$F$3142,RATEIOS!$D$2:$D$3142,$A6,RATEIOS!$C$2:$C$3142,12) -> 0 | N6: =SUM(B6:M6) -> 6203978.3
A7: DESPESAS COM IMPOSTOS | B7: =SUMIFS(RATEIOS!$F$2:$F$3142,RATEIOS!$D$2:$D$3142,$A7,RATEIOS!$C$2:$C$3142,1) -> 112505.43 | C7: =SUMIFS(RATEIOS!$F$2:$F$3142,RATEIOS!$D$2:$D$3142,$A7,RATEIOS!$C$2:$C$3142,2) -> 167.53 | D7: =SUMIFS(RATEIOS!$F$2:$F$3142,RATEIOS!$D$2:$D$3142,$A7,RATEIOS!$C$2:$C$3142,3) -> 26586.39 | E7: =SUMIFS(RATEIOS!$F$2:$F$3142,RATEIOS!$D$2:$D$3142,$A7,RATEIOS!$C$2:$C$3142,4) -> 77886.53 | F7: =SUMIFS(RATEIOS!$F$2:$F$3142,RATEIOS!$D$2:$D$3142,$A7,RATEIOS!$C$2:$C$3142,5) -> 22633.43 | G7: =SUMIFS(RATEIOS!$F$2:$F$3142,RATEIOS!$D$2:$D$3142,$A7,RATEIOS!$C$2:$C$3142,6) -> 43144.35 | H7: =SUMIFS(RATEIOS!$F$2:$F$3142,RATEIOS!$D$2:$D$3142,$A7,RATEIOS!$C$2:$C$3142,7) -> 63692.84 | I7: =SUMIFS(RATEIOS!$F$2:$F$3142,RATEIOS!$D$2:$D$3142,$A7,RATEIOS!$C$2:$C$3142,8) -> 53612.67 | J7: =SUMIFS(RATEIOS!$F$2:$F$3142,RATEIOS!$D$2:$D$3142,$A7,RATEIOS!$C$2:$C$3142,9) -> 31077.96 | K7: =SUMIFS(RATEIOS!$F$2:$F$3142,RATEIOS!$D$2:$D$3142,$A7,RATEIOS!$C$2:$C$3142,10) -> 0 | L7: =SUMIFS(RATEIOS!$F$2:$F$3142,RATEIOS!$D$2:$D$3142,$A7,RATEIOS!$C$2:$C$3142,11) -> 0 | M7: =SUMIFS(RATEIOS!$F$2:$F$3142,RATEIOS!$D$2:$D$3142,$A7,RATEIOS!$C$2:$C$3142,12) -> 0 | N7: =SUM(B7:M7) -> 431307.13
A8: DESPESAS COM SALÁRIOS E BENEFÍCIOS | B8: =SUMIFS(RATEIOS!$F$2:$F$3142,RATEIOS!$D$2:$D$3142,$A8,RATEIOS!$C$2:$C$3142,1) -> 112752.58 | C8: =SUMIFS(RATEIOS!$F$2:$F$3142,RATEIOS!$D$2:$D$3142,$A8,RATEIOS!$C$2:$C$3142,2) -> 136934.05 | D8: =SUMIFS(RATEIOS!$F$2:$F$3142,RATEIOS!$D$2:$D$3142,$A8,RATEIOS!$C$2:$C$3142,3) -> 141460.62 | E8: =SUMIFS(RATEIOS!$F$2:$F$3142,RATEIOS!$D$2:$D$3142,$A8,RATEIOS!$C$2:$C$3142,4) -> 145003.09 | F8: =SUMIFS(RATEIOS!$F$2:$F$3142,RATEIOS!$D$2:$D$3142,$A8,RATEIOS!$C$2:$C$3142,5) -> 157262.82 | G8: =SUMIFS(RATEIOS!$F$2:$F$3142,RATEIOS!$D$2:$D$3142,$A8,RATEIOS!$C$2:$C$3142,6) -> 155790.71 | H8: =SUMIFS(RATEIOS!$F$2:$F$3142,RATEIOS!$D$2:$D$3142,$A8,RATEIOS!$C$2:$C$3142,7) -> 153178.18 | I8: =SUMIFS(RATEIOS!$F$2:$F$3142,RATEIOS!$D$2:$D$3142,$A8,RATEIOS!$C$2:$C$3142,8) -> 160754.32 | J8: =SUMIFS(RATEIOS!$F$2:$F$3142,RATEIOS!$D$2:$D$3142,$A8,RATEIOS!$C$2:$C$3142,9) -> 2560 | K8: =SUMIFS(RATEIOS!$F$2:$F$3142,RATEIOS!$D$2:$D$3142,$A8,RATEIOS!$C$2:$C$3142,10) -> 0 | L8: =SUMIFS(RATEIOS!$F$2:$F$3142,RATEIOS!$D$2:$D$3142,$A8,RATEIOS!$C$2:$C$3142,11) -> 0 | M8: =SUMIFS(RATEIOS!$F$2:$F$3142,RATEIOS!$D$2:$D$3142,$A8,RATEIOS!$C$2:$C$3142,12) -> 0 | N8: =SUM(B8:M8) -> 1165696.4
A9: DESPESAS COM PRESTADORES DE SERVIÇOS EM SAÚDE - TERCEIROS | B9: =SUMIFS(RATEIOS!$F$2:$F$3142,RATEIOS!$D$2:$D$3142,$A9,RATEIOS!$C$2:$C$3142,1) -> 12906.33 | C9: =SUMIFS(RATEIOS!$F$2:$F$3142,RATEIOS!$D$2:$D$3142,$A9,RATEIOS!$C$2:$C$3142,2) -> 0 | D9: =SUMIFS(RATEIOS!$F$2:$F$3142,RATEIOS!$D$2:$D$3142,$A9,RATEIOS!$C$2:$C$3142,3) -> 80696.85 | E9: =SUMIFS(RATEIOS!$F$2:$F$3142,RATEIOS!$D$2:$D$3142,$A9,RATEIOS!$C$2:$C$3142,4) -> 9600 | F9: =SUMIFS(RATEIOS!$F$2:$F$3142,RATEIOS!$D$2:$D$3142,$A9,RATEIOS!$C$2:$C$3142,5) -> 90002.06 | G9: =SUMIFS(RATEIOS!$F$2:$F$3142,RATEIOS!$D$2:$D$3142,$A9,RATEIOS!$C$2:$C$3142,6) -> 55015.76 | H9: =SUMIFS(RATEIOS!$F$2:$F$3142,RATEIOS!$D$2:$D$3142,$A9,RATEIOS!$C$2:$C$3142,7) -> 13206.33 | I9: =SUMIFS(RATEIOS!$F$2:$F$3142,RATEIOS!$D$2:$D$3142,$A9,RATEIOS!$C$2:$C$3142,8) -> 57888.88 | J9: =SUMIFS(RATEIOS!$F$2:$F$3142,RATEIOS!$D$2:$D$3142,$A9,RATEIOS!$C$2:$C$3142,9) -> 42340 | K9: =SUMIFS(RATEIOS!$F$2:$F$3142,RATEIOS!$D$2:$D$3142,$A9,RATEIOS!$C$2:$C$3142,10) -> 0 | L9: =SUMIFS(RATEIOS!$F$2:$F$3142,RATEIOS!$D$2:$D$3142,$A9,RATEIOS!$C$2:$C$3142,11) -> 0 | M9: =SUMIFS(RATEIOS!$F$2:$F$3142,RATEIOS!$D$2:$D$3142,$A9,RATEIOS!$C$2:$C$3142,12) -> 0 | N9: =SUM(B9:M9) -> 361656.21
A10: DESPESAS COM PRESTAÇÃO DE SERVIÇOS - SÓCIOS | B10: =SUMIFS(RATEIOS!$F$2:$F$3142,RATEIOS!$D$2:$D$3142,$A10,RATEIOS!$C$2:$C$3142,1) -> 0 | C10: =SUMIFS(RATEIOS!$F$2:$F$3142,RATEIOS!$D$2:$D$3142,$A10,RATEIOS!$C$2:$C$3142,2) -> 0 | D10: =SUMIFS(RATEIOS!$F$2:$F$3142,RATEIOS!$D$2:$D$3142,$A10,RATEIOS!$C$2:$C$3142,3) -> 100000 | E10: =SUMIFS(RATEIOS!$F$2:$F$3142,RATEIOS!$D$2:$D$3142,$A10,RATEIOS!$C$2:$C$3142,4) -> 0 | F10: =SUMIFS(RATEIOS!$F$2:$F$3142,RATEIOS!$D$2:$D$3142,$A10,RATEIOS!$C$2:$C$3142,5) -> 80000 | G10: =SUMIFS(RATEIOS!$F$2:$F$3142,RATEIOS!$D$2:$D$3142,$A10,RATEIOS!$C$2:$C$3142,6) -> 44863 | H10: =SUMIFS(RATEIOS!$F$2:$F$3142,RATEIOS!$D$2:$D$3142,$A10,RATEIOS!$C$2:$C$3142,7) -> 0 | I10: =SUMIFS(RATEIOS!$F$2:$F$3142,RATEIOS!$D$2:$D$3142,$A10,RATEIOS!$C$2:$C$3142,8) -> 87226 | J10: =SUMIFS(RATEIOS!$F$2:$F$3142,RATEIOS!$D$2:$D$3142,$A10,RATEIOS!$C$2:$C$3142,9) -> 48000 | K10: =SUMIFS(RATEIOS!$F$2:$F$3142,RATEIOS!$D$2:$D$3142,$A10,RATEIOS!$C$2:$C$3142,10) -> 0 | L10: =SUMIFS(RATEIOS!$F$2:$F$3142,RATEIOS!$D$2:$D$3142,$A10,RATEIOS!$C$2:$C$3142,11) -> 0 | M10: =SUMIFS(RATEIOS!$F$2:$F$3142,RATEIOS!$D$2:$D$3142,$A10,RATEIOS!$C$2:$C$3142,12) -> 0 | N10: =SUM(B10:M10) -> 360089
